Workbook

Sheet MUEBLES
A1: Cantidad | B1: ID Módulo | C1: Mueble | D1: Precio Unit. Blanco | E1: Precio Unit. Maderado
B2: ALA-RIN-656832 | C2: Alacena Rinconera 650 x 680 x 320 mm | D2: 2692.08 | E2: 3321.8658
B3: ALA-1PU-306832 | C3: Alacena 1 Puerta 300 x 680 x 320 mm | D3: 1609.2284 | E3: 2016.3004
B4: ALA-1PU-406832 | C4: Alacena 1 Puerta 400 x 680 x 320 mm | D4: 1855.1811 | E4: 2319.5009
B5: ALA-1PU-506832 | C5: Alacena 1 Puerta 500 x 680 x 320 mm | D5: 2106.0299 | E5: 2613.6642
B6: ALA-1PU-606832 | C6: Alacena 1 Puerta 600 x 680 x 320 mm | D6: 2356.8786 | E6: 2907.8275
B7: ALA-2PU-706832 | C7: Alacena 2 Puertas 700 x 680 x 320 mm | D7: 2932.4086 | E7: 3462.672
B8: ALA-2PU-806832 | C8: Alacena 2 Puertas 800 x 680 x 320 mm | D8: 3183.2573 | E8: 3756.8353
B9: ALA-2PU-906832 | C9: Alacena 2 Puertas 900 x 680 x 320 mm | D9: 3432.8975 | E9: 4049.7901
B10: ALA-BAS-503432 | C10: Alacena Basculante 500 x 340 x 320 mm | D10: ='📊 Resumen y Cotización'!E21 -> 2603.8228 | E10: ='📊 Resumen y Cotización'!H21 -> 3390.6832
B11: ALA-BAS-603432 | C11: Alacena Basculante 600 x 340 x 320 mm | D11: 1623.7291 | E11: 2015.9109
B12: ALA-BAS-703432 | C12: Alacena Basculante 700 x 340 x 320 mm | D12: 1771.5051 | E12: 2190.544
B13: ALA-BAS-803432 | C13: Alacena Basculante 800 x 340 x 320 mm | D13: 1919.281 | E13: 2365.1771
B14: ALA-NIC-276832 | C14: Alacena Nicho Abierto 270 x 680 x 320 mm | D14: 1332.2447 | E14: 1496.2447
B15: ALA-MIC-503432 | C15: Alacena Nicho Microondas 500 x 340 x 320 mm | D15: ='📊 Resumen y Cotización'!E26 -> 2121.3042 | E15: ='📊 Resumen y Cotización'!H26 -> 2389.3042
B16: ALA-MIC-603432 | C16: Alacena Nicho Microondas 600 x 340 x 320 mm | D16: 1231.2649 | E16: 1395.2649
B17: GAB-RIN-1057258 | C17: Gabinete Rinconero 1050 x 720 x 580 mm | D17: 4504.9847 | E17: 5557.6467
B18: GAB-1PU-307258 | C18: Gabinete 1 Puerta 300 x 720 x 580 mm | D18: 2417.6515 | E18: 2991.311
B19: GAB-1PU-407258 | C19: Gabinete 1 Puerta 400 x 720 x 580 mm | D19: 2712.0903 | E19: 3338.7819
B20: GAB-1PU-507258 | C20: Gabinete 1 Puerta 500 x 720 x 580 mm | D20: 3006.5291 | E20: 3686.2528
B21: GAB-1PU-607258 | C21: Gabinete 1 Puerta 600 x 720 x 580 mm | D21: 3302.8639 | E21: 4036.2517
B22: GAB-2PU-707258 | C22: Gabinete 2 Puertas 700 x 720 x 580 mm | D22: 3931.0708 | E22: 4655.7147
B23: GAB-2PU-807258 | C23: Gabinete 2 Puertas 800 x 720 x 580 mm | D23: 4232.7096 | E23: 5012.7856
B24: GAB-2PU-907258 | C24: Gabinete 2 Puertas 900 x 720 x 580 mm | D24: 4534.3484 | E24: 5369.8565
B25: GAB-3CA-407258 | C25: Gabinete 3 Cajones 400 x 720 x 580 mm | D25: 5346.4467 | E25: 6269.8763
B26: GAB-3CA-507258 | C26: Gabinete 3 Cajones 500 x 720 x 580 mm | D26: 5818.4021 | E26: 6840.7689
B27: GAB-3CA-607258 | C27: Gabinete 3 Cajones 600 x 720 x 580 mm | D27: 6290.3575 | E27: 7411.6615
B28: GAB-MIC-603658 | C28: Gabinete Nicho Microondas 600 x 360 x 580 mm | D28: ='📊 Resumen y Cotización'!E39 -> 3448.9284 | E28: ='📊 Resumen y Cotización'!H39 -> 3716.9284
B29: GAB-1CA-603658 | C29: Gabinete 1 Cajon 600 x 360 x 580 mm | D29: ='📊 Resumen y Cotización'!E40 -> 5590.5653 | E29: ='📊 Resumen y Cotización'!H40 -> 7212.7094
B30: GAB-NIC-207258 | C30: Gabinete Nicho 200 x 720 x 580 mm | D30: 2105.7105 | E30: 2162.6226
B31: GAB-NIC-TOA-207258 | C31: Gabinete Nicho Toallero 200 x 720 x 580 mm | D31: 2436.5499 | E31: 2526.8539
B32: TAR-1PU-607258 | C32: Gabinete Tarja 1 Puerta 600 x 720 x 580 mm | D32: 2798.3182 | E32: 3336.1712
B33: TAR-2PU-707258 | C33: Gabinete Tarja 2 Puertas 700 x 720 x 580 mm | D33: 3344.5709 | E33: 3852.6721
B34: TAR-2PU-807258 | C34: Gabinete Tarja 2 Puertas 800 x 720 x 580 mm | D34: 3563.3248 | E34: 4105.8502
B35: TAR-2PU-907258 | C35: Gabinete Tarja 2 Puertas 900 x 720 x 580 mm | D35: 3782.0787 | E35: 4359.0283
B36: DES-1PU-4021058 | C36: Despensa 1 Puerta 400 x 2100 x 580 mm | D36: 6853.0481 | E36: 8113.7517
B37: DES-1PU-6021058 | C37: Despensa 1 Puerta 600 x 2100 x 580 mm | D37: 8387.3513 | E37: 9913.1631
B38: DES-2PU-8021058 | C38: Despensa 2 Puertas 800 x 2100 x 580 mm | D38: 10223.553 | E38: 12020.521
B39: DES-HOR-6021058 | C39: Torre Horno y Micro 600 x 2100 x 580 mm | D39: 8788.1361 | E39: 9053.4828
B40: DES-HOR-7021058 | C40: Torre Horno y Micro 700 x 2100 x 580 mm | D40: 10202.726 | E40: 10312.439
B41: DES-HOR-3CA-6021058 | C41: Torre Horno y Micro c/Cajones 600 x 2100 x 580 mm | D41: =D39*('📊 Resumen y Cotización'!D52/'📊 Resumen y Cotización'!D50) -> 11871.515 | E41: =E39*('📊 Resumen y Cotización'!G52/'📊 Resumen y Cotización'!G50) -> 12766.457
B42: DES-HOR-3CA-7021058 | C42: Torre Horno y Micro c/Cajones 700 x 2100 x 580 mm | D42: =D40*('📊 Resumen y Cotización'!D53/'📊 Resumen y Cotización'!D51) -> 14146.825 | E42: =E40*('📊 Resumen y Cotización'!G53/'📊 Resumen y Cotización'!G51) -> 14203.954
B43: DES-NIC-4021061 | C43: Despensa Nicho 400 x 2100 x 610 mm | D43: 6351.7242 | E43: 6298.4838
B44: PAN-ALA-3434 | C44: Panel Alacena 340 x 340 mm | D44: 183.2406 | E44: 183.2406
B45: PAN-ALA-6834 | C45: Panel Alacena 680 x 340 mm | D45: 344.72121 | E45: 344.72121
B46: PAN-GAB-7261 | C46: Panel Gabinete 720 x 610 mm | D46: 615.9616 | E46: 615.9616
B47: PAN-DES-21061 | C47: Panel Despensa 2100 x 610 mm | D47: 1721.728 | E47: 1721.728
B48: PAN-DES-21034 | C48: Panel Despensa 2100 x 340 mm | D48: =D47*('📊 Resumen y Cotización'!D59/'📊 Resumen y Cotización'!D58) -> 1023.2811 | E48: =E47*('📊 Resumen y Cotización'!G59/'📊 Resumen y Cotización'!G58) -> 1023.2811
B49: ZOC-24015 | C49: Zoclo 2400 x 150 mm | D49: 598.31607 | E49: 598.31607

Sheet 📊 Resumen y Cotización
A1: RESUMEN Y COTIZACIÓN COMPARATIVA
A2: Compara el mismo proyecto en muebles interiores blancos y totalmente maderados; los precios pendientes quedan bloqueados.
A3: Proyecto: | B3: Mobiliario Completo (Exportado desde SketchUp) | H3: Fecha: | I3: 46221 | K3: Moneda: | L3: MXN ($)
A4: Cliente: | B4: Público General / Cotización Proyecto
A6: CANTIDAD TOTAL | C6: MUEBLES BLANCO | E6: MUEBLES MADERADO | G6: CUBIERTA | I6: FINAL BLANCO | K6: FINAL MADERADO | M6: DIFERENCIA
A7: =SUM(A13:A60) -> 9 | C7: =L25 -> 47739.652 | E7: =M25 -> 59954.276 | G7: ='🧱 Cubiertas'!H4 -> 0 | I7: =L28 -> 55377.996 | K7: =M28 -> 69546.96 | M7: =IF(ISNUMBER(M28),M28-L28,"PENDIENTE") -> 14168.964
A8: Unidades cotizadas | C8: Venta de muebles | E8: Venta conocida | G8: Partida separada del mobiliario | I8: Muebles + cubierta + IVA | K8: Se habilita sin alertas | M8: Maderado − blanco
A10: COTIZADOR COMPARATIVO DE MUEBLES | K10: ESTRUCTURA DE VENTA
A11: Edita Cantidad y los campos amarillos. BLA y MAD se recalculan en paralelo; Estado MAD advierte módulos con costos incompletos. | K11: =IF(SUM('📋 Explosión y Despiece Bla'!$V$2:$V$643)+SUM('📋 Explosión y Despiece Mad'!$V$2:$V$713)=0,"✓ COSTOS COMPLETOS","⚠ REVISAR PRECIOS FALTANTES") -> ✓ COSTOS COMPLETOS
A12: Cantidad | B12: ID Módulo | C12: Mueble | D12: Costo BLA | E12: Precio BLA | F12: Total BLA | G12: Costo MAD | H12: Precio MAD | I12: Total MAD | J12: Estado MAD | K12: Concepto | L12: Blanco | M12: Maderado | N12: Nota
A13: 1 | B13: ALA-RIN-656832 | C13: Alacena Rinconera 650 x 680 x 320 mm | D13: =SUMIF('📋 Explosión y Despiece Bla'!$K$2:$K$643,B13,'📋 Explosión y Despiece Bla'!$S$2:$S$643) -> 703.90877 | E13: =D13*$L$14+$L$15 -> 4716.1888 | F13: =A13*E13 -> 4716.1888 | G13: =SUMIF('📋 Explosión y Despiece Mad'!$K$2:$K$713,B13,'📋 Explosión y Despiece Mad'!$S$2:$S$713) -> 922.07751 | H13: =G13*$L$14+$L$15 -> 6177.9193 | I13: =A13*H13 -> 6177.9193 | J13: =IF(SUMIF('📋 Explosión y Despiece Mad'!$K$2:$K$713,B13,'📋 Explosión y Despiece Mad'!$V$2:$V$713)>0,"PENDIENTE","OK") -> OK | K13: Costo directo | L13: =A13*D13+A14*D14+A15*D15+A16*D16+A17*D17+A18*D18+A19*D19+A20*D20+A22*D22+A23*D23+A24*D24+A25*D25+A27*D27+A28*D28+A29*D29+A30*D30+A31*D31+A32*D32+A33*D33+A34*D34+A35*D35+A36*D36+A37*D37+A38*D38+A41*D41+A42*D42+A43*D43+A44*D44+A45*D45+A46*D46+A47*D47+A48*D48+A49*D49+A50*D50+A51*D51+A54*D54+A55*D55+A56*D56+A57*D57+A58*D58+A60*D60 -> 7125.3211 | M13: =A13*G13+A14*G14+A15*G15+A16*G16+A17*G17+A18*G18+A19*G19+A20*G20+A22*G22+A23*G23+A24*G24+A25*G25+A27*G27+A28*G28+A29*G29+A30*G30+A31*G31+A32*G32+A33*G33+A34*G34+A35*G35+A36*G36+A37*G37+A38*G38+A41*G41+A42*G42+A43*G43+A44*G44+A45*G45+A46*G46+A47*G47+A48*G48+A49*G49+A50*G50+A51*G51+A54*G54+A55*G55+A56*G56+A57*G57+A58*G58+A60*G60 -> 8948.3994 | N13: Antes de margen y mano de obra
A14: 0 | B14: ALA-1PU-306832 | C14: Alacena 1 Puerta 300 x 680 x 320 mm | D14: =SUMIF('📋 Explosión y Despiece Bla'!$K$2:$K$643,B14,'📋 Explosión y Despiece Bla'!$S$2:$S$643) -> 423.39961 | E14: =D14*$L$14+$L$15 -> 2836.7774 | F14: =A14*E14 -> 0 | G14: =SUMIF('📋 Explosión y Despiece Mad'!$K$2:$K$713,B14,'📋 Explosión y Despiece Mad'!$S$2:$S$713) -> 558.55436 | H14: =G14*$L$14+$L$15 -> 3742.3142 | I14: =A14*H14 -> 0 | J14: =IF(SUMIF('📋 Explosión y Despiece Mad'!$K$2:$K$713,B14,'📋 Explosión y Despiece Mad'!$V$2:$V$713)>0,"PENDIENTE","OK") -> OK | K14: Factor de venta | L14: 6.7 | M14: =L14 -> 6.7 | N14: Común para ambos acabados
A15: 0 | B15: ALA-1PU-406832 | C15: Alacena 1 Puerta 400 x 680 x 320 mm | D15: =SUMIF('📋 Explosión y Despiece Bla'!$K$2:$K$643,B15,'📋 Explosión y Despiece Bla'!$S$2:$S$643) -> 487.26541 | E15: =D15*$L$14+$L$15 -> 3264.6783 | F15: =A15*E15 -> 0 | G15: =SUMIF('📋 Explosión y Despiece Mad'!$K$2:$K$713,B15,'📋 Explosión y Despiece Mad'!$S$2:$S$713) -> 642.51766 | H15: =G15*$L$14+$L$15 -> 4304.8683 | I15: =A15*H15 -> 0 | J15: =IF(SUMIF('📋 Explosión y Despiece Mad'!$K$2:$K$713,B15,'📋 Explosión y Despiece Mad'!$V$2:$V$713)>0,"PENDIENTE","OK") -> OK | K15: Mano de obra / unidad | L15: 0 | M15: =L15 -> 0 | N15: Común para ambos acabados
A16: 0 | B16: ALA-1PU-506832 | C16: Alacena 1 Puerta 500 x 680 x 320 mm | D16: =SUMIF('📋 Explosión y Despiece Bla'!$K$2:$K$643,B16,'📋 Explosión y Despiece Bla'!$S$2:$S$643) -> 552.35521 | E16: =D16*$L$14+$L$15 -> 3700.7799 | F16: =A16*E16 -> 0 | G16: =SUMIF('📋 Explosión y Despiece Mad'!$K$2:$K$713,B16,'📋 Explosión y Despiece Mad'!$S$2:$S$713) -> 724.07748 | H16: =G16*$L$14+$L$15 -> 4851.3191 | I16: =A16*H16 -> 0 | J16: =IF(SUMIF('📋 Explosión y Despiece Mad'!$K$2:$K$713,B16,'📋 Explosión y Despiece Mad'!$V$2:$V$713)>0,"PENDIENTE","OK") -> OK | K16: Venta de muebles | L16: =SUM(F13:F60) -> 47739.652 | M16: =SUM(I13:I60) -> 59954.276 | N16: Excluye cubiertas
A17: 0 | B17: ALA-1PU-606832 | C17: Alacena 1 Puerta 600 x 680 x 320 mm | D17: =SUMIF('📋 Explosión y Despiece Bla'!$K$2:$K$643,B17,'📋 Explosión y Despiece Bla'!$S$2:$S$643) -> 617.445 | E17: =D17*$L$14+$L$15 -> 4136.8815 | F17: =A17*E17 -> 0 | G17: =SUMIF('📋 Explosión y Despiece Mad'!$K$2:$K$713,B17,'📋 Explosión y Despiece Mad'!$S$2:$S$713) -> 805.6373 | H17: =G17*$L$14+$L$15 -> 5397.7699 | I17: =A17*H17 -> 0 | J17: =IF(SUMIF('📋 Explosión y Despiece Mad'!$K$2:$K$713,B17,'📋 Explosión y Despiece Mad'!$V$2:$V$713)>0,"PENDIENTE","OK") -> OK
A18: 0 | B18: ALA-2PU-706832 | C18: Alacena 2 Puertas 700 x 680 x 320 mm | D18: =SUMIF('📋 Explosión y Despiece Bla'!$K$2:$K$643,B18,'📋 Explosión y Despiece Bla'!$S$2:$S$643) -> 773.66478 | E18: =D18*$L$14+$L$15 -> 5183.554 | F18: =A18*E18 -> 0 | G18: =SUMIF('📋 Explosión y Despiece Mad'!$K$2:$K$713,B18,'📋 Explosión y Despiece Mad'!$S$2:$S$713) -> 954.32709 | H18: =G18*$L$14+$L$15 -> 6393.9915 | I18: =A18*H18 -> 0 | J18: =IF(SUMIF('📋 Explosión y Despiece Mad'!$K$2:$K$713,B18,'📋 Explosión y Despiece Mad'!$V$2:$V$713)>0,"PENDIENTE","OK") -> OK | K18: CUBIERTA SEPARADA
A19: 2 | B19: ALA-2PU-806832 | C19: Alacena 2 Puertas 800 x 680 x 320 mm | D19: =SUMIF('📋 Explosión y Despiece Bla'!$K$2:$K$643,B19,'📋 Explosión y Despiece Bla'!$S$2:$S$643) -> 838.75457 | E19: =D19*$L$14+$L$15 -> 5619.6556 | F19: =A19*E19 -> 11239.311 | G19: =SUMIF('📋 Explosión y Despiece Mad'!$K$2:$K$713,B19,'📋 Explosión y Despiece Mad'!$S$2:$S$713) -> 1035.8869 | H19: =G19*$L$14+$L$15 -> 6940.4423 | I19: =A19*H19 -> 13880.885 | J19: =IF(SUMIF('📋 Explosión y Despiece Mad'!$K$2:$K$713,B19,'📋 Explosión y Despiece Mad'!$V$2:$V$713)>0,"PENDIENTE","OK") -> OK | K19: Tipo de cubierta | L19: SIN CUBIERTA | M19: =L19 -> SIN CUBIERTA | N19: Seleccionar aquí para toda la cotización
A20: 0 | B20: ALA-2PU-906832 | C20: Alacena 2 Puertas 900 x 680 x 320 mm | D20: =SUMIF('📋 Explosión y Despiece Bla'!$K$2:$K$643,B20,'📋 Explosión y Despiece Bla'!$S$2:$S$643) -> 903.5088 | E20: =D20*$L$14+$L$15 -> 6053.509 | F20: =A20*E20 -> 0 | G20: =SUMIF('📋 Explosión y Despiece Mad'!$K$2:$K$713,B20,'📋 Explosión y Despiece Mad'!$S$2:$S$713) -> 1117.1112 | H20: =G20*$L$14+$L$15 -> 7484.6447 | I20: =A20*H20 -> 0 | J20: =IF(SUMIF('📋 Explosión y Despiece Mad'!$K$2:$K$713,B20,'📋 Explosión y Despiece Mad'!$V$2:$V$713)>0,"PENDIENTE","OK") -> OK | K20: Multiplicador | L20: ='🧱 Cubiertas'!E3 -> 4 | M20: =L20 -> 4 | N20: Mismo concepto que el factor de muebles
A21: 0 | B21: ALA-BAS-503432 | C21: Alacena Basculante 500 x 340 x 320 mm | D21: =SUMIF('📋 Explosión y Despiece Bla'!$K$2:$K$643,B21,'📋 Explosión y Despiece Bla'!$S$2:$S$643) -> 388.63027 | E21: =D21*$L$14+$L$15 -> 2603.8228 | F21: =A21*E21 -> 0 | G21: =SUMIF('📋 Explosión y Despiece Mad'!$K$2:$K$713,B21,'📋 Explosión y Despiece Mad'!$S$2:$S$713) -> 506.07213 | H21: =G21*$L$14+$L$15 -> 3390.6832 | I21: =A21*H21 -> 0 | J21: =IF(SUMIF('📋 Explosión y Despiece Mad'!$K$2:$K$713,B21,'📋 Explosión y Despiece Mad'!$V$2:$V$713)>0,"PENDIENTE","OK") -> OK | K21: Costo cubierta | L21: ='🧱 Cubiertas'!H5 -> 0 | M21: =L21 -> 0 | N21: Costo según largo total redondeado a múltiplos de 1.20 m
A22: 1 | B22: ALA-BAS-603432 | C22: Alacena Basculante 600 x 340 x 320 mm | D22: =SUMIF('📋 Explosión y Despiece Bla'!$K$2:$K$643,B22,'📋 Explosión y Despiece Bla'!$S$2:$S$643) -> 426.90847 | E22: =D22*$L$14+$L$15 -> 2860.2867 | F22: =A22*E22 -> 2860.2867 | G22: =SUMIF('📋 Explosión y Despiece Mad'!$K$2:$K$713,B22,'📋 Explosión y Despiece Mad'!$S$2:$S$713) -> 554.57695 | H22: =G22*$L$14+$L$15 -> 3715.6656 | I22: =A22*H22 -> 3715.6656 | J22: =IF(SUMIF('📋 Explosión y Despiece Mad'!$K$2:$K$713,B22,'📋 Explosión y Despiece Mad'!$V$2:$V$713)>0,"PENDIENTE","OK") -> OK | K22: Venta cubierta | L22: ='🧱 Cubiertas'!H4 -> 0 | M22: =L22 -> 0 | N22: Partida independiente; no incluida en precios unitarios de muebles
A23: 1 | B23: ALA-BAS-703432 | C23: Alacena Basculante 700 x 340 x 320 mm | D23: =SUMIF('📋 Explosión y Despiece Bla'!$K$2:$K$643,B23,'📋 Explosión y Despiece Bla'!$S$2:$S$643) -> 465.18666 | E23: =D23*$L$14+$L$15 -> 3116.7506 | F23: =A23*E23 -> 3116.7506 | G23: =SUMIF('📋 Explosión y Despiece Mad'!$K$2:$K$713,B23,'📋 Explosión y Despiece Mad'!$S$2:$S$713) -> 603.08178 | H23: =G23*$L$14+$L$15 -> 4040.6479 | I23: =A23*H23 -> 4040.6479 | J23: =IF(SUMIF('📋 Explosión y Despiece Mad'!$K$2:$K$713,B23,'📋 Explosión y Despiece Mad'!$V$2:$V$713)>0,"PENDIENTE","OK") -> OK
A24: 0 | B24: ALA-BAS-803432 | C24: Alacena Basculante 800 x 340 x 320 mm | D24: =SUMIF('📋 Explosión y Despiece Bla'!$K$2:$K$643,B24,'📋 Explosión y Despiece Bla'!$S$2:$S$643) -> 503.46485 | E24: =D24*$L$14+$L$15 -> 3373.2145 | F24: =A24*E24 -> 0 | G24: =SUMIF('📋 Explosión y Despiece Mad'!$K$2:$K$713,B24,'📋 Explosión y Despiece Mad'!$S$2:$S$713) -> 651.5866 | H24: =G24*$L$14+$L$15 -> 4365.6303 | I24: =A24*H24 -> 0 | J24: =IF(SUMIF('📋 Explosión y Despiece Mad'!$K$2:$K$713,B24,'📋 Explosión y Despiece Mad'!$V$2:$V$713)>0,"PENDIENTE","OK") -> OK | K24: PRESUPUESTO TOTAL
A25: 1 | B25: ALA-NIC-276832 | C25: Alacena Nicho Abierto 270 x 680 x 320 mm | D25: =SUMIF('📋 Explosión y Despiece Bla'!$K$2:$K$643,B25,'📋 Explosión y Despiece Bla'!$S$2:$S$643) -> 379.54202 | E25: =D25*$L$14+$L$15 -> 2542.9315 | F25: =A25*E25 -> 2542.9315 | G25: =SUMIF('📋 Explosión y Despiece Mad'!$K$2:$K$713,B25,'📋 Explosión y Despiece Mad'!$S$2:$S$713) -> 419.54202 | H25: =G25*$L$14+$L$15 -> 2810.9315 | I25: =A25*H25 -> 2810.9315 | J25: =IF(SUMIF('📋 Explosión y Despiece Mad'!$K$2:$K$713,B25,'📋 Explosión y Despiece Mad'!$V$2:$V$713)>0,"PENDIENTE","OK") -> OK | K25: Muebles | L25: =L16 -> 47739.652 | M25: =M16 -> 59954.276 | N25: Solo mobiliario; excluye cubierta
A26: 0 | B26: ALA-MIC-503432 | C26: Alacena Nicho Microondas 500 x 340 x 320 mm | D26: =SUMIF('📋 Explosión y Despiece Bla'!$K$2:$K$643,B26,'📋 Explosión y Despiece Bla'!$S$2:$S$643) -> 316.61257 | E26: =D26*$L$14+$L$15 -> 2121.3042 | F26: =A26*E26 -> 0 | G26: =SUMIF('📋 Explosión y Despiece Mad'!$K$2:$K$713,B26,'📋 Explosión y Despiece Mad'!$S$2:$S$713) -> 356.61257 | H26: =G26*$L$14+$L$15 -> 2389.3042 | I26: =A26*H26 -> 0 | J26: =IF(SUMIF('📋 Explosión y Despiece Mad'!$K$2:$K$713,B26,'📋 Explosión y Despiece Mad'!$V$2:$V$713)>0,"PENDIENTE","OK") -> OK | K26: Cubierta | L26: ='🧱 Cubiertas'!H4 -> 0 | M26: ='🧱 Cubiertas'!H4 -> 0 | N26: Cobro separado por largo total de cocina
A27: 0 | B27: ALA-MIC-603432 | C27: Alacena Nicho Microondas 600 x 340 x 320 mm | D27: =SUMIF('📋 Explosión y Despiece Bla'!$K$2:$K$643,B27,'📋 Explosión y Despiece Bla'!$S$2:$S$643) -> 351.5288 | E27: =D27*$L$14+$L$15 -> 2355.2429 | F27: =A27*E27 -> 0 | G27: =SUMIF('📋 Explosión y Despiece Mad'!$K$2:$K$713,B27,'📋 Explosión y Despiece Mad'!$S$2:$S$713) -> 391.5288 | H27: =G27*$L$14+$L$15 -> 2623.2429 | I27: =A27*H27 -> 0 | J27: =IF(SUMIF('📋 Explosión y Despiece Mad'!$K$2:$K$713,B27,'📋 Explosión y Despiece Mad'!$V$2:$V$713)>0,"PENDIENTE","OK") -> OK | K27: IVA (16%) | L27: =SUM(L25:L26)*16% -> 7638.3442 | M27: =SUM(M25:M26)*16% -> 9592.6841 | N27: 16% sobre muebles y cubierta
A28: 1 | B28: GAB-RIN-1057258 | C28: Gabinete Rinconero 1050 x 720 x 580 mm | D28: =SUMIF('📋 Explosión y Despiece Bla'!$K$2:$K$643,B28,'📋 Explosión y Despiece Bla'!$S$2:$S$643) -> 1161.3762 | E28: =D28*$L$14+$L$15 -> 7781.2205 | F28: =A28*E28 -> 7781.2205 | G28: =SUMIF('📋 Explosión y Despiece Mad'!$K$2:$K$713,B28,'📋 Explosión y Despiece Mad'!$S$2:$S$713) -> 1540.2864 | H28: =G28*$L$14+$L$15 -> 10319.919 | I28: =A28*H28 -> 10319.919 | J28: =IF(SUMIF('📋 Explosión y Despiece Mad'!$K$2:$K$713,B28,'📋 Explosión y Despiece Mad'!$V$2:$V$713)>0,"PENDIENTE","OK") -> OK | K28: GRAN TOTAL | L28: =SUM(L25:L27) -> 55377.996 | M28: =IF(SUM('📋 Explosión y Despiece Mad'!$V$2:$V$713)>0,"PENDIENTE",SUM(M25:M27)) -> 69546.96 | N28: Suma de muebles, cubierta e IVA
A29: 0 | B29: GAB-1PU-307258 | C29: Gabinete 1 Puerta 300 x 720 x 580 mm | D29: =SUMIF('📋 Explosión y Despiece Bla'!$K$2:$K$643,B29,'📋 Explosión y Despiece Bla'!$S$2:$S$643) -> 625.98997 | E29: =D29*$L$14+$L$15 -> 4194.1328 | F29: =A29*E29 -> 0 | G29: =SUMIF('📋 Explosión y Despiece Mad'!$K$2:$K$713,B29,'📋 Explosión y Despiece Mad'!$S$2:$S$713) -> 823.42706 | H29: =G29*$L$14+$L$15 -> 5516.9613 | I29: =A29*H29 -> 0 | J29: =IF(SUMIF('📋 Explosión y Despiece Mad'!$K$2:$K$713,B29,'📋 Explosión y Despiece Mad'!$V$2:$V$713)>0,"PENDIENTE","OK") -> OK | K29: Diferencia MAD vs BLA | M29: =IF(ISNUMBER(M28),M28-L28,"PENDIENTE") -> 14168.964 | N29: Disponible con costos completos
A30: 0 | B30: GAB-1PU-407258 | C30: Gabinete 1 Puerta 400 x 720 x 580 mm | D30: =SUMIF('📋 Explosión y Despiece Bla'!$K$2:$K$643,B30,'📋 Explosión y Despiece Bla'!$S$2:$S$643) -> 702.10003 | E30: =D30*$L$14+$L$15 -> 4704.0702 | F30: =A30*E30 -> 0 | G30: =SUMIF('📋 Explosión y Despiece Mad'!$K$2:$K$713,B30,'📋 Explosión y Despiece Mad'!$S$2:$S$713) -> 919.52979 | H30: =G30*$L$14+$L$15 -> 6160.8496 | I30: =A30*H30 -> 0 | J30: =IF(SUMIF('📋 Explosión y Despiece Mad'!$K$2:$K$713,B30,'📋 Explosión y Despiece Mad'!$V$2:$V$713)>0,"PENDIENTE","OK") -> OK
A31: 0 | B31: GAB-1PU-507258 | C31: Gabinete 1 Puerta 500 x 720 x 580 mm | D31: =SUMIF('📋 Explosión y Despiece Bla'!$K$2:$K$643,B31,'📋 Explosión y Despiece Bla'!$S$2:$S$643) -> 778.21009 | E31: =D31*$L$14+$L$15 -> 5214.0076 | F31: =A31*E31 -> 0 | G31: =SUMIF('📋 Explosión y Despiece Mad'!$K$2:$K$713,B31,'📋 Explosión y Despiece Mad'!$S$2:$S$713) -> 1015.6325 | H31: =G31*$L$14+$L$15 -> 6804.7378 | I31: =A31*H31 -> 0 | J31: =IF(SUMIF('📋 Explosión y Despiece Mad'!$K$2:$K$713,B31,'📋 Explosión y Despiece Mad'!$V$2:$V$713)>0,"PENDIENTE","OK") -> OK | K31: PRESUPUESTO TOTAL DISTRIBUIDOR
A32: 0 | B32: GAB-1PU-607258 | C32: Gabinete 1 Puerta 600 x 720 x 580 mm | D32: =SUMIF('📋 Explosión y Despiece Bla'!$K$2:$K$643,B32,'📋 Explosión y Despiece Bla'!$S$2:$S$643) -> 854.79416 | E32: =D32*$L$14+$L$15 -> 5727.1208 | F32: =A32*E32 -> 0 | G32: =SUMIF('📋 Explosión y Despiece Mad'!$K$2:$K$713,B32,'📋 Explosión y Despiece Mad'!$S$2:$S$713) -> 1112.4857 | H32: =G32*$L$14+$L$15 -> 7453.6545 | I32: =A32*H32 -> 0 | J32: =IF(SUMIF('📋 Explosión y Despiece Mad'!$K$2:$K$713,B32,'📋 Explosión y Despiece Mad'!$V$2:$V$713)>0,"PENDIENTE","OK") -> OK | K32: Muebles | L32: =L25*65% -> 31030.773 | M32: =IF(ISNUMBER(M25),M25*65%,"PENDIENTE") -> 38970.279 | N32: 35% de descuento sobre muebles
A33: 0 | B33: GAB-2PU-707258 | C33: Gabinete 2 Puertas 700 x 720 x 580 mm | D33: =SUMIF('📋 Explosión y Despiece Bla'!$K$2:$K$643,B33,'📋 Explosión y Despiece Bla'!$S$2:$S$643) -> 1024.4223 | E33: =D33*$L$14+$L$15 -> 6863.6291 | F33: =A33*E33 -> 0 | G33: =SUMIF('📋 Explosión y Despiece Mad'!$K$2:$K$713,B33,'📋 Explosión y Despiece Mad'!$S$2:$S$713) -> 1279.0795 | H33: =G33*$L$14+$L$15 -> 8569.8327 | I33: =A33*H33 -> 0 | J33: =IF(SUMIF('📋 Explosión y Despiece Mad'!$K$2:$K$713,B33,'📋 Explosión y Despiece Mad'!$V$2:$V$713)>0,"PENDIENTE","OK") -> OK | K33: Cubierta | L33: =L26*65% -> 0 | M33: =IF(ISNUMBER(M26),M26*65%,"PENDIENTE") -> 0 | N33: 35% de descuento sobre cubierta
A34: 0 | B34: GAB-2PU-807258 | C34: Gabinete 2 Puertas 800 x 720 x 580 mm | D34: =SUMIF('📋 Explosión y Despiece Bla'!$K$2:$K$643,B34,'📋 Explosión y Despiece Bla'!$S$2:$S$643) -> 1102.3323 | E34: =D34*$L$14+$L$15 -> 7385.6265 | F34: =A34*E34 -> 0 | G34: =SUMIF('📋 Explosión y Despiece Mad'!$K$2:$K$713,B34,'📋 Explosión y Despiece Mad'!$S$2:$S$713) -> 1378.0322 | H34: =G34*$L$14+$L$15 -> 9232.816 | I34: =A34*H34 -> 0 | J34: =IF(SUMIF('📋 Explosión y Despiece Mad'!$K$2:$K$713,B34,'📋 Explosión y Despiece Mad'!$V$2:$V$713)>0,"PENDIENTE","OK") -> OK | K34: IVA (16%) | L34: =SUM(L32:L33)*16% -> 4964.9238 | M34: =IF(OR(NOT(ISNUMBER(M32)),NOT(ISNUMBER(M33))),"PENDIENTE",SUM(M32:M33)*16%) -> 6235.2447 | N34: 16% sobre muebles y cubierta con descuento
A35: 0 | B35: GAB-2PU-907258 | C35: Gabinete 2 Puertas 900 x 720 x 580 mm | D35: =SUMIF('📋 Explosión y Despiece Bla'!$K$2:$K$643,B35,'📋 Explosión y Despiece Bla'!$S$2:$S$643) -> 1180.2424 | E35: =D35*$L$14+$L$15 -> 7907.6239 | F35: =A35*E35 -> 0 | G35: =SUMIF('📋 Explosión y Despiece Mad'!$K$2:$K$713,B35,'📋 Explosión y Despiece Mad'!$S$2:$S$713) -> 1476.985 | H35: =G35*$L$14+$L$15 -> 9895.7992 | I35: =A35*H35 -> 0 | J35: =IF(SUMIF('📋 Explosión y Despiece Mad'!$K$2:$K$713,B35,'📋 Explosión y Despiece Mad'!$V$2:$V$713)>0,"PENDIENTE","OK") -> OK | K35: GRAN TOTAL DISTRIBUIDOR | L35: =SUM(L32:L34) -> 35995.697 | M35: =IF(OR(NOT(ISNUMBER(M32)),NOT(ISNUMBER(M33)),NOT(ISNUMBER(M34))),"PENDIENTE",SUM(M32:M34)) -> 45205.524 | N35: Total distribuidor con IVA
A36: 1 | B36: GAB-3CA-407258 | C36: Gabinete 3 Cajones 400 x 720 x 580 mm | D36: =SUMIF('📋 Explosión y Despiece Bla'!$K$2:$K$643,B36,'📋 Explosión y Despiece Bla'!$S$2:$S$643) -> 1375.9038 | E36: =D36*$L$14+$L$15 -> 9218.5552 | F36: =A36*E36 -> 9218.5552 | G36: =SUMIF('📋 Explosión y Despiece Mad'!$K$2:$K$713,B36,'📋 Explosión y Despiece Mad'!$S$2:$S$713) -> 1705.4619 | H36: =G36*$L$14+$L$15 -> 11426.595 | I36: =A36*H36 -> 11426.595 | J36: =IF(SUMIF('📋 Explosión y Despiece Mad'!$K$2:$K$713,B36,'📋 Explosión y Despiece Mad'!$V$2:$V$713)>0,"PENDIENTE","OK") -> OK | K36: Diferencia MAD vs BLA | M36: =IF(AND(ISNUMBER(L35),ISNUMBER(M35)),M35-L35,"PENDIENTE") -> 9209.8267 | N36: Disponible con costos completos
A37: 0 | B37: GAB-3CA-507258 | C37: Gabinete 3 Cajones 500 x 720 x 580 mm | D37: =SUMIF('📋 Explosión y Despiece Bla'!$K$2:$K$643,B37,'📋 Explosión y Despiece Bla'!$S$2:$S$643) -> 1496.9653 | E37: =D37*$L$14+$L$15 -> 10029.668 | F37: =A37*E37 -> 0 | G37: =SUMIF('📋 Explosión y Despiece Mad'!$K$2:$K$713,B37,'📋 Explosión y Despiece Mad'!$S$2:$S$713) -> 1864.4679 | H37: =G37*$L$14+$L$15 -> 12491.935 | I37: =A37*H37 -> 0 | J37: =IF(SUMIF('📋 Explosión y Despiece Mad'!$K$2:$K$713,B37,'📋 Explosión y Despiece Mad'!$V$2:$V$713)>0,"PENDIENTE","OK") -> OK
A38: 0 | B38: GAB-3CA-607258 | C38: Gabinete 3 Cajones 600 x 720 x 580 mm | D38: =SUMIF('📋 Explosión y Despiece Bla'!$K$2:$K$643,B38,'📋 Explosión y Despiece Bla'!$S$2:$S$643) -> 1618.0269 | E38: =D38*$L$14+$L$15 -> 10840.781 | F38: =A38*E38 -> 0 | G38: =SUMIF('📋 Explosión y Despiece Mad'!$K$2:$K$713,B38,'📋 Explosión y Despiece Mad'!$S$2:$S$713) -> 2023.4738 | H38: =G38*$L$14+$L$15 -> 13557.275 | I38: =A38*H38 -> 0 | J38: =IF(SUMIF('📋 Explosión y Despiece Mad'!$K$2:$K$713,B38,'📋 Explosión y Despiece Mad'!$V$2:$V$713)>0,"PENDIENTE","OK") -> OK
A39: 0 | B39: GAB-MIC-603658 | C39: Gabinete Nicho Microondas 600 x 360 x 580 mm | D39: =SUMIF('📋 Explosión y Despiece Bla'!$K$2:$K$643,B39,'📋 Explosión y Despiece Bla'!$S$2:$S$643) -> 514.76544 | E39: =D39*$L$14+$L$15 -> 3448.9284 | F39: =A39*E39 -> 0 | G39: =SUMIF('📋 Explosión y Despiece Mad'!$K$2:$K$713,B39,'📋 Explosión y Despiece Mad'!$S$2:$S$713) -> 554.76544 | H39: =G39*$L$14+$L$15 -> 3716.9284 | I39: =A39*H39 -> 0 | J39: =IF(SUMIF('📋 Explosión y Despiece Mad'!$K$2:$K$713,B39,'📋 Explosión y Despiece Mad'!$V$2:$V$713)>0,"PENDIENTE","OK") -> OK
A40: 0 | B40: GAB-1CA-603658 | C40: Gabinete 1 Cajon 600 x 360 x 580 mm | D40: =SUMIF('📋 Explosión y Despiece Bla'!$K$2:$K$643,B40,'📋 Explosión y Despiece Bla'!$S$2:$S$643) -> 834.41273 | E40: =D40*$L$14+$L$15 -> 5590.5653 | F40: =A40*E40 -> 0 | G40: =SUMIF('📋 Explosión y Despiece Mad'!$K$2:$K$713,B40,'📋 Explosión y Despiece Mad'!$S$2:$S$713) -> 1076.5238 | H40: =G40*$L$14+$L$15 -> 7212.7094 | I40: =A40*H40 -> 0 | J40: =IF(SUMIF('📋 Explosión y Despiece Mad'!$K$2:$K$713,B40,'📋 Explosión y Despiece Mad'!$V$2:$V$713)>0,"PENDIENTE","OK") -> OK
A41: 0 | B41: GAB-NIC-207258 | C41: Gabinete Nicho 200 x 720 x 580 mm | D41: =SUMIF('📋 Explosión y Despiece Bla'!$K$2:$K$643,B41,'📋 Explosión y Despiece Bla'!$S$2:$S$643) -> 598.91581 | E41: =D41*$L$14+$L$15 -> 4012.736 | F41: =A41*E41 -> 0 | G41: =SUMIF('📋 Explosión y Despiece Mad'!$K$2:$K$713,B41,'📋 Explosión y Despiece Mad'!$S$2:$S$713) -> 599.94325 | H41: =G41*$L$14+$L$15 -> 4019.6198 | I41: =A41*H41 -> 0 | J41: =IF(SUMIF('📋 Explosión y Despiece Mad'!$K$2:$K$713,B41,'📋 Explosión y Despiece Mad'!$V$2:$V$713)>0,"PENDIENTE","OK") -> OK
A42: 0 | B42: GAB-NIC-TOA-207258 | C42: Gabinete Nicho Toallero 200 x 720 x 580 mm | D42: =SUMIF('📋 Explosión y Despiece Bla'!$K$2:$K$643,B42,'📋 Explosión y Despiece Bla'!$S$2:$S$643) -> 676.91574 | E42: =D42*$L$14+$L$15 -> 4535.3355 | F42: =A42*E42 -> 0 | G42: =SUMIF('📋 Explosión y Despiece Mad'!$K$2:$K$713,B42,'📋 Explosión y Despiece Mad'!$S$2:$S$713) -> 687.72474 | H42: =G42*$L$14+$L$15 -> 4607.7558 | I42: =A42*H42 -> 0 | J42: =IF(SUMIF('📋 Explosión y Despiece Mad'!$K$2:$K$713,B42,'📋 Explosión y Despiece Mad'!$V$2:$V$713)>0,"PENDIENTE","OK") -> OK
A43: 0 | B43: TAR-1PU-607258 | C43: Gabinete Tarja 1 Puerta 600 x 720 x 580 mm | D43: =SUMIF('📋 Explosión y Despiece Bla'!$K$2:$K$643,B43,'📋 Explosión y Despiece Bla'!$S$2:$S$643) -> 728.63275 | E43: =D43*$L$14+$L$15 -> 4881.8394 | F43: =A43*E43 -> 0 | G43: =SUMIF('📋 Explosión y Despiece Mad'!$K$2:$K$713,B43,'📋 Explosión y Despiece Mad'!$S$2:$S$713) -> 922.60451 | H43: =G43*$L$14+$L$15 -> 6181.4502 | I43: =A43*H43 -> 0 | J43: =IF(SUMIF('📋 Explosión y Despiece Mad'!$K$2:$K$713,B43,'📋 Explosión y Despiece Mad'!$V$2:$V$713)>0,"PENDIENTE","OK") -> OK
A44: 0 | B44: TAR-2PU-707258 | C44: Gabinete Tarja 2 Puertas 700 x 720 x 580 mm | D44: =SUMIF('📋 Explosión y Despiece Bla'!$K$2:$K$643,B44,'📋 Explosión y Despiece Bla'!$S$2:$S$643) -> 877.79727 | E44: =D44*$L$14+$L$15 -> 5881.2417 | F44: =A44*E44 -> 0 | G44: =SUMIF('📋 Explosión y Despiece Mad'!$K$2:$K$713,B44,'📋 Explosión y Despiece Mad'!$S$2:$S$713) -> 1061.0511 | H44: =G44*$L$14+$L$15 -> 7109.0423 | I44: =A44*H44 -> 0 | J44: =IF(SUMIF('📋 Explosión y Despiece Mad'!$K$2:$K$713,B44,'📋 Explosión y Despiece Mad'!$V$2:$V$713)>0,"PENDIENTE","OK") -> OK
A45: 1 | B45: TAR-2PU-807258 | C45: Gabinete Tarja 2 Puertas 800 x 720 x 580 mm | D45: =SUMIF('📋 Explosión y Despiece Bla'!$K$2:$K$643,B45,'📋 Explosión y Despiece Bla'!$S$2:$S$643) -> 934.98611 | E45: =D45*$L$14+$L$15 -> 6264.407 | F45: =A45*E45 -> 6264.407 | G45: =SUMIF('📋 Explosión y Despiece Mad'!$K$2:$K$713,B45,'📋 Explosión y Despiece Mad'!$S$2:$S$713) -> 1131.599 | H45: =G45*$L$14+$L$15 -> 7581.7131 | I45: =A45*H45 -> 7581.7131 | J45: =IF(SUMIF('📋 Explosión y Despiece Mad'!$K$2:$K$713,B45,'📋 Explosión y Despiece Mad'!$V$2:$V$713)>0,"PENDIENTE","OK") -> OK
A46: 0 | B46: TAR-2PU-907258 | C46: Gabinete Tarja 2 Puertas 900 x 720 x 580 mm | D46: =SUMIF('📋 Explosión y Despiece Bla'!$K$2:$K$643,B46,'📋 Explosión y Despiece Bla'!$S$2:$S$643) -> 992.17495 | E46: =D46*$L$14+$L$15 -> 6647.5722 | F46: =A46*E46 -> 0 | G46: =SUMIF('📋 Explosión y Despiece Mad'!$K$2:$K$713,B46,'📋 Explosión y Despiece Mad'!$S$2:$S$713) -> 1202.1468 | H46: =G46*$L$14+$L$15 -> 8054.3839 | I46: =A46*H46 -> 0 | J46: =IF(SUMIF('📋 Explosión y Despiece Mad'!$K$2:$K$713,B46,'📋 Explosión y Despiece Mad'!$V$2:$V$713)>0,"PENDIENTE","OK") -> OK
A47: 0 | B47: DES-1PU-4021058 | C47: Despensa 1 Puerta 400 x 2100 x 580 mm | D47: =SUMIF('📋 Explosión y Despiece Bla'!$K$2:$K$643,B47,'📋 Explosión y Despiece Bla'!$S$2:$S$643) -> 1771.21 | E47: =D47*$L$14+$L$15 -> 11867.107 | F47: =A47*E47 -> 0 | G47: =SUMIF('📋 Explosión y Despiece Mad'!$K$2:$K$713,B47,'📋 Explosión y Despiece Mad'!$S$2:$S$713) -> 2227.6777 | H47: =G47*$L$14+$L$15 -> 14925.441 | I47: =A47*H47 -> 0 | J47: =IF(SUMIF('📋 Explosión y Despiece Mad'!$K$2:$K$713,B47,'📋 Explosión y Despiece Mad'!$V$2:$V$713)>0,"PENDIENTE","OK") -> OK
A48: 0 | B48: DES-1PU-6021058 | C48: Despensa 1 Puerta 600 x 2100 x 580 mm | D48: =SUMIF('📋 Explosión y Despiece Bla'!$K$2:$K$643,B48,'📋 Explosión y Despiece Bla'!$S$2:$S$643) -> 2168.2504 | E48: =D48*$L$14+$L$15 -> 14527.278 | F48: =A48*E48 -> 0 | G48: =SUMIF('📋 Explosión y Despiece Mad'!$K$2:$K$713,B48,'📋 Explosión y Despiece Mad'!$S$2:$S$713) -> 2724.0437 | H48: =G48*$L$14+$L$15 -> 18251.093 | I48: =A48*H48 -> 0 | J48: =IF(SUMIF('📋 Explosión y Despiece Mad'!$K$2:$K$713,B48,'📋 Explosión y Despiece Mad'!$V$2:$V$713)>0,"PENDIENTE","OK") -> OK
... A60: 0 | B60: ZOC-24015 | C60: Zoclo 2400 x 150 mm | D60: =SUMIF('📋 Explosión y Despiece Bla'!$K$2:$K$643,B60,'📋 Explosión y Despiece Bla'!$S$2:$S$643) -> 168.27689 | E60: =D60*$L$14+$L$15 -> 1127.4551 | F60: =A60*E60 -> 0 | G60: =SUMIF('📋 Explosión y Despiece Mad'!$K$2:$K$713,B60,'📋 Explosión y Despiece Mad'!$S$2:$S$713) -> 168.27689 | H60: =G60*$L$14+$L$15 -> 1127.4551 | I60: =A60*H60 -> 0 | J60: =IF(SUMIF('📋 Explosión y Despiece Mad'!$K$2:$K$713,B60,'📋 Explosión y Despiece Mad'!$V$2:$V$713)>0,"PENDIENTE","OK") -> OK
E61: TOTAL BLA | F61: =SUM(F13:F60) -> 47739.652 | H61: TOTAL MAD | I61: =SUM(I13:I60) -> 59954.276

Sheet 🧱 Cubiertas
A1: COTIZADOR DE CUBIERTAS POR MÓDULO
A2: Calcula cubiertas para gabinetes bajos y tarjas; el largo total seleccionado se cobra en múltiplos de 1.20 m × 0.60 m.
A3: Tipo de cubierta | B3: ='📊 Resumen y Cotización'!L19 -> SIN CUBIERTA | D3: Multiplicador | E3: 4 | G3: Módulos aplicables | H3: =COUNTIF(C7:C54,"SÍ") -> 19
A4: Costo por ML | B4: =IFERROR(_xlfn.XLOOKUP(B3,'⚙️ Configuración Costos'!$A$23:$A$25,'⚙️ Configuración Costos'!$B$23:$B$25),0) -> 0 | D4: Largo real seleccionado | E4: {=SUMPRODUCT('📊 Resumen y Cotización'!$A$13:$A$60,$D$7:$D$54,--($C$7:$C$54="SÍ"))} -> 2.25 | G4: Venta seleccionada | H4: =SUMPRODUCT('📊 Resumen y Cotización'!$A$13:$A$60,$F$7:$F$54) -> 0
A5: Estado | B5: =IF(B3="SIN CUBIERTA","○ SIN CUBIERTA",IF(B4>0,"✓ PRECIO CONFIGURADO","⚠ REVISAR CONFIGURACIÓN")) -> ○ SIN CUBIERTA | D5: Largo cobrable | E5: =IF(E4=0,0,ROUNDUP(E4/1.2,0)*1.2) -> 2.4 | G5: Costo seleccionado | H5: =SUMPRODUCT('📊 Resumen y Cotización'!$A$13:$A$60,$E$7:$E$54) -> 0
A6: ID Módulo | B6: Mueble | C6: Aplica | D6: Ancho (m) | E6: Costo cubierta | F6: Precio cubierta
A7: ='📊 Resumen y Cotización'!B13 -> ALA-RIN-656832 | B7: ='📊 Resumen y Cotización'!C13 -> Alacena Rinconera 650 x 680 x 320 mm | C7: =IF(OR(LEFT(A7,4)="GAB-",LEFT(A7,4)="TAR-"),"SÍ","NO") -> NO | D7: 0 | E7: =IF(AND(C7="SÍ",$B$3<>"SIN CUBIERTA",$E$4>0),D7*$B$4*($E$5/$E$4),0) -> 0 | F7: =E7*$E$3 -> 0
A8: ='📊 Resumen y Cotización'!B14 -> ALA-1PU-306832 | B8: ='📊 Resumen y Cotización'!C14 -> Alacena 1 Puerta 300 x 680 x 320 mm | C8: =IF(OR(LEFT(A8,4)="GAB-",LEFT(A8,4)="TAR-"),"SÍ","NO") -> NO | D8: 0 | E8: =IF(AND(C8="SÍ",$B$3<>"SIN CUBIERTA",$E$4>0),D8*$B$4*($E$5/$E$4),0) -> 0 | F8: =E8*$E$3 -> 0
A9: ='📊 Resumen y Cotización'!B15 -> ALA-1PU-406832 | B9: ='📊 Resumen y Cotización'!C15 -> Alacena 1 Puerta 400 x 680 x 320 mm | C9: =IF(OR(LEFT(A9,4)="GAB-",LEFT(A9,4)="TAR-"),"SÍ","NO") -> NO | D9: 0 | E9: =IF(AND(C9="SÍ",$B$3<>"SIN CUBIERTA",$E$4>0),D9*$B$4*($E$5/$E$4),0) -> 0 | F9: =E9*$E$3 -> 0
A10: ='📊 Resumen y Cotización'!B16 -> ALA-1PU-506832 | B10: ='📊 Resumen y Cotización'!C16 -> Alacena 1 Puerta 500 x 680 x 320 mm | C10: =IF(OR(LEFT(A10,4)="GAB-",LEFT(A10,4)="TAR-"),"SÍ","NO") -> NO | D10: 0 | E10: =IF(AND(C10="SÍ",$B$3<>"SIN CUBIERTA",$E$4>0),D10*$B$4*($E$5/$E$4),0) -> 0 | F10: =E10*$E$3 -> 0
A11: ='📊 Resumen y Cotización'!B17 -> ALA-1PU-606832 | B11: ='📊 Resumen y Cotización'!C17 -> Alacena 1 Puerta 600 x 680 x 320 mm | C11: =IF(OR(LEFT(A11,4)="GAB-",LEFT(A11,4)="TAR-"),"SÍ","NO") -> NO | D11: 0 | E11: =IF(AND(C11="SÍ",$B$3<>"SIN CUBIERTA",$E$4>0),D11*$B$4*($E$5/$E$4),0) -> 0 | F11: =E11*$E$3 -> 0
A12: ='📊 Resumen y Cotización'!B18 -> ALA-2PU-706832 | B12: ='📊 Resumen y Cotización'!C18 -> Alacena 2 Puertas 700 x 680 x 320 mm | C12: =IF(OR(LEFT(A12,4)="GAB-",LEFT(A12,4)="TAR-"),"SÍ","NO") -> NO | D12: 0 | E12: =IF(AND(C12="SÍ",$B$3<>"SIN CUBIERTA",$E$4>0),D12*$B$4*($E$5/$E$4),0) -> 0 | F12: =E12*$E$3 -> 0
A13: ='📊 Resumen y Cotización'!B19 -> ALA-2PU-806832 | B13: ='📊 Resumen y Cotización'!C19 -> Alacena 2 Puertas 800 x 680 x 320 mm | C13: =IF(OR(LEFT(A13,4)="GAB-",LEFT(A13,4)="TAR-"),"SÍ","NO") -> NO | D13: 0 | E13: =IF(AND(C13="SÍ",$B$3<>"SIN CUBIERTA",$E$4>0),D13*$B$4*($E$5/$E$4),0) -> 0 | F13: =E13*$E$3 -> 0
A14: ='📊 Resumen y Cotización'!B20 -> ALA-2PU-906832 | B14: ='📊 Resumen y Cotización'!C20 -> Alacena 2 Puertas 900 x 680 x 320 mm | C14: =IF(OR(LEFT(A14,4)="GAB-",LEFT(A14,4)="TAR-"),"SÍ","NO") -> NO | D14: 0 | E14: =IF(AND(C14="SÍ",$B$3<>"SIN CUBIERTA",$E$4>0),D14*$B$4*($E$5/$E$4),0) -> 0 | F14: =E14*$E$3 -> 0
A15: ='📊 Resumen y Cotización'!B21 -> ALA-BAS-503432 | B15: ='📊 Resumen y Cotización'!C21 -> Alacena Basculante 500 x 340 x 320 mm | C15: =IF(OR(LEFT(A15,4)="GAB-",LEFT(A15,4)="TAR-"),"SÍ","NO") -> NO | D15: 0 | E15: =IF(AND(C15="SÍ",$B$3<>"SIN CUBIERTA",$E$4>0),D15*$B$4*($E$5/$E$4),0) -> 0 | F15: =E15*$E$3 -> 0
A16: ='📊 Resumen y Cotización'!B22 -> ALA-BAS-603432 | B16: ='📊 Resumen y Cotización'!C22 -> Alacena Basculante 600 x 340 x 320 mm | C16: =IF(OR(LEFT(A16,4)="GAB-",LEFT(A16,4)="TAR-"),"SÍ","NO") -> NO | D16: 0 | E16: =IF(AND(C16="SÍ",$B$3<>"SIN CUBIERTA",$E$4>0),D16*$B$4*($E$5/$E$4),0) -> 0 | F16: =E16*$E$3 -> 0
A17: ='📊 Resumen y Cotización'!B23 -> ALA-BAS-703432 | B17: ='📊 Resumen y Cotización'!C23 -> Alacena Basculante 700 x 340 x 320 mm | C17: =IF(OR(LEFT(A17,4)="GAB-",LEFT(A17,4)="TAR-"),"SÍ","NO") -> NO | D17: 0 | E17: =IF(AND(C17="SÍ",$B$3<>"SIN CUBIERTA",$E$4>0),D17*$B$4*($E$5/$E$4),0) -> 0 | F17: =E17*$E$3 -> 0
A18: ='📊 Resumen y Cotización'!B24 -> ALA-BAS-803432 | B18: ='📊 Resumen y Cotización'!C24 -> Alacena Basculante 800 x 340 x 320 mm | C18: =IF(OR(LEFT(A18,4)="GAB-",LEFT(A18,4)="TAR-"),"SÍ","NO") -> NO | D18: 0 | E18: =IF(AND(C18="SÍ",$B$3<>"SIN CUBIERTA",$E$4>0),D18*$B$4*($E$5/$E$4),0) -> 0 | F18: =E18*$E$3 -> 0
... A45: ='📊 Resumen y Cotización'!B51 -> DES-HOR-7021058 | B45: ='📊 Resumen y Cotización'!C51 -> Torre Horno y Micro 700 x 2100 x 580 mm | C45: =IF(OR(LEFT(A45,4)="GAB-",LEFT(A45,4)="TAR-"),"SÍ","NO") -> NO | D45: 0 | E45: =IF(AND(C45="SÍ",$B$3<>"SIN CUBIERTA",$E$4>0),D45*$B$4*($E$5/$E$4),0) -> 0 | F45: =E45*$E$3 -> 0
A46: DES-HOR-3CA-6021058 | B46: Torre Horno y Micro c/Cajones 600 x 2100 x 580 mm | C46: NO | D46: 0 | E46: =IF(C46="SÍ",D46*$B$4,0) -> 0 | F46: =E46*$E$3 -> 0
A47: DES-HOR-3CA-7021058 | B47: Torre Horno y Micro c/Cajones 700 x 2100 x 580 mm | C47: NO | D47: 0 | E47: =IF(C47="SÍ",D47*$B$4,0) -> 0 | F47: =E47*$E$3 -> 0
A48: ='📊 Resumen y Cotización'!B54 -> DES-NIC-4021061 | B48: ='📊 Resumen y Cotización'!C54 -> Despensa Nicho 400 x 2100 x 610 mm | C48: =IF(OR(LEFT(A48,4)="GAB-",LEFT(A48,4)="TAR-"),"SÍ","NO") -> NO | D48: 0 | E48: =IF(AND(C48="SÍ",$B$3<>"SIN CUBIERTA",$E$4>0),D48*$B$4*($E$5/$E$4),0) -> 0 | F48: =E48*$E$3 -> 0
A49: ='📊 Resumen y Cotización'!B55 -> PAN-ALA-3434 | B49: ='📊 Resumen y Cotización'!C55 -> Panel Alacena 340 x 340 mm | C49: =IF(OR(LEFT(A49,4)="GAB-",LEFT(A49,4)="TAR-"),"SÍ","NO") -> NO | D49: 0 | E49: =IF(AND(C49="SÍ",$B$3<>"SIN CUBIERTA",$E$4>0),D49*$B$4*($E$5/$E$4),0) -> 0 | F49: =E49*$E$3 -> 0
A50: ='📊 Resumen y Cotización'!B56 -> PAN-ALA-6834 | B50: ='📊 Resumen y Cotización'!C56 -> Panel Alacena 680 x 340 mm | C50: =IF(OR(LEFT(A50,4)="GAB-",LEFT(A50,4)="TAR-"),"SÍ","NO") -> NO | D50: 0 | E50: =IF(AND(C50="SÍ",$B$3<>"SIN CUBIERTA",$E$4>0),D50*$B$4*($E$5/$E$4),0) -> 0 | F50: =E50*$E$3 -> 0
A51: ='📊 Resumen y Cotización'!B57 -> PAN-GAB-7261 | B51: ='📊 Resumen y Cotización'!C57 -> Panel Gabinete 720 x 610 mm | C51: =IF(OR(LEFT(A51,4)="GAB-",LEFT(A51,4)="TAR-"),"SÍ","NO") -> NO | D51: 0 | E51: =IF(AND(C51="SÍ",$B$3<>"SIN CUBIERTA",$E$4>0),D51*$B$4*($E$5/$E$4),0) -> 0 | F51: =E51*$E$3 -> 0
A52: ='📊 Resumen y Cotización'!B58 -> PAN-DES-21061 | B52: ='📊 Resumen y Cotización'!C58 -> Panel Despensa 2100 x 610 mm | C52: =IF(OR(LEFT(A52,4)="GAB-",LEFT(A52,4)="TAR-"),"SÍ","NO") -> NO | D52: 0 | E52: =IF(AND(C52="SÍ",$B$3<>"SIN CUBIERTA",$E$4>0),D52*$B$4*($E$5/$E$4),0) -> 0 | F52: =E52*$E$3 -> 0
A53: PAN-DES-21034 | B53: Panel Despensa 2100 x 340 mm | C53: NO | D53: 0 | E53: =IF(C53="SÍ",D53*$B$4,0) -> 0 | F53: =E53*$E$3 -> 0
A54: ='📊 Resumen y Cotización'!B60 -> ZOC-24015 | B54: ='📊 Resumen y Cotización'!C60 -> Zoclo 2400 x 150 mm | C54: =IF(OR(LEFT(A54,4)="GAB-",LEFT(A54,4)="TAR-"),"SÍ","NO") -> NO | D54: 0 | E54: =IF(AND(C54="SÍ",$B$3<>"SIN CUBIERTA",$E$4>0),D54*$B$4*($E$5/$E$4),0) -> 0 | F54: =E54*$E$3 -> 0

Sheet 📋 Explosión y Despiece Bla
A1: Cantidad | B1: Largo (mm) | C1: Ancho (mm) | D1: Descripción de la Pieza / Módulo | E1: Materia Prima | F1: Veta | G1: Largo 1 | H1: Largo 2 | I1: Ancho 1 | J1: Ancho 2 | K1: Codigo | L1: Código Pieza | M1: M² Totales | N1: ML Cintilla | O1: Costo Unit. Mat/Herr | P1: Costo Tot. Mat/Herr | Q1: Costo Unit. Cintilla | R1: Costo Tot. Cintilla | S1: Costo Total Elemento | T1: Validación | U1: Detalle de alerta | V1: Alerta
A2: Alacena Rinconera 650 x 680 x 320 mm
A3: 1 | B3: 680 | C3: 320 | D3: Lateral Derecho | E3: ARAUCO BLANCO | F3: 0 | G3: 1 | H3: 1 | I3: 1 | J3: 1 | K3: ALA-RIN-656832 | L3: LAT-ALA-6832-D | M3: =IF(AND(ISNUMBER(B3),ISNUMBER(C3),B3>0,C3>0),A3*(B3*C3/1000000),0) -> 0.2176 | N3: =IF(AND(ISNUMBER(B3),B3>0),A3*(((G3+H3)*B3+(I3+J3)*C3)/1000),0) -> 2 | O3: =IF(E3="HERRAJE",IFERROR(_xlfn.XLOOKUP(D3,'⚙️ Configuración Costos'!$A$11:$A$20,'⚙️ Configuración Costos'!$B$11:$B$20),""),IFERROR(_xlfn.XLOOKUP(E3,'⚙️ Configuración Costos'!$A$5:$A$6,'⚙️ Configuración Costos'!$B$5:$B$6),"")) -> 239.84262 | P3: =IF(E3="HERRAJE",A3*O3,M3*O3) -> 52.189755 | Q3: =IF(E3="HERRAJE",0,IFERROR(_xlfn.XLOOKUP(E3,'⚙️ Configuración Costos'!$E$5:$E$6,'⚙️ Configuración Costos'!$F$5:$F$6),"")) -> 6 | R3: =N3*Q3 -> 12 | S3: =P3+R3 -> 64.189755 | T3: =IF(K3="","SIN ID MÓDULO",IF(E3="HERRAJE",IF(OR(O3="",O3<=0),"SIN PRECIO HERRAJE","OK"),IF(OR(O3="",O3<=0),"SIN PRECIO MATERIAL",IF(AND(N3>0,OR(Q3="",Q3<=0)),"SIN PRECIO CINTILLA","OK")))) -> OK | U3: =IF(T3="OK","",IF(T3="SIN PRECIO HERRAJE","Capturar precio: "&D3,IF(T3="SIN PRECIO MATERIAL","Configurar material: "&E3,IF(T3="SIN PRECIO CINTILLA","Configurar cintilla: "&E3,IF(T3="SIN ID MÓDULO","Revisar ID del módulo",""))))) | V3: =IF(T3="OK",0,IF(T3="",0,1)) -> 0
A4: 1 | B4: 680 | C4: 320 | D4: Lateral Izquierdo | E4: ARAUCO BLANCO | F4: 0 | G4: 1 | H4: 1 | I4: 1 | J4: 1 | K4: ALA-RIN-656832 | L4: LAT-ALA-6832-I | M4: =IF(AND(ISNUMBER(B4),ISNUMBER(C4),B4>0,C4>0),A4*(B4*C4/1000000),0) -> 0.2176 | N4: =IF(AND(ISNUMBER(B4),B4>0),A4*(((G4+H4)*B4+(I4+J4)*C4)/1000),0) -> 2 | O4: =IF(E4="HERRAJE",IFERROR(_xlfn.XLOOKUP(D4,'⚙️ Configuración Costos'!$A$11:$A$20,'⚙️ Configuración Costos'!$B$11:$B$20),""),IFERROR(_xlfn.XLOOKUP(E4,'⚙️ Configuración Costos'!$A$5:$A$6,'⚙️ Configuración Costos'!$B$5:$B$6),"")) -> 239.84262 | P4: =IF(E4="HERRAJE",A4*O4,M4*O4) -> 52.189755 | Q4: =IF(E4="HERRAJE",0,IFERROR(_xlfn.XLOOKUP(E4,'⚙️ Configuración Costos'!$E$5:$E$6,'⚙️ Configuración Costos'!$F$5:$F$6),"")) -> 6 | R4: =N4*Q4 -> 12 | S4: =P4+R4 -> 64.189755 | T4: =IF(K4="","SIN ID MÓDULO",IF(E4="HERRAJE",IF(OR(O4="",O4<=0),"SIN PRECIO HERRAJE","OK"),IF(OR(O4="",O4<=0),"SIN PRECIO MATERIAL",IF(AND(N4>0,OR(Q4="",Q4<=0)),"SIN PRECIO CINTILLA","OK")))) -> OK | U4: =IF(T4="OK","",IF(T4="SIN PRECIO HERRAJE","Capturar precio: "&D4,IF(T4="SIN PRECIO MATERIAL","Configurar material: "&E4,IF(T4="SIN PRECIO CINTILLA","Configurar cintilla: "&E4,IF(T4="SIN ID MÓDULO","Revisar ID del módulo",""))))) | V4: =IF(T4="OK",0,IF(T4="",0,1)) -> 0
A5: 1 | B5: 649 | C5: 619 | D5: Respaldo Alacena | E5: ARAUCO BLANCO | F5: 0 | G5: 0 | H5: 0 | I5: 0 | J5: 0 | K5: ALA-RIN-656832 | L5: RES-ALA-6865 | M5: =IF(AND(ISNUMBER(B5),ISNUMBER(C5),B5>0,C5>0),A5*(B5*C5/1000000),0) -> 0.401731 | N5: =IF(AND(ISNUMBER(B5),B5>0),A5*(((G5+H5)*B5+(I5+J5)*C5)/1000),0) -> 0 | O5: =IF(E5="HERRAJE",IFERROR(_xlfn.XLOOKUP(D5,'⚙️ Configuración Costos'!$A$11:$A$20,'⚙️ Configuración Costos'!$B$11:$B$20),""),IFERROR(_xlfn.XLOOKUP(E5,'⚙️ Configuración Costos'!$A$5:$A$6,'⚙️ Configuración Costos'!$B$5:$B$6),"")) -> 239.84262 | P5: =IF(E5="HERRAJE",A5*O5,M5*O5) -> 96.352217 | Q5: =IF(E5="HERRAJE",0,IFERROR(_xlfn.XLOOKUP(E5,'⚙️ Configuración Costos'!$E$5:$E$6,'⚙️ Configuración Costos'!$F$5:$F$6),"")) -> 6 | R5: =N5*Q5 -> 0 | S5: =P5+R5 -> 96.352217 | T5: =IF(K5="","SIN ID MÓDULO",IF(E5="HERRAJE",IF(OR(O5="",O5<=0),"SIN PRECIO HERRAJE","OK"),IF(OR(O5="",O5<=0),"SIN PRECIO MATERIAL",IF(AND(N5>0,OR(Q5="",Q5<=0)),"SIN PRECIO CINTILLA","OK")))) -> OK | U5: =IF(T5="OK","",IF(T5="SIN PRECIO HERRAJE","Capturar precio: "&D5,IF(T5="SIN PRECIO MATERIAL","Configurar material: "&E5,IF(T5="SIN PRECIO CINTILLA","Configurar cintilla: "&E5,IF(T5="SIN ID MÓDULO","Revisar ID del módulo",""))))) | V5: =IF(T5="OK",0,IF(T5="",0,1)) -> 0
A6: 1 | B6: 619 | C6: 320 | D6: Base Alacena | E6: ARAUCO BLANCO | F6: 0 | G6: 1 | H6: 1 | I6: 0 | J6: 0 | K6: ALA-RIN-656832 | L6: BAS-ALA-6532 | M6: =IF(AND(ISNUMBER(B6),ISNUMBER(C6),B6>0,C6>0),A6*(B6*C6/1000000),0) -> 0.19808 | N6: =IF(AND(ISNUMBER(B6),B6>0),A6*(((G6+H6)*B6+(I6+J6)*C6)/1000),0) -> 1.238 | O6: =IF(E6="HERRAJE",IFERROR(_xlfn.XLOOKUP(D6,'⚙️ Configuración Costos'!$A$11:$A$20,'⚙️ Configuración Costos'!$B$11:$B$20),""),IFERROR(_xlfn.XLOOKUP(E6,'⚙️ Configuración Costos'!$A$5:$A$6,'⚙️ Configuración Costos'!$B$5:$B$6),"")) -> 239.84262 | P6: =IF(E6="HERRAJE",A6*O6,M6*O6) -> 47.508027 | Q6: =IF(E6="HERRAJE",0,IFERROR(_xlfn.XLOOKUP(E6,'⚙️ Configuración Costos'!$E$5:$E$6,'⚙️ Configuración Costos'!$F$5:$F$6),"")) -> 6 | R6: =N6*Q6 -> 7.428 | S6: =P6+R6 -> 54.936027 | T6: =IF(K6="","SIN ID MÓDULO",IF(E6="HERRAJE",IF(OR(O6="",O6<=0),"SIN PRECIO HERRAJE","OK"),IF(OR(O6="",O6<=0),"SIN PRECIO MATERIAL",IF(AND(N6>0,OR(Q6="",Q6<=0)),"SIN PRECIO CINTILLA","OK")))) -> OK | U6: =IF(T6="OK","",IF(T6="SIN PRECIO HERRAJE","Capturar precio: "&D6,IF(T6="SIN PRECIO MATERIAL","Configurar material: "&E6,IF(T6="SIN PRECIO CINTILLA","Configurar cintilla: "&E6,IF(T6="SIN ID MÓDULO","Revisar ID del módulo",""))))) | V6: =IF(T6="OK",0,IF(T6="",0,1)) -> 0
A7: 1 | B7: 619 | C7: 320 | D7: Techo Alacena | E7: ARAUCO BLANCO | F7: 0 | G7: 1 | H7: 1 | I7: 0 | J7: 0 | K7: ALA-RIN-656832 | L7: TEC-ALA-6532 | M7: =IF(AND(ISNUMBER(B7),ISNUMBER(C7),B7>0,C7>0),A7*(B7*C7/1000000),0) -> 0.19808 | N7: =IF(AND(ISNUMBER(B7),B7>0),A7*(((G7+H7)*B7+(I7+J7)*C7)/1000),0) -> 1.238 | O7: =IF(E7="HERRAJE",IFERROR(_xlfn.XLOOKUP(D7,'⚙️ Configuración Costos'!$A$11:$A$20,'⚙️ Configuración Costos'!$B$11:$B$20),""),IFERROR(_xlfn.XLOOKUP(E7,'⚙️ Configuración Costos'!$A$5:$A$6,'⚙️ Configuración Costos'!$B$5:$B$6),"")) -> 239.84262 | P7: =IF(E7="HERRAJE",A7*O7,M7*O7) -> 47.508027 | Q7: =IF(E7="HERRAJE",0,IFERROR(_xlfn.XLOOKUP(E7,'⚙️ Configuración Costos'!$E$5:$E$6,'⚙️ Configuración Costos'!$F$5:$F$6),"")) -> 6 | R7: =N7*Q7 -> 7.428 | S7: =P7+R7 -> 54.936027 | T7: =IF(K7="","SIN ID MÓDULO",IF(E7="HERRAJE",IF(OR(O7="",O7<=0),"SIN PRECIO HERRAJE","OK"),IF(OR(O7="",O7<=0),"SIN PRECIO MATERIAL",IF(AND(N7>0,OR(Q7="",Q7<=0)),"SIN PRECIO CINTILLA","OK")))) -> OK | U7: =IF(T7="OK","",IF(T7="SIN PRECIO HERRAJE","Capturar precio: "&D7,IF(T7="SIN PRECIO MATERIAL","Configurar material: "&E7,IF(T7="SIN PRECIO CINTILLA","Configurar cintilla: "&E7,IF(T7="SIN ID MÓDULO","Revisar ID del módulo",""))))) | V7: =IF(T7="OK",0,IF(T7="",0,1)) -> 0
A8: 1 | B8: 649 | C8: 339 | D8: Tapa Ciega | E8: ARAUCO BLANCO | F8: 0 | G8: 0 | H8: 0 | I8: 0 | J8: 0 | K8: ALA-RIN-656832 | L8: TAP-ALA-6534 | M8: =IF(AND(ISNUMBER(B8),ISNUMBER(C8),B8>0,C8>0),A8*(B8*C8/1000000),0) -> 0.220011 | N8: =IF(AND(ISNUMBER(B8),B8>0),A8*(((G8+H8)*B8+(I8+J8)*C8)/1000),0) -> 0 | O8: =IF(E8="HERRAJE",IFERROR(_xlfn.XLOOKUP(D8,'⚙️ Configuración Costos'!$A$11:$A$20,'⚙️ Configuración Costos'!$B$11:$B$20),""),IFERROR(_xlfn.XLOOKUP(E8,'⚙️ Configuración Costos'!$A$5:$A$6,'⚙️ Configuración Costos'!$B$5:$B$6),"")) -> 239.84262 | P8: =IF(E8="HERRAJE",A8*O8,M8*O8) -> 52.768015 | Q8: =IF(E8="HERRAJE",0,IFERROR(_xlfn.XLOOKUP(E8,'⚙️ Configuración Costos'!$E$5:$E$6,'⚙️ Configuración Costos'!$F$5:$F$6),"")) -> 6 | R8: =N8*Q8 -> 0 | S8: =P8+R8 -> 52.768015 | T8: =IF(K8="","SIN ID MÓDULO",IF(E8="HERRAJE",IF(OR(O8="",O8<=0),"SIN PRECIO HERRAJE","OK"),IF(OR(O8="",O8<=0),"SIN PRECIO MATERIAL",IF(AND(N8>0,OR(Q8="",Q8<=0)),"SIN PRECIO CINTILLA","OK")))) -> OK | U8: =IF(T8="OK","",IF(T8="SIN PRECIO HERRAJE","Capturar precio: "&D8,IF(T8="SIN PRECIO MATERIAL","Configurar material: "&E8,IF(T8="SIN PRECIO CINTILLA","Configurar cintilla: "&E8,IF(T8="SIN ID MÓDULO","Revisar ID del módulo",""))))) | V8: =IF(T8="OK",0,IF(T8="",0,1)) -> 0
A9: 1 | B9: 619 | C9: 256 | D9: Entrepano Alacena | E9: ARAUCO BLANCO | F9: 0 | G9: 1 | H9: 0 | I9: 0 | J9: 0 | K9: ALA-RIN-656832 | L9: ENT-ALA-6526 | M9: =IF(AND(ISNUMBER(B9),ISNUMBER(C9),B9>0,C9>0),A9*(B9*C9/1000000),0) -> 0.158464 | N9: =IF(AND(ISNUMBER(B9),B9>0),A9*(((G9+H9)*B9+(I9+J9)*C9)/1000),0) -> 0.619 | O9: =IF(E9="HERRAJE",IFERROR(_xlfn.XLOOKUP(D9,'⚙️ Configuración Costos'!$A$11:$A$20,'⚙️ Configuración Costos'!$B$11:$B$20),""),IFERROR(_xlfn.XLOOKUP(E9,'⚙️ Configuración Costos'!$A$5:$A$6,'⚙️ Configuración Costos'!$B$5:$B$6),"")) -> 239.84262 | P9: =IF(E9="HERRAJE",A9*O9,M9*O9) -> 38.006421 | Q9: =IF(E9="HERRAJE",0,IFERROR(_xlfn.XLOOKUP(E9,'⚙️ Configuración Costos'!$E$5:$E$6,'⚙️ Configuración Costos'!$F$5:$F$6),"")) -> 6 | R9: =N9*Q9 -> 3.714 | S9: =P9+R9 -> 41.720421 | T9: =IF(K9="","SIN ID MÓDULO",IF(E9="HERRAJE",IF(OR(O9="",O9<=0),"SIN PRECIO HERRAJE","OK"),IF(OR(O9="",O9<=0),"SIN PRECIO MATERIAL",IF(AND(N9>0,OR(Q9="",Q9<=0)),"SIN PRECIO CINTILLA","OK")))) -> OK | U9: =IF(T9="OK","",IF(T9="SIN PRECIO HERRAJE","Capturar precio: "&D9,IF(T9="SIN PRECIO MATERIAL","Configurar material: "&E9,IF(T9="SIN PRECIO CINTILLA","Configurar cintilla: "&E9,IF(T9="SIN ID MÓDULO","Revisar ID del módulo",""))))) | V9: =IF(T9="OK",0,IF(T9="",0,1)) -> 0
A10: 1 | B10: 649 | C10: 70 | D10: Refuerzo Bisagra | E10: ARAUCO BLANCO | F10: 0 | G10: 1 | H10: 1 | I10: 0 | J10: 0 | K10: ALA-RIN-656832 | L10: REF-BIS-ALA-657 | M10: =IF(AND(ISNUMBER(B10),ISNUMBER(C10),B10>0,C10>0),A10*(B10*C10/1000000),0) -> 0.04543 | N10: =IF(AND(ISNUMBER(B10),B10>0),A10*(((G10+H10)*B10+(I10+J10)*C10)/1000),0) -> 1.298 | O10: =IF(E10="HERRAJE",IFERROR(_xlfn.XLOOKUP(D10,'⚙️ Configuración Costos'!$A$11:$A$20,'⚙️ Configuración Costos'!$B$11:$B$20),""),IFERROR(_xlfn.XLOOKUP(E10,'⚙️ Configuración Costos'!$A$5:$A$6,'⚙️ Configuración Costos'!$B$5:$B$6),"")) -> 239.84262 | P10: =IF(E10="HERRAJE",A10*O10,M10*O10) -> 10.89605 | Q10: =IF(E10="HERRAJE",0,IFERROR(_xlfn.XLOOKUP(E10,'⚙️ Configuración Costos'!$E$5:$E$6,'⚙️ Configuración Costos'!$F$5:$F$6),"")) -> 6 | R10: =N10*Q10 -> 7.788 | S10: =P10+R10 -> 18.68405 | T10: =IF(K10="","SIN ID MÓDULO",IF(E10="HERRAJE",IF(OR(O10="",O10<=0),"SIN PRECIO HERRAJE","OK"),IF(OR(O10="",O10<=0),"SIN PRECIO MATERIAL",IF(AND(N10>0,OR(Q10="",Q10<=0)),"SIN PRECIO CINTILLA","OK")))) -> OK | U10: =IF(T10="OK","",IF(T10="SIN PRECIO HERRAJE","Capturar precio: "&D10,IF(T10="SIN PRECIO MATERIAL","Configurar material: "&E10,IF(T10="SIN PRECIO CINTILLA","Configurar cintilla: "&E10,IF(T10="SIN ID MÓDULO","Revisar ID del módulo",""))))) | V10: =IF(T10="OK",0,IF(T10="",0,1)) -> 0
A11: 1 | B11: 320 | C11: 50 | D11: Ajuste Inferior | E11: ARAUCO BLANCO | F11: 0 | G11: 0 | H11: 0 | I11: 1 | J11: 1 | K11: ALA-RIN-656832 | L11: AJU-INF-ALA-325 | M11: =IF(AND(ISNUMBER(B11),ISNUMBER(C11),B11>0,C11>0),A11*(B11*C11/1000000),0) -> 0.016 | N11: =IF(AND(ISNUMBER(B11),B11>0),A11*(((G11+H11)*B11+(I11+J11)*C11)/1000),0) -> 0.1 | O11: =IF(E11="HERRAJE",IFERROR(_xlfn.XLOOKUP(D11,'⚙️ Configuración Costos'!$A$11:$A$20,'⚙️ Configuración Costos'!$B$11:$B$20),""),IFERROR(_xlfn.XLOOKUP(E11,'⚙️ Configuración Costos'!$A$5:$A$6,'⚙️ Configuración Costos'!$B$5:$B$6),"")) -> 239.84262 | P11: =IF(E11="HERRAJE",A11*O11,M11*O11) -> 3.837482 | Q11: =IF(E11="HERRAJE",0,IFERROR(_xlfn.XLOOKUP(E11,'⚙️ Configuración Costos'!$E$5:$E$6,'⚙️ Configuración Costos'!$F$5:$F$6),"")) -> 6 | R11: =N11*Q11 -> 0.6 | S11: =P11+R11 -> 4.437482 | T11: =IF(K11="","SIN ID MÓDULO",IF(E11="HERRAJE",IF(OR(O11="",O11<=0),"SIN PRECIO HERRAJE","OK"),IF(OR(O11="",O11<=0),"SIN PRECIO MATERIAL",IF(AND(N11>0,OR(Q11="",Q11<=0)),"SIN PRECIO CINTILLA","OK")))) -> OK | U11: =IF(T11="OK","",IF(T11="SIN PRECIO HERRAJE","Capturar precio: "&D11,IF(T11="SIN PRECIO MATERIAL","Configurar material: "&E11,IF(T11="SIN PRECIO CINTILLA","Configurar cintilla: "&E11,IF(T11="SIN ID MÓDULO","Revisar ID del módulo",""))))) | V11: =IF(T11="OK",0,IF(T11="",0,1)) -> 0
A12: 1 | B12: 320 | C12: 50 | D12: Ajuste superior | E12: ARAUCO BLANCO | F12: 0 | G12: 0 | H12: 0 | I12: 1 | J12: 1 | K12: ALA-RIN-656832 | L12: AJU-SUP-ALA-325 | M12: =IF(AND(ISNUMBER(B12),ISNUMBER(C12),B12>0,C12>0),A12*(B12*C12/1000000),0) -> 0.016 | N12: =IF(AND(ISNUMBER(B12),B12>0),A12*(((G12+H12)*B12+(I12+J12)*C12)/1000),0) -> 0.1 | O12: =IF(E12="HERRAJE",IFERROR(_xlfn.XLOOKUP(D12,'⚙️ Configuración Costos'!$A$11:$A$20,'⚙️ Configuración Costos'!$B$11:$B$20),""),IFERROR(_xlfn.XLOOKUP(E12,'⚙️ Configuración Costos'!$A$5:$A$6,'⚙️ Configuración Costos'!$B$5:$B$6),"")) -> 239.84262 | P12: =IF(E12="HERRAJE",A12*O12,M12*O12) -> 3.837482 | Q12: =IF(E12="HERRAJE",0,IFERROR(_xlfn.XLOOKUP(E12,'⚙️ Configuración Costos'!$E$5:$E$6,'⚙️ Configuración Costos'!$F$5:$F$6),"")) -> 6 | R12: =N12*Q12 -> 0.6 | S12: =P12+R12 -> 4.437482 | T12: =IF(K12="","SIN ID MÓDULO",IF(E12="HERRAJE",IF(OR(O12="",O12<=0),"SIN PRECIO HERRAJE","OK"),IF(OR(O12="",O12<=0),"SIN PRECIO MATERIAL",IF(AND(N12>0,OR(Q12="",Q12<=0)),"SIN PRECIO CINTILLA","OK")))) -> OK | U12: =IF(T12="OK","",IF(T12="SIN PRECIO HERRAJE","Capturar precio: "&D12,IF(T12="SIN PRECIO MATERIAL","Configurar material: "&E12,IF(T12="SIN PRECIO CINTILLA","Configurar cintilla: "&E12,IF(T12="SIN ID MÓDULO","Revisar ID del módulo",""))))) | V12: =IF(T12="OK",0,IF(T12="",0,1)) -> 0
A13: 1 | B13: 677 | C13: 292 | D13: Puerta Alacena | E13: VESTO NOUGAT | F13: 1 | G13: 1 | H13: 1 | I13: 1 | J13: 1 | K13: ALA-RIN-656832 | L13: PUE-ALA-6829 | M13: =IF(AND(ISNUMBER(B13),ISNUMBER(C13),B13>0,C13>0),A13*(B13*C13/1000000),0) -> 0.197684 | N13: =IF(AND(ISNUMBER(B13),B13>0),A13*(((G13+H13)*B13+(I13+J13)*C13)/1000),0) -> 1.938 | O13: =IF(E13="HERRAJE",IFERROR(_xlfn.XLOOKUP(D13,'⚙️ Configuración Costos'!$A$11:$A$20,'⚙️ Configuración Costos'!$B$11:$B$20),""),IFERROR(_xlfn.XLOOKUP(E13,'⚙️ Configuración Costos'!$A$5:$A$6,'⚙️ Configuración Costos'!$B$5:$B$6),"")) -> 332.85246 | P13: =IF(E13="HERRAJE",A13*O13,M13*O13) -> 65.799606 | Q13: =IF(E13="HERRAJE",0,IFERROR(_xlfn.XLOOKUP(E13,'⚙️ Configuración Costos'!$E$5:$E$6,'⚙️ Configuración Costos'!$F$5:$F$6),"")) -> 9.5 | R13: =N13*Q13 -> 18.411 | S13: =P13+R13 -> 84.210606 | T13: =IF(K13="","SIN ID MÓDULO",IF(E13="HERRAJE",IF(OR(O13="",O13<=0),"SIN PRECIO HERRAJE","OK"),IF(OR(O13="",O13<=0),"SIN PRECIO MATERIAL",IF(AND(N13>0,OR(Q13="",Q13<=0)),"SIN PRECIO CINTILLA","OK")))) -> OK | U13: =IF(T13="OK","",IF(T13="SIN PRECIO HERRAJE","Capturar precio: "&D13,IF(T13="SIN PRECIO MATERIAL","Configurar material: "&E13,IF(T13="SIN PRECIO CINTILLA","Configurar cintilla: "&E13,IF(T13="SIN ID MÓDULO","Revisar ID del módulo",""))))) | V13: =IF(T13="OK",0,IF(T13="",0,1)) -> 0
A14: 1 | B14: 677 | C14: 70 | D14: Ajuste 1 Rinconero | E14: VESTO NOUGAT | F14: 1 | G14: 1 | H14: 1 | I14: 1 | J14: 1 | K14: ALA-RIN-656832 | L14: AJU-RIN-ALA-687 | M14: =IF(AND(ISNUMBER(B14),ISNUMBER(C14),B14>0,C14>0),A14*(B14*C14/1000000),0) -> 0.04739 | N14: =IF(AND(ISNUMBER(B14),B14>0),A14*(((G14+H14)*B14+(I14+J14)*C14)/1000),0) -> 1.494 | O14: =IF(E14="HERRAJE",IFERROR(_xlfn.XLOOKUP(D14,'⚙️ Configuración Costos'!$A$11:$A$20,'⚙️ Configuración Costos'!$B$11:$B$20),""),IFERROR(_xlfn.XLOOKUP(E14,'⚙️ Configuración Costos'!$A$5:$A$6,'⚙️ Configuración Costos'!$B$5:$B$6),"")) -> 332.85246 | P14: =IF(E14="HERRAJE",A14*O14,M14*O14) -> 15.773878 | Q14: =IF(E14="HERRAJE",0,IFERROR(_xlfn.XLOOKUP(E14,'⚙️ Configuración Costos'!$E$5:$E$6,'⚙️ Configuración Costos'!$F$5:$F$6),"")) -> 9.5 | R14: =N14*Q14 -> 14.193 | S14: =P14+R14 -> 29.966878 | T14: =IF(K14="","SIN ID MÓDULO",IF(E14="HERRAJE",IF(OR(O14="",O14<=0),"SIN PRECIO HERRAJE","OK"),IF(OR(O14="",O14<=0),"SIN PRECIO MATERIAL",IF(AND(N14>0,OR(Q14="",Q14<=0)),"SIN PRECIO CINTILLA","OK")))) -> OK | U14: =IF(T14="OK","",IF(T14="SIN PRECIO HERRAJE","Capturar precio: "&D14,IF(T14="SIN PRECIO MATERIAL","Configurar material: "&E14,IF(T14="SIN PRECIO CINTILLA","Configurar cintilla: "&E14,IF(T14="SIN ID MÓDULO","Revisar ID del módulo",""))))) | V14: =IF(T14="OK",0,IF(T14="",0,1)) -> 0
... A19: 30 | B19: 0 | C19: 0 | D19: Tornillo 4x50 mm | E19: HERRAJE | F19: 0 | G19: 0 | H19: 0 | I19: 0 | J19: 0 | K19: ALA-RIN-656832 | L19: TOR-4X50 | M19: =IF(AND(ISNUMBER(B19),ISNUMBER(C19),B19>0,C19>0),A19*(B19*C19/1000000),0) -> 0 | N19: =IF(AND(ISNUMBER(B19),B19>0),A19*(((G19+H19)*B19+(I19+J19)*C19)/1000),0) -> 0 | O19: =IF(E19="HERRAJE",IFERROR(_xlfn.XLOOKUP(D19,'⚙️ Configuración Costos'!$A$11:$A$20,'⚙️ Configuración Costos'!$B$11:$B$20),""),IFERROR(_xlfn.XLOOKUP(E19,'⚙️ Configuración Costos'!$A$5:$A$6,'⚙️ Configuración Costos'!$B$5:$B$6),"")) -> 1.5 | P19: =IF(E19="HERRAJE",A19*O19,M19*O19) -> 45 | Q19: =IF(E19="HERRAJE",0,IFERROR(_xlfn.XLOOKUP(E19,'⚙️ Configuración Costos'!$E$5:$E$6,'⚙️ Configuración Costos'!$F$5:$F$6),"")) -> 0 | R19: =N19*Q19 -> 0 | S19: =P19+R19 -> 45 | T19: =IF(K19="","SIN ID MÓDULO",IF(E19="HERRAJE",IF(OR(O19="",O19<=0),"SIN PRECIO HERRAJE","OK"),IF(OR(O19="",O19<=0),"SIN PRECIO MATERIAL",IF(AND(N19>0,OR(Q19="",Q19<=0)),"SIN PRECIO CINTILLA","OK")))) -> OK | U19: =IF(T19="OK","",IF(T19="SIN PRECIO HERRAJE","Capturar precio: "&D19,IF(T19="SIN PRECIO MATERIAL","Configurar material: "&E19,IF(T19="SIN PRECIO CINTILLA","Configurar cintilla: "&E19,IF(T19="SIN ID MÓDULO","Revisar ID del módulo",""))))) | V19: =IF(T19="OK",0,IF(T19="",0,1)) -> 0
A20: TOTALES | M20: =SUM(M3:M19) -> 1.96792 | N20: =SUM(N3:N19) -> 13.479 | P20: =SUM(P3:P19) -> 605.93377 | R20: =SUM(R3:R19) -> 97.975 | S20: =SUM(S3:S19) -> 703.90877
A21: Alacena 1 Puerta 300 x 680 x 320 mm
A22: 1 | B22: 680 | C22: 320 | D22: Lateral Derecho | E22: ARAUCO BLANCO | F22: 0 | G22: 1 | H22: 1 | I22: 1 | J22: 1 | K22: ALA-1PU-306832 | L22: LAT-ALA-6832-D | M22: =IF(AND(ISNUMBER(B22),ISNUMBER(C22),B22>0,C22>0),A22*(B22*C22/1000000),0) -> 0.2176 | N22: =IF(AND(ISNUMBER(B22),B22>0),A22*(((G22+H22)*B22+(I22+J22)*C22)/1000),0) -> 2 | O22: =IF(E22="HERRAJE",IFERROR(_xlfn.XLOOKUP(D22,'⚙️ Configuración Costos'!$A$11:$A$20,'⚙️ Configuración Costos'!$B$11:$B$20),""),IFERROR(_xlfn.XLOOKUP(E22,'⚙️ Configuración Costos'!$A$5:$A$6,'⚙️ Configuración Costos'!$B$5:$B$6),"")) -> 239.84262 | P22: =IF(E22="HERRAJE",A22*O22,M22*O22) -> 52.189755 | Q22: =IF(E22="HERRAJE",0,IFERROR(_xlfn.XLOOKUP(E22,'⚙️ Configuración Costos'!$E$5:$E$6,'⚙️ Configuración Costos'!$F$5:$F$6),"")) -> 6 | R22: =N22*Q22 -> 12 | S22: =P22+R22 -> 64.189755 | T22: =IF(K22="","SIN ID MÓDULO",IF(E22="HERRAJE",IF(OR(O22="",O22<=0),"SIN PRECIO HERRAJE","OK"),IF(OR(O22="",O22<=0),"SIN PRECIO MATERIAL",IF(AND(N22>0,OR(Q22="",Q22<=0)),"SIN PRECIO CINTILLA","OK")))) -> OK | U22: =IF(T22="OK","",IF(T22="SIN PRECIO HERRAJE","Capturar precio: "&D22,IF(T22="SIN PRECIO MATERIAL","Configurar material: "&E22,IF(T22="SIN PRECIO CINTILLA","Configurar cintilla: "&E22,IF(T22="SIN ID MÓDULO","Revisar ID del módulo",""))))) | V22: =IF(T22="OK",0,IF(T22="",0,1)) -> 0
A23: 1 | B23: 680 | C23: 320 | D23: Lateral Izquierdo | E23: ARAUCO BLANCO | F23: 0 | G23: 1 | H23: 1 | I23: 1 | J23: 1 | K23: ALA-1PU-306832 | L23: LAT-ALA-6832-I | M23: =IF(AND(ISNUMBER(B23),ISNUMBER(C23),B23>0,C23>0),A23*(B23*C23/1000000),0) -> 0.2176 | N23: =IF(AND(ISNUMBER(B23),B23>0),A23*(((G23+H23)*B23+(I23+J23)*C23)/1000),0) -> 2 | O23: =IF(E23="HERRAJE",IFERROR(_xlfn.XLOOKUP(D23,'⚙️ Configuración Costos'!$A$11:$A$20,'⚙️ Configuración Costos'!$B$11:$B$20),""),IFERROR(_xlfn.XLOOKUP(E23,'⚙️ Configuración Costos'!$A$5:$A$6,'⚙️ Configuración Costos'!$B$5:$B$6),"")) -> 239.84262 | P23: =IF(E23="HERRAJE",A23*O23,M23*O23) -> 52.189755 | Q23: =IF(E23="HERRAJE",0,IFERROR(_xlfn.XLOOKUP(E23,'⚙️ Configuración Costos'!$E$5:$E$6,'⚙️ Configuración Costos'!$F$5:$F$6),"")) -> 6 | R23: =N23*Q23 -> 12 | S23: =P23+R23 -> 64.189755 | T23: =IF(K23="","SIN ID MÓDULO",IF(E23="HERRAJE",IF(OR(O23="",O23<=0),"SIN PRECIO HERRAJE","OK"),IF(OR(O23="",O23<=0),"SIN PRECIO MATERIAL",IF(AND(N23>0,OR(Q23="",Q23<=0)),"SIN PRECIO CINTILLA","OK")))) -> OK | U23: =IF(T23="OK","",IF(T23="SIN PRECIO HERRAJE","Capturar precio: "&D23,IF(T23="SIN PRECIO MATERIAL","Configurar material: "&E23,IF(T23="SIN PRECIO CINTILLA","Configurar cintilla: "&E23,IF(T23="SIN ID MÓDULO","Revisar ID del módulo",""))))) | V23: =IF(T23="OK",0,IF(T23="",0,1)) -> 0
A24: 1 | B24: 649 | C24: 269 | D24: Respaldo Alacena | E24: ARAUCO BLANCO | F24: 0 | G24: 0 | H24: 0 | I24: 0 | J24: 0 | K24: ALA-1PU-306832 | L24: RES-ALA-6830 | M24: =IF(AND(ISNUMBER(B24),ISNUMBER(C24),B24>0,C24>0),A24*(B24*C24/1000000),0) -> 0.174581 | N24: =IF(AND(ISNUMBER(B24),B24>0),A24*(((G24+H24)*B24+(I24+J24)*C24)/1000),0) -> 0 | O24: =IF(E24="HERRAJE",IFERROR(_xlfn.XLOOKUP(D24,'⚙️ Configuración Costos'!$A$11:$A$20,'⚙️ Configuración Costos'!$B$11:$B$20),""),IFERROR(_xlfn.XLOOKUP(E24,'⚙️ Configuración Costos'!$A$5:$A$6,'⚙️ Configuración Costos'!$B$5:$B$6),"")) -> 239.84262 | P24: =IF(E24="HERRAJE",A24*O24,M24*O24) -> 41.871965 | Q24: =IF(E24="HERRAJE",0,IFERROR(_xlfn.XLOOKUP(E24,'⚙️ Configuración Costos'!$E$5:$E$6,'⚙️ Configuración Costos'!$F$5:$F$6),"")) -> 6 | R24: =N24*Q24 -> 0 | S24: =P24+R24 -> 41.871965 | T24: =IF(K24="","SIN ID MÓDULO",IF(E24="HERRAJE",IF(OR(O24="",O24<=0),"SIN PRECIO HERRAJE","OK"),IF(OR(O24="",O24<=0),"SIN PRECIO MATERIAL",IF(AND(N24>0,OR(Q24="",Q24<=0)),"SIN PRECIO CINTILLA","OK")))) -> OK | U24: =IF(T24="OK","",IF(T24="SIN PRECIO HERRAJE","Capturar precio: "&D24,IF(T24="SIN PRECIO MATERIAL","Configurar material: "&E24,IF(T24="SIN PRECIO CINTILLA","Configurar cintilla: "&E24,IF(T24="SIN ID MÓDULO","Revisar ID del módulo",""))))) | V24: =IF(T24="OK",0,IF(T24="",0,1)) -> 0
A25: 1 | B25: 269 | C25: 320 | D25: Base Alacena | E25: ARAUCO BLANCO | F25: 0 | G25: 0 | H25: 0 | I25: 1 | J25: 1 | K25: ALA-1PU-306832 | L25: BAS-ALA-3027 | M25: =IF(AND(ISNUMBER(B25),ISNUMBER(C25),B25>0,C25>0),A25*(B25*C25/1000000),0) -> 0.08608 | N25: =IF(AND(ISNUMBER(B25),B25>0),A25*(((G25+H25)*B25+(I25+J25)*C25)/1000),0) -> 0.64 | O25: =IF(E25="HERRAJE",IFERROR(_xlfn.XLOOKUP(D25,'⚙️ Configuración Costos'!$A$11:$A$20,'⚙️ Configuración Costos'!$B$11:$B$20),""),IFERROR(_xlfn.XLOOKUP(E25,'⚙️ Configuración Costos'!$A$5:$A$6,'⚙️ Configuración Costos'!$B$5:$B$6),"")) -> 239.84262 | P25: =IF(E25="HERRAJE",A25*O25,M25*O25) -> 20.645653 | Q25: =IF(E25="HERRAJE",0,IFERROR(_xlfn.XLOOKUP(E25,'⚙️ Configuración Costos'!$E$5:$E$6,'⚙️ Configuración Costos'!$F$5:$F$6),"")) -> 6 | R25: =N25*Q25 -> 3.84 | S25: =P25+R25 -> 24.485653 | T25: =IF(K25="","SIN ID MÓDULO",IF(E25="HERRAJE",IF(OR(O25="",O25<=0),"SIN PRECIO HERRAJE","OK"),IF(OR(O25="",O25<=0),"SIN PRECIO MATERIAL",IF(AND(N25>0,OR(Q25="",Q25<=0)),"SIN PRECIO CINTILLA","OK")))) -> OK | U25: =IF(T25="OK","",IF(T25="SIN PRECIO HERRAJE","Capturar precio: "&D25,IF(T25="SIN PRECIO MATERIAL","Configurar material: "&E25,IF(T25="SIN PRECIO CINTILLA","Configurar cintilla: "&E25,IF(T25="SIN ID MÓDULO","Revisar ID del módulo",""))))) | V25: =IF(T25="OK",0,IF(T25="",0,1)) -> 0
A26: 1 | B26: 269 | C26: 320 | D26: Techo Alacena | E26: ARAUCO BLANCO | F26: 0 | G26: 0 | H26: 0 | I26: 1 | J26: 1 | K26: ALA-1PU-306832 | L26: TEC-ALA-3027 | M26: =IF(AND(ISNUMBER(B26),ISNUMBER(C26),B26>0,C26>0),A26*(B26*C26/1000000),0) -> 0.08608 | N26: =IF(AND(ISNUMBER(B26),B26>0),A26*(((G26+H26)*B26+(I26+J26)*C26)/1000),0) -> 0.64 | O26: =IF(E26="HERRAJE",IFERROR(_xlfn.XLOOKUP(D26,'⚙️ Configuración Costos'!$A$11:$A$20,'⚙️ Configuración Costos'!$B$11:$B$20),""),IFERROR(_xlfn.XLOOKUP(E26,'⚙️ Configuración Costos'!$A$5:$A$6,'⚙️ Configuración Costos'!$B$5:$B$6),"")) -> 239.84262 | P26: =IF(E26="HERRAJE",A26*O26,M26*O26) -> 20.645653 | Q26: =IF(E26="HERRAJE",0,IFERROR(_xlfn.XLOOKUP(E26,'⚙️ Configuración Costos'!$E$5:$E$6,'⚙️ Configuración Costos'!$F$5:$F$6),"")) -> 6 | R26: =N26*Q26 -> 3.84 | S26: =P26+R26 -> 24.485653 | T26: =IF(K26="","SIN ID MÓDULO",IF(E26="HERRAJE",IF(OR(O26="",O26<=0),"SIN PRECIO HERRAJE","OK"),IF(OR(O26="",O26<=0),"SIN PRECIO MATERIAL",IF(AND(N26>0,OR(Q26="",Q26<=0)),"SIN PRECIO CINTILLA","OK")))) -> OK | U26: =IF(T26="OK","",IF(T26="SIN PRECIO HERRAJE","Capturar precio: "&D26,IF(T26="SIN PRECIO MATERIAL","Configurar material: "&E26,IF(T26="SIN PRECIO CINTILLA","Configurar cintilla: "&E26,IF(T26="SIN ID MÓDULO","Revisar ID del módulo",""))))) | V26: =IF(T26="OK",0,IF(T26="",0,1)) -> 0
A27: 1 | B27: 269 | C27: 256 | D27: Entrepano Alacena | E27: ARAUCO BLANCO | F27: 0 | G27: 1 | H27: 1 | I27: 0 | J27: 0 | K27: ALA-1PU-306832 | L27: ENT-ALA-3026 | M27: =IF(AND(ISNUMBER(B27),ISNUMBER(C27),B27>0,C27>0),A27*(B27*C27/1000000),0) -> 0.068864 | N27: =IF(AND(ISNUMBER(B27),B27>0),A27*(((G27+H27)*B27+(I27+J27)*C27)/1000),0) -> 0.538 | O27: =IF(E27="HERRAJE",IFERROR(_xlfn.XLOOKUP(D27,'⚙️ Configuración Costos'!$A$11:$A$20,'⚙️ Configuración Costos'!$B$11:$B$20),""),IFERROR(_xlfn.XLOOKUP(E27,'⚙️ Configuración Costos'!$A$5:$A$6,'⚙️ Configuración Costos'!$B$5:$B$6),"")) -> 239.84262 | P27: =IF(E27="HERRAJE",A27*O27,M27*O27) -> 16.516522 | Q27: =IF(E27="HERRAJE",0,IFERROR(_xlfn.XLOOKUP(E27,'⚙️ Configuración Costos'!$E$5:$E$6,'⚙️ Configuración Costos'!$F$5:$F$6),"")) -> 6 | R27: =N27*Q27 -> 3.228 | S27: =P27+R27 -> 19.744522 | T27: =IF(K27="","SIN ID MÓDULO",IF(E27="HERRAJE",IF(OR(O27="",O27<=0),"SIN PRECIO HERRAJE","OK"),IF(OR(O27="",O27<=0),"SIN PRECIO MATERIAL",IF(AND(N27>0,OR(Q27="",Q27<=0)),"SIN PRECIO CINTILLA","OK")))) -> OK | U27: =IF(T27="OK","",IF(T27="SIN PRECIO HERRAJE","Capturar precio: "&D27,IF(T27="SIN PRECIO MATERIAL","Configurar material: "&E27,IF(T27="SIN PRECIO CINTILLA","Configurar cintilla: "&E27,IF(T27="SIN ID MÓDULO","Revisar ID del módulo",""))))) | V27: =IF(T27="OK",0,IF(T27="",0,1)) -> 0
A28: 1 | B28: 677 | C28: 297 | D28: Puerta Alacena | E28: VESTO NOUGAT | F28: 1 | G28: 1 | H28: 1 | I28: 1 | J28: 1 | K28: ALA-1PU-306832 | L28: PUE-ALA-6830 | M28: =IF(AND(ISNUMBER(B28),ISNUMBER(C28),B28>0,C28>0),A28*(B28*C28/1000000),0) -> 0.201069 | N28: =IF(AND(ISNUMBER(B28),B28>0),A28*(((G28+H28)*B28+(I28+J28)*C28)/1000),0) -> 1.948 | O28: =IF(E28="HERRAJE",IFERROR(_xlfn.XLOOKUP(D28,'⚙️ Configuración Costos'!$A$11:$A$20,'⚙️ Configuración Costos'!$B$11:$B$20),""),IFERROR(_xlfn.XLOOKUP(E28,'⚙️ Configuración Costos'!$A$5:$A$6,'⚙️ Configuración Costos'!$B$5:$B$6),"")) -> 332.85246 | P28: =IF(E28="HERRAJE",A28*O28,M28*O28) -> 66.926311 | Q28: =IF(E28="HERRAJE",0,IFERROR(_xlfn.XLOOKUP(E28,'⚙️ Configuración Costos'!$E$5:$E$6,'⚙️ Configuración Costos'!$F$5:$F$6),"")) -> 9.5 | R28: =N28*Q28 -> 18.506 | S28: =P28+R28 -> 85.432311 | T28: =IF(K28="","SIN ID MÓDULO",IF(E28="HERRAJE",IF(OR(O28="",O28<=0),"SIN PRECIO HERRAJE","OK"),IF(OR(O28="",O28<=0),"SIN PRECIO MATERIAL",IF(AND(N28>0,OR(Q28="",Q28<=0)),"SIN PRECIO CINTILLA","OK")))) -> OK | U28: =IF(T28="OK","",IF(T28="SIN PRECIO HERRAJE","Capturar precio: "&D28,IF(T28="SIN PRECIO MATERIAL","Configurar material: "&E28,IF(T28="SIN PRECIO CINTILLA","Configurar cintilla: "&E28,IF(T28="SIN ID MÓDULO","Revisar ID del módulo",""))))) | V28: =IF(T28="OK",0,IF(T28="",0,1)) -> 0
A29: 2 | B29: 0 | C29: 0 | D29: Bisagra Cierre Lento | E29: HERRAJE | F29: 0 | G29: 0 | H29: 0 | I29: 0 | J29: 0 | K29: ALA-1PU-306832 | L29: BIS-CL | M29: =IF(AND(ISNUMBER(B29),ISNUMBER(C29),B29>0,C29>0),A29*(B29*C29/1000000),0) -> 0 | N29: =IF(AND(ISNUMBER(B29),B29>0),A29*(((G29+H29)*B29+(I29+J29)*C29)/1000),0) -> 0 | O29: =IF(E29="HERRAJE",IFERROR(_xlfn.XLOOKUP(D29,'⚙️ Configuración Costos'!$A$11:$A$20,'⚙️ Configuración Costos'!$B$11:$B$20),""),IFERROR(_xlfn.XLOOKUP(E29,'⚙️ Configuración Costos'!$A$5:$A$6,'⚙️ Configuración Costos'!$B$5:$B$6),"")) -> 20 | P29: =IF(E29="HERRAJE",A29*O29,M29*O29) -> 40 | Q29: =IF(E29="HERRAJE",0,IFERROR(_xlfn.XLOOKUP(E29,'⚙️ Configuración Costos'!$E$5:$E$6,'⚙️ Configuración Costos'!$F$5:$F$6),"")) -> 0 | R29: =N29*Q29 -> 0 | S29: =P29+R29 -> 40 | T29: =IF(K29="","SIN ID MÓDULO",IF(E29="HERRAJE",IF(OR(O29="",O29<=0),"SIN PRECIO HERRAJE","OK"),IF(OR(O29="",O29<=0),"SIN PRECIO MATERIAL",IF(AND(N29>0,OR(Q29="",Q29<=0)),"SIN PRECIO CINTILLA","OK")))) -> OK | U29: =IF(T29="OK","",IF(T29="SIN PRECIO HERRAJE","Capturar precio: "&D29,IF(T29="SIN PRECIO MATERIAL","Configurar material: "&E29,IF(T29="SIN PRECIO CINTILLA","Configurar cintilla: "&E29,IF(T29="SIN ID MÓDULO","Revisar ID del módulo",""))))) | V29: =IF(T29="OK",0,IF(T29="",0,1)) -> 0
A30: 1 | B30: 0 | C30: 0 | D30: Jaladera Acero Inox | E30: HERRAJE | F30: 0 | G30: 0 | H30: 0 | I30: 0 | J30: 0 | K30: ALA-1PU-306832 | L30: JAL-INOX | M30: =IF(AND(ISNUMBER(B30),ISNUMBER(C30),B30>0,C30>0),A30*(B30*C30/1000000),0) -> 0 | N30: =IF(AND(ISNUMBER(B30),B30>0),A30*(((G30+H30)*B30+(I30+J30)*C30)/1000),0) -> 0 | O30: =IF(E30="HERRAJE",IFERROR(_xlfn.XLOOKUP(D30,'⚙️ Configuración Costos'!$A$11:$A$20,'⚙️ Configuración Costos'!$B$11:$B$20),""),IFERROR(_xlfn.XLOOKUP(E30,'⚙️ Configuración Costos'!$A$5:$A$6,'⚙️ Configuración Costos'!$B$5:$B$6),"")) -> 15 | P30: =IF(E30="HERRAJE",A30*O30,M30*O30) -> 15 | Q30: =IF(E30="HERRAJE",0,IFERROR(_xlfn.XLOOKUP(E30,'⚙️ Configuración Costos'!$E$5:$E$6,'⚙️ Configuración Costos'!$F$5:$F$6),"")) -> 0 | R30: =N30*Q30 -> 0 | S30: =P30+R30 -> 15 | T30: =IF(K30="","SIN ID MÓDULO",IF(E30="HERRAJE",IF(OR(O30="",O30<=0),"SIN PRECIO HERRAJE","OK"),IF(OR(O30="",O30<=0),"SIN PRECIO MATERIAL",IF(AND(N30>0,OR(Q30="",Q30<=0)),"SIN PRECIO CINTILLA","OK")))) -> OK | U30: =IF(T30="OK","",IF(T30="SIN PRECIO HERRAJE","Capturar precio: "&D30,IF(T30="SIN PRECIO MATERIAL","Configurar material: "&E30,IF(T30="SIN PRECIO CINTILLA","Configurar cintilla: "&E30,IF(T30="SIN ID MÓDULO","Revisar ID del módulo",""))))) | V30: =IF(T30="OK",0,IF(T30="",0,1)) -> 0
A31: 4 | B31: 0 | C31: 0 | D31: Soporte de Entrepaño | E31: HERRAJE | F31: 0 | G31: 0 | H31: 0 | I31: 0 | J31: 0 | K31: ALA-1PU-306832 | L31: SOP-ENT | M31: =IF(AND(ISNUMBER(B31),ISNUMBER(C31),B31>0,C31>0),A31*(B31*C31/1000000),0) -> 0 | N31: =IF(AND(ISNUMBER(B31),B31>0),A31*(((G31+H31)*B31+(I31+J31)*C31)/1000),0) -> 0 | O31: =IF(E31="HERRAJE",IFERROR(_xlfn.XLOOKUP(D31,'⚙️ Configuración Costos'!$A$11:$A$20,'⚙️ Configuración Costos'!$B$11:$B$20),""),IFERROR(_xlfn.XLOOKUP(E31,'⚙️ Configuración Costos'!$A$5:$A$6,'⚙️ Configuración Costos'!$B$5:$B$6),"")) -> 2 | P31: =IF(E31="HERRAJE",A31*O31,M31*O31) -> 8 | Q31: =IF(E31="HERRAJE",0,IFERROR(_xlfn.XLOOKUP(E31,'⚙️ Configuración Costos'!$E$5:$E$6,'⚙️ Configuración Costos'!$F$5:$F$6),"")) -> 0 | R31: =N31*Q31 -> 0 | S31: =P31+R31 -> 8 | T31: =IF(K31="","SIN ID MÓDULO",IF(E31="HERRAJE",IF(OR(O31="",O31<=0),"SIN PRECIO HERRAJE","OK"),IF(OR(O31="",O31<=0),"SIN PRECIO MATERIAL",IF(AND(N31>0,OR(Q31="",Q31<=0)),"SIN PRECIO CINTILLA","OK")))) -> OK | U31: =IF(T31="OK","",IF(T31="SIN PRECIO HERRAJE","Capturar precio: "&D31,IF(T31="SIN PRECIO MATERIAL","Configurar material: "&E31,IF(T31="SIN PRECIO CINTILLA","Configurar cintilla: "&E31,IF(T31="SIN ID MÓDULO","Revisar ID del módulo",""))))) | V31: =IF(T31="OK",0,IF(T31="",0,1)) -> 0
A32: 24 | B32: 0 | C32: 0 | D32: Tornillo 4x50 mm | E32: HERRAJE | F32: 0 | G32: 0 | H32: 0 | I32: 0 | J32: 0 | K32: ALA-1PU-306832 | L32: TOR-4X50 | M32: =IF(AND(ISNUMBER(B32),ISNUMBER(C32),B32>0,C32>0),A32*(B32*C32/1000000),0) -> 0 | N32: =IF(AND(ISNUMBER(B32),B32>0),A32*(((G32+H32)*B32+(I32+J32)*C32)/1000),0) -> 0 | O32: =IF(E32="HERRAJE",IFERROR(_xlfn.XLOOKUP(D32,'⚙️ Configuración Costos'!$A$11:$A$20,'⚙️ Configuración Costos'!$B$11:$B$20),""),IFERROR(_xlfn.XLOOKUP(E32,'⚙️ Configuración Costos'!$A$5:$A$6,'⚙️ Configuración Costos'!$B$5:$B$6),"")) -> 1.5 | P32: =IF(E32="HERRAJE",A32*O32,M32*O32) -> 36 | Q32: =IF(E32="HERRAJE",0,IFERROR(_xlfn.XLOOKUP(E32,'⚙️ Configuración Costos'!$E$5:$E$6,'⚙️ Configuración Costos'!$F$5:$F$6),"")) -> 0 | R32: =N32*Q32 -> 0 | S32: =P32+R32 -> 36 | T32: =IF(K32="","SIN ID MÓDULO",IF(E32="HERRAJE",IF(OR(O32="",O32<=0),"SIN PRECIO HERRAJE","OK"),IF(OR(O32="",O32<=0),"SIN PRECIO MATERIAL",IF(AND(N32>0,OR(Q32="",Q32<=0)),"SIN PRECIO CINTILLA","OK")))) -> OK | U32: =IF(T32="OK","",IF(T32="SIN PRECIO HERRAJE","Capturar precio: "&D32,IF(T32="SIN PRECIO MATERIAL","Configurar material: "&E32,IF(T32="SIN PRECIO CINTILLA","Configurar cintilla: "&E32,IF(T32="SIN ID MÓDULO","Revisar ID del módulo",""))))) | V32: =IF(T32="OK",0,IF(T32="",0,1)) -> 0
A33: TOTALES | M33: =SUM(M22:M32) -> 1.051874 | N33: =SUM(N22:N32) -> 7.766 | P33: =SUM(P22:P32) -> 369.98561 | R33: =SUM(R22:R32) -> 53.414 | S33: =SUM(S22:S32) -> 423.39961
A34: Alacena 1 Puerta 400 x 680 x 320 mm
A35: 1 | B35: 680 | C35: 320 | D35: Lateral Derecho | E35: ARAUCO BLANCO | F35: 0 | G35: 1 | H35: 1 | I35: 1 | J35: 1 | K35: ALA-1PU-406832 | L35: LAT-ALA-6832-D | M35: =IF(AND(ISNUMBER(B35),ISNUMBER(C35),B35>0,C35>0),A35*(B35*C35/1000000),0) -> 0.2176 | N35: =IF(AND(ISNUMBER(B35),B35>0),A35*(((G35+H35)*B35+(I35+J35)*C35)/1000),0) -> 2 | O35: =IF(E35="HERRAJE",IFERROR(_xlfn.XLOOKUP(D35,'⚙️ Configuración Costos'!$A$11:$A$20,'⚙️ Configuración Costos'!$B$11:$B$20),""),IFERROR(_xlfn.XLOOKUP(E35,'⚙️ Configuración Costos'!$A$5:$A$6,'⚙️ Configuración Costos'!$B$5:$B$6),"")) -> 239.84262 | P35: =IF(E35="HERRAJE",A35*O35,M35*O35) -> 52.189755 | Q35: =IF(E35="HERRAJE",0,IFERROR(_xlfn.XLOOKUP(E35,'⚙️ Configuración Costos'!$E$5:$E$6,'⚙️ Configuración Costos'!$F$5:$F$6),"")) -> 6 | R35: =N35*Q35 -> 12 | S35: =P35+R35 -> 64.189755 | T35: =IF(K35="","SIN ID MÓDULO",IF(E35="HERRAJE",IF(OR(O35="",O35<=0),"SIN PRECIO HERRAJE","OK"),IF(OR(O35="",O35<=0),"SIN PRECIO MATERIAL",IF(AND(N35>0,OR(Q35="",Q35<=0)),"SIN PRECIO CINTILLA","OK")))) -> OK | U35: =IF(T35="OK","",IF(T35="SIN PRECIO HERRAJE","Capturar precio: "&D35,IF(T35="SIN PRECIO MATERIAL","Configurar material: "&E35,IF(T35="SIN PRECIO CINTILLA","Configurar cintilla: "&E35,IF(T35="SIN ID MÓDULO","Revisar ID del módulo",""))))) | V35: =IF(T35="OK",0,IF(T35="",0,1)) -> 0
A36: 1 | B36: 680 | C36: 320 | D36: Lateral Izquierdo | E36: ARAUCO BLANCO | F36: 0 | G36: 1 | H36: 1 | I36: 1 | J36: 1 | K36: ALA-1PU-406832 | L36: LAT-ALA-6832-I | M36: =IF(AND(ISNUMBER(B36),ISNUMBER(C36),B36>0,C36>0),A36*(B36*C36/1000000),0) -> 0.2176 | N36: =IF(AND(ISNUMBER(B36),B36>0),A36*(((G36+H36)*B36+(I36+J36)*C36)/1000),0) -> 2 | O36: =IF(E36="HERRAJE",IFERROR(_xlfn.XLOOKUP(D36,'⚙️ Configuración Costos'!$A$11:$A$20,'⚙️ Configuración Costos'!$B$11:$B$20),""),IFERROR(_xlfn.XLOOKUP(E36,'⚙️ Configuración Costos'!$A$5:$A$6,'⚙️ Configuración Costos'!$B$5:$B$6),"")) -> 239.84262 | P36: =IF(E36="HERRAJE",A36*O36,M36*O36) -> 52.189755 | Q36: =IF(E36="HERRAJE",0,IFERROR(_xlfn.XLOOKUP(E36,'⚙️ Configuración Costos'!$E$5:$E$6,'⚙️ Configuración Costos'!$F$5:$F$6),"")) -> 6 | R36: =N36*Q36 -> 12 | S36: =P36+R36 -> 64.189755 | T36: =IF(K36="","SIN ID MÓDULO",IF(E36="HERRAJE",IF(OR(O36="",O36<=0),"SIN PRECIO HERRAJE","OK"),IF(OR(O36="",O36<=0),"SIN PRECIO MATERIAL",IF(AND(N36>0,OR(Q36="",Q36<=0)),"SIN PRECIO CINTILLA","OK")))) -> OK | U36: =IF(T36="OK","",IF(T36="SIN PRECIO HERRAJE","Capturar precio: "&D36,IF(T36="SIN PRECIO MATERIAL","Configurar material: "&E36,IF(T36="SIN PRECIO CINTILLA","Configurar cintilla: "&E36,IF(T36="SIN ID MÓDULO","Revisar ID del módulo",""))))) | V36: =IF(T36="OK",0,IF(T36="",0,1)) -> 0
A37: 1 | B37: 649 | C37: 369 | D37: Respaldo Alacena | E37: ARAUCO BLANCO | F37: 0 | G37: 0 | H37: 0 | I37: 0 | J37: 0 | K37: ALA-1PU-406832 | L37: RES-ALA-6840 | M37: =IF(AND(ISNUMBER(B37),ISNUMBER(C37),B37>0,C37>0),A37*(B37*C37/1000000),0) -> 0.239481 | N37: =IF(AND(ISNUMBER(B37),B37>0),A37*(((G37+H37)*B37+(I37+J37)*C37)/1000),0) -> 0 | O37: =IF(E37="HERRAJE",IFERROR(_xlfn.XLOOKUP(D37,'⚙️ Configuración Costos'!$A$11:$A$20,'⚙️ Configuración Costos'!$B$11:$B$20),""),IFERROR(_xlfn.XLOOKUP(E37,'⚙️ Configuración Costos'!$A$5:$A$6,'⚙️ Configuración Costos'!$B$5:$B$6),"")) -> 239.84262 | P37: =IF(E37="HERRAJE",A37*O37,M37*O37) -> 57.437751 | Q37: =IF(E37="HERRAJE",0,IFERROR(_xlfn.XLOOKUP(E37,'⚙️ Configuración Costos'!$E$5:$E$6,'⚙️ Configuración Costos'!$F$5:$F$6),"")) -> 6 | R37: =N37*Q37 -> 0 | S37: =P37+R37 -> 57.437751 | T37: =IF(K37="","SIN ID MÓDULO",IF(E37="HERRAJE",IF(OR(O37="",O37<=0),"SIN PRECIO HERRAJE","OK"),IF(OR(O37="",O37<=0),"SIN PRECIO MATERIAL",IF(AND(N37>0,OR(Q37="",Q37<=0)),"SIN PRECIO CINTILLA","OK")))) -> OK | U37: =IF(T37="OK","",IF(T37="SIN PRECIO HERRAJE","Capturar precio: "&D37,IF(T37="SIN PRECIO MATERIAL","Configurar material: "&E37,IF(T37="SIN PRECIO CINTILLA","Configurar cintilla: "&E37,IF(T37="SIN ID MÓDULO","Revisar ID del módulo",""))))) | V37: =IF(T37="OK",0,IF(T37="",0,1)) -> 0
A38: 1 | B38: 369 | C38: 320 | D38: Base Alacena | E38: ARAUCO BLANCO | F38: 0 | G38: 1 | H38: 1 | I38: 0 | J38: 0 | K38: ALA-1PU-406832 | L38: BAS-ALA-4032 | M38: =IF(AND(ISNUMBER(B38),ISNUMBER(C38),B38>0,C38>0),A38*(B38*C38/1000000),0) -> 0.11808 | N38: =IF(AND(ISNUMBER(B38),B38>0),A38*(((G38+H38)*B38+(I38+J38)*C38)/1000),0) -> 0.738 | O38: =IF(E38="HERRAJE",IFERROR(_xlfn.XLOOKUP(D38,'⚙️ Configuración Costos'!$A$11:$A$20,'⚙️ Configuración Costos'!$B$11:$B$20),""),IFERROR(_xlfn.XLOOKUP(E38,'⚙️ Configuración Costos'!$A$5:$A$6,'⚙️ Configuración Costos'!$B$5:$B$6),"")) -> 239.84262 | P38: =IF(E38="HERRAJE",A38*O38,M38*O38) -> 28.320617 | Q38: =IF(E38="HERRAJE",0,IFERROR(_xlfn.XLOOKUP(E38,'⚙️ Configuración Costos'!$E$5:$E$6,'⚙️ Configuración Costos'!$F$5:$F$6),"")) -> 6 | R38: =N38*Q38 -> 4.428 | S38: =P38+R38 -> 32.748617 | T38: =IF(K38="","SIN ID MÓDULO",IF(E38="HERRAJE",IF(OR(O38="",O38<=0),"SIN PRECIO HERRAJE","OK"),IF(OR(O38="",O38<=0),"SIN PRECIO MATERIAL",IF(AND(N38>0,OR(Q38="",Q38<=0)),"SIN PRECIO CINTILLA","OK")))) -> OK | U38: =IF(T38="OK","",IF(T38="SIN PRECIO HERRAJE","Capturar precio: "&D38,IF(T38="SIN PRECIO MATERIAL","Configurar material: "&E38,IF(T38="SIN PRECIO CINTILLA","Configurar cintilla: "&E38,IF(T38="SIN ID MÓDULO","Revisar ID del módulo",""))))) | V38: =IF(T38="OK",0,IF(T38="",0,1)) -> 0
A39: 1 | B39: 369 | C39: 320 | D39: Techo Alacena | E39: ARAUCO BLANCO | F39: 0 | G39: 1 | H39: 1 | I39: 0 | J39: 0 | K39: ALA-1PU-406832 | L39: TEC-ALA-4032 | M39: =IF(AND(ISNUMBER(B39),ISNUMBER(C39),B39>0,C39>0),A39*(B39*C39/1000000),0) -> 0.11808 | N39: =IF(AND(ISNUMBER(B39),B39>0),A39*(((G39+H39)*B39+(I39+J39)*C39)/1000),0) -> 0.738 | O39: =IF(E39="HERRAJE",IFERROR(_xlfn.XLOOKUP(D39,'⚙️ Configuración Costos'!$A$11:$A$20,'⚙️ Configuración Costos'!$B$11:$B$20),""),IFERROR(_xlfn.XLOOKUP(E39,'⚙️ Configuración Costos'!$A$5:$A$6,'⚙️ Configuración Costos'!$B$5:$B$6),"")) -> 239.84262 | P39: =IF(E39="HERRAJE",A39*O39,M39*O39) -> 28.320617 | Q39: =IF(E39="HERRAJE",0,IFERROR(_xlfn.XLOOKUP(E39,'⚙️ Configuración Costos'!$E$5:$E$6,'⚙️ Configuración Costos'!$F$5:$F$6),"")) -> 6 | R39: =N39*Q39 -> 4.428 | S39: =P39+R39 -> 32.748617 | T39: =IF(K39="","SIN ID MÓDULO",IF(E39="HERRAJE",IF(OR(O39="",O39<=0),"SIN PRECIO HERRAJE","OK"),IF(OR(O39="",O39<=0),"SIN PRECIO MATERIAL",IF(AND(N39>0,OR(Q39="",Q39<=0)),"SIN PRECIO CINTILLA","OK")))) -> OK | U39: =IF(T39="OK","",IF(T39="SIN PRECIO HERRAJE","Capturar precio: "&D39,IF(T39="SIN PRECIO MATERIAL","Configurar material: "&E39,IF(T39="SIN PRECIO CINTILLA","Configurar cintilla: "&E39,IF(T39="SIN ID MÓDULO","Revisar ID del módulo",""))))) | V39: =IF(T39="OK",0,IF(T39="",0,1)) -> 0
A40: 1 | B40: 369 | C40: 256 | D40: Entrepano Alacena | E40: ARAUCO BLANCO | F40: 0 | G40: 1 | H40: 1 | I40: 0 | J40: 0 | K40: ALA-1PU-406832 | L40: ENT-ALA-4026 | M40: =IF(AND(ISNUMBER(B40),ISNUMBER(C40),B40>0,C40>0),A40*(B40*C40/1000000),0) -> 0.094464 | N40: =IF(AND(ISNUMBER(B40),B40>0),A40*(((G40+H40)*B40+(I40+J40)*C40)/1000),0) -> 0.738 | O40: =IF(E40="HERRAJE",IFERROR(_xlfn.XLOOKUP(D40,'⚙️ Configuración Costos'!$A$11:$A$20,'⚙️ Configuración Costos'!$B$11:$B$20),""),IFERROR(_xlfn.XLOOKUP(E40,'⚙️ Configuración Costos'!$A$5:$A$6,'⚙️ Configuración Costos'!$B$5:$B$6),"")) -> 239.84262 | P40: =IF(E40="HERRAJE",A40*O40,M40*O40) -> 22.656494 | Q40: =IF(E40="HERRAJE",0,IFERROR(_xlfn.XLOOKUP(E40,'⚙️ Configuración Costos'!$E$5:$E$6,'⚙️ Configuración Costos'!$F$5:$F$6),"")) -> 6 | R40: =N40*Q40 -> 4.428 | S40: =P40+R40 -> 27.084494 | T40: =IF(K40="","SIN ID MÓDULO",IF(E40="HERRAJE",IF(OR(O40="",O40<=0),"SIN PRECIO HERRAJE","OK"),IF(OR(O40="",O40<=0),"SIN PRECIO MATERIAL",IF(AND(N40>0,OR(Q40="",Q40<=0)),"SIN PRECIO CINTILLA","OK")))) -> OK | U40: =IF(T40="OK","",IF(T40="SIN PRECIO HERRAJE","Capturar precio: "&D40,IF(T40="SIN PRECIO MATERIAL","Configurar material: "&E40,IF(T40="SIN PRECIO CINTILLA","Configurar cintilla: "&E40,IF(T40="SIN ID MÓDULO","Revisar ID del módulo",""))))) | V40: =IF(T40="OK",0,IF(T40="",0,1)) -> 0
A41: 1 | B41: 677 | C41: 397 | D41: Puerta Alacena | E41: VESTO NOUGAT | F41: 1 | G41: 1 | H41: 1 | I41: 1 | J41: 1 | K41: ALA-1PU-406832 | L41: PUE-ALA-6840 | M41: =IF(AND(ISNUMBER(B41),ISNUMBER(C41),B41>0,C41>0),A41*(B41*C41/1000000),0) -> 0.268769 | N41: =IF(AND(ISNUMBER(B41),B41>0),A41*(((G41+H41)*B41+(I41+J41)*C41)/1000),0) -> 2.148 | O41: =IF(E41="HERRAJE",IFERROR(_xlfn.XLOOKUP(D41,'⚙️ Configuración Costos'!$A$11:$A$20,'⚙️ Configuración Costos'!$B$11:$B$20),""),IFERROR(_xlfn.XLOOKUP(E41,'⚙️ Configuración Costos'!$A$5:$A$6,'⚙️ Configuración Costos'!$B$5:$B$6),"")) -> 332.85246 | P41: =IF(E41="HERRAJE",A41*O41,M41*O41) -> 89.460423 | Q41: =IF(E41="HERRAJE",0,IFERROR(_xlfn.XLOOKUP(E41,'⚙️ Configuración Costos'!$E$5:$E$6,'⚙️ Configuración Costos'!$F$5:$F$6),"")) -> 9.5 | R41: =N41*Q41 -> 20.406 | S41: =P41+R41 -> 109.86642 | T41: =IF(K41="","SIN ID MÓDULO",IF(E41="HERRAJE",IF(OR(O41="",O41<=0),"SIN PRECIO HERRAJE","OK"),IF(OR(O41="",O41<=0),"SIN PRECIO MATERIAL",IF(AND(N41>0,OR(Q41="",Q41<=0)),"SIN PRECIO CINTILLA","OK")))) -> OK | U41: =IF(T41="OK","",IF(T41="SIN PRECIO HERRAJE","Capturar precio: "&D41,IF(T41="SIN PRECIO MATERIAL","Configurar material: "&E41,IF(T41="SIN PRECIO CINTILLA","Configurar cintilla: "&E41,IF(T41="SIN ID MÓDULO","Revisar ID del módulo",""))))) | V41: =IF(T41="OK",0,IF(T41="",0,1)) -> 0
A42: 2 | B42: 0 | C42: 0 | D42: Bisagra Cierre Lento | E42: HERRAJE | F42: 0 | G42: 0 | H42: 0 | I42: 0 | J42: 0 | K42: ALA-1PU-406832 | L42: BIS-CL | M42: =IF(AND(ISNUMBER(B42),ISNUMBER(C42),B42>0,C42>0),A42*(B42*C42/1000000),0) -> 0 | N42: =IF(AND(ISNUMBER(B42),B42>0),A42*(((G42+H42)*B42+(I42+J42)*C42)/1000),0) -> 0 | O42: =IF(E42="HERRAJE",IFERROR(_xlfn.XLOOKUP(D42,'⚙️ Configuración Costos'!$A$11:$A$20,'⚙️ Configuración Costos'!$B$11:$B$20),""),IFERROR(_xlfn.XLOOKUP(E42,'⚙️ Configuración Costos'!$A$5:$A$6,'⚙️ Configuración Costos'!$B$5:$B$6),"")) -> 20 | P42: =IF(E42="HERRAJE",A42*O42,M42*O42) -> 40 | Q42: =IF(E42="HERRAJE",0,IFERROR(_xlfn.XLOOKUP(E42,'⚙️ Configuración Costos'!$E$5:$E$6,'⚙️ Configuración Costos'!$F$5:$F$6),"")) -> 0 | R42: =N42*Q42 -> 0 | S42: =P42+R42 -> 40 | T42: =IF(K42="","SIN ID MÓDULO",IF(E42="HERRAJE",IF(OR(O42="",O42<=0),"SIN PRECIO HERRAJE","OK"),IF(OR(O42="",O42<=0),"SIN PRECIO MATERIAL",IF(AND(N42>0,OR(Q42="",Q42<=0)),"SIN PRECIO CINTILLA","OK")))) -> OK | U42: =IF(T42="OK","",IF(T42="SIN PRECIO HERRAJE","Capturar precio: "&D42,IF(T42="SIN PRECIO MATERIAL","Configurar material: "&E42,IF(T42="SIN PRECIO CINTILLA","Configurar cintilla: "&E42,IF(T42="SIN ID MÓDULO","Revisar ID del módulo",""))))) | V42: =IF(T42="OK",0,IF(T42="",0,1)) -> 0
A43: 1 | B43: 0 | C43: 0 | D43: Jaladera Acero Inox | E43: HERRAJE | F43: 0 | G43: 0 | H43: 0 | I43: 0 | J43: 0 | K43: ALA-1PU-406832 | L43: JAL-INOX | M43: =IF(AND(ISNUMBER(B43),ISNUMBER(C43),B43>0,C43>0),A43*(B43*C43/1000000),0) -> 0 | N43: =IF(AND(ISNUMBER(B43),B43>0),A43*(((G43+H43)*B43+(I43+J43)*C43)/1000),0) -> 0 | O43: =IF(E43="HERRAJE",IFERROR(_xlfn.XLOOKUP(D43,'⚙️ Configuración Costos'!$A$11:$A$20,'⚙️ Configuración Costos'!$B$11:$B$20),""),IFERROR(_xlfn.XLOOKUP(E43,'⚙️ Configuración Costos'!$A$5:$A$6,'⚙️ Configuración Costos'!$B$5:$B$6),"")) -> 15 | P43: =IF(E43="HERRAJE",A43*O43,M43*O43) -> 15 | Q43: =IF(E43="HERRAJE",0,IFERROR(_xlfn.XLOOKUP(E43,'⚙️ Configuración Costos'!$E$5:$E$6,'⚙️ Configuración Costos'!$F$5:$F$6),"")) -> 0 | R43: =N43*Q43 -> 0 | S43: =P43+R43 -> 15 | T43: =IF(K43="","SIN ID MÓDULO",IF(E43="HERRAJE",IF(OR(O43="",O43<=0),"SIN PRECIO HERRAJE","OK"),IF(OR(O43="",O43<=0),"SIN PRECIO MATERIAL",IF(AND(N43>0,OR(Q43="",Q43<=0)),"SIN PRECIO CINTILLA","OK")))) -> OK | U43: =IF(T43="OK","",IF(T43="SIN PRECIO HERRAJE","Capturar precio: "&D43,IF(T43="SIN PRECIO MATERIAL","Configurar material: "&E43,IF(T43="SIN PRECIO CINTILLA","Configurar cintilla: "&E43,IF(T43="SIN ID MÓDULO","Revisar ID del módulo",""))))) | V43: =IF(T43="OK",0,IF(T43="",0,1)) -> 0
A44: 4 | B44: 0 | C44: 0 | D44: Soporte de Entrepaño | E44: HERRAJE | F44: 0 | G44: 0 | H44: 0 | I44: 0 | J44: 0 | K44: ALA-1PU-406832 | L44: SOP-ENT | M44: =IF(AND(ISNUMBER(B44),ISNUMBER(C44),B44>0,C44>0),A44*(B44*C44/1000000),0) -> 0 | N44: =IF(AND(ISNUMBER(B44),B44>0),A44*(((G44+H44)*B44+(I44+J44)*C44)/1000),0) -> 0 | O44: =IF(E44="HERRAJE",IFERROR(_xlfn.XLOOKUP(D44,'⚙️ Configuración Costos'!$A$11:$A$20,'⚙️ Configuración Costos'!$B$11:$B$20),""),IFERROR(_xlfn.XLOOKUP(E44,'⚙️ Configuración Costos'!$A$5:$A$6,'⚙️ Configuración Costos'!$B$5:$B$6),"")) -> 2 | P44: =IF(E44="HERRAJE",A44*O44,M44*O44) -> 8 | Q44: =IF(E44="HERRAJE",0,IFERROR(_xlfn.XLOOKUP(E44,'⚙️ Configuración Costos'!$E$5:$E$6,'⚙️ Configuración Costos'!$F$5:$F$6),"")) -> 0 | R44: =N44*Q44 -> 0 | S44: =P44+R44 -> 8 | T44: =IF(K44="","SIN ID MÓDULO",IF(E44="HERRAJE",IF(OR(O44="",O44<=0),"SIN PRECIO HERRAJE","OK"),IF(OR(O44="",O44<=0),"SIN PRECIO MATERIAL",IF(AND(N44>0,OR(Q44="",Q44<=0)),"SIN PRECIO CINTILLA","OK")))) -> OK | U44: =IF(T44="OK","",IF(T44="SIN PRECIO HERRAJE","Capturar precio: "&D44,IF(T44="SIN PRECIO MATERIAL","Configurar material: "&E44,IF(T44="SIN PRECIO CINTILLA","Configurar cintilla: "&E44,IF(T44="SIN ID MÓDULO","Revisar ID del módulo",""))))) | V44: =IF(T44="OK",0,IF(T44="",0,1)) -> 0
A45: 24 | B45: 0 | C45: 0 | D45: Tornillo 4x50 mm | E45: HERRAJE | F45: 0 | G45: 0 | H45: 0 | I45: 0 | J45: 0 | K45: ALA-1PU-406832 | L45: TOR-4X50 | M45: =IF(AND(ISNUMBER(B45),ISNUMBER(C45),B45>0,C45>0),A45*(B45*C45/1000000),0) -> 0 | N45: =IF(AND(ISNUMBER(B45),B45>0),A45*(((G45+H45)*B45+(I45+J45)*C45)/1000),0) -> 0 | O45: =IF(E45="HERRAJE",IFERROR(_xlfn.XLOOKUP(D45,'⚙️ Configuración Costos'!$A$11:$A$20,'⚙️ Configuración Costos'!$B$11:$B$20),""),IFERROR(_xlfn.XLOOKUP(E45,'⚙️ Configuración Costos'!$A$5:$A$6,'⚙️ Configuración Costos'!$B$5:$B$6),"")) -> 1.5 | P45: =IF(E45="HERRAJE",A45*O45,M45*O45) -> 36 | Q45: =IF(E45="HERRAJE",0,IFERROR(_xlfn.XLOOKUP(E45,'⚙️ Configuración Costos'!$E$5:$E$6,'⚙️ Configuración Costos'!$F$5:$F$6),"")) -> 0 | R45: =N45*Q45 -> 0 | S45: =P45+R45 -> 36 | T45: =IF(K45="","SIN ID MÓDULO",IF(E45="HERRAJE",IF(OR(O45="",O45<=0),"SIN PRECIO HERRAJE","OK"),IF(OR(O45="",O45<=0),"SIN PRECIO MATERIAL",IF(AND(N45>0,OR(Q45="",Q45<=0)),"SIN PRECIO CINTILLA","OK")))) -> OK | U45: =IF(T45="OK","",IF(T45="SIN PRECIO HERRAJE","Capturar precio: "&D45,IF(T45="SIN PRECIO MATERIAL","Configurar material: "&E45,IF(T45="SIN PRECIO CINTILLA","Configurar cintilla: "&E45,IF(T45="SIN ID MÓDULO","Revisar ID del módulo",""))))) | V45: =IF(T45="OK",0,IF(T45="",0,1)) -> 0
A46: TOTALES | M46: =SUM(M35:M45) -> 1.274074 | N46: =SUM(N35:N45) -> 8.362 | P46: =SUM(P35:P45) -> 429.57541 | R46: =SUM(R35:R45) -> 57.69 | S46: =SUM(S35:S45) -> 487.26541
A47: Alacena 1 Puerta 500 x 680 x 320 mm
A48: 1 | B48: 680 | C48: 320 | D48: Lateral Derecho | E48: ARAUCO BLANCO | F48: 0 | G48: 1 | H48: 1 | I48: 1 | J48: 1 | K48: ALA-1PU-506832 | L48: LAT-ALA-6832-D | M48: =IF(AND(ISNUMBER(B48),ISNUMBER(C48),B48>0,C48>0),A48*(B48*C48/1000000),0) -> 0.2176 | N48: =IF(AND(ISNUMBER(B48),B48>0),A48*(((G48+H48)*B48+(I48+J48)*C48)/1000),0) -> 2 | O48: =IF(E48="HERRAJE",IFERROR(_xlfn.XLOOKUP(D48,'⚙️ Configuración Costos'!$A$11:$A$20,'⚙️ Configuración Costos'!$B$11:$B$20),""),IFERROR(_xlfn.XLOOKUP(E48,'⚙️ Configuración Costos'!$A$5:$A$6,'⚙️ Configuración Costos'!$B$5:$B$6),"")) -> 239.84262 | P48: =IF(E48="HERRAJE",A48*O48,M48*O48) -> 52.189755 | Q48: =IF(E48="HERRAJE",0,IFERROR(_xlfn.XLOOKUP(E48,'⚙️ Configuración Costos'!$E$5:$E$6,'⚙️ Configuración Costos'!$F$5:$F$6),"")) -> 6 | R48: =N48*Q48 -> 12 | S48: =P48+R48 -> 64.189755 | T48: =IF(K48="","SIN ID MÓDULO",IF(E48="HERRAJE",IF(OR(O48="",O48<=0),"SIN PRECIO HERRAJE","OK"),IF(OR(O48="",O48<=0),"SIN PRECIO MATERIAL",IF(AND(N48>0,OR(Q48="",Q48<=0)),"SIN PRECIO CINTILLA","OK")))) -> OK | U48: =IF(T48="OK","",IF(T48="SIN PRECIO HERRAJE","Capturar precio: "&D48,IF(T48="SIN PRECIO MATERIAL","Configurar material: "&E48,IF(T48="SIN PRECIO CINTILLA","Configurar cintilla: "&E48,IF(T48="SIN ID MÓDULO","Revisar ID del módulo",""))))) | V48: =IF(T48="OK",0,IF(T48="",0,1)) -> 0
A49: 1 | B49: 680 | C49: 320 | D49: Lateral Izquierdo | E49: ARAUCO BLANCO | F49: 0 | G49: 1 | H49: 1 | I49: 1 | J49: 1 | K49: ALA-1PU-506832 | L49: LAT-ALA-6832-I | M49: =IF(AND(ISNUMBER(B49),ISNUMBER(C49),B49>0,C49>0),A49*(B49*C49/1000000),0) -> 0.2176 | N49: =IF(AND(ISNUMBER(B49),B49>0),A49*(((G49+H49)*B49+(I49+J49)*C49)/1000),0) -> 2 | O49: =IF(E49="HERRAJE",IFERROR(_xlfn.XLOOKUP(D49,'⚙️ Configuración Costos'!$A$11:$A$20,'⚙️ Configuración Costos'!$B$11:$B$20),""),IFERROR(_xlfn.XLOOKUP(E49,'⚙️ Configuración Costos'!$A$5:$A$6,'⚙️ Configuración Costos'!$B$5:$B$6),"")) -> 239.84262 | P49: =IF(E49="HERRAJE",A49*O49,M49*O49) -> 52.189755 | Q49: =IF(E49="HERRAJE",0,IFERROR(_xlfn.XLOOKUP(E49,'⚙️ Configuración Costos'!$E$5:$E$6,'⚙️ Configuración Costos'!$F$5:$F$6),"")) -> 6 | R49: =N49*Q49 -> 12 | S49: =P49+R49 -> 64.189755 | T49: =IF(K49="","SIN ID MÓDULO",IF(E49="HERRAJE",IF(OR(O49="",O49<=0),"SIN PRECIO HERRAJE","OK"),IF(OR(O49="",O49<=0),"SIN PRECIO MATERIAL",IF(AND(N49>0,OR(Q49="",Q49<=0)),"SIN PRECIO CINTILLA","OK")))) -> OK | U49: =IF(T49="OK","",IF(T49="SIN PRECIO HERRAJE","Capturar precio: "&D49,IF(T49="SIN PRECIO MATERIAL","Configurar material: "&E49,IF(T49="SIN PRECIO CINTILLA","Configurar cintilla: "&E49,IF(T49="SIN ID MÓDULO","Revisar ID del módulo",""))))) | V49: =IF(T49="OK",0,IF(T49="",0,1)) -> 0
A50: 1 | B50: 649 | C50: 469 | D50: Respaldo Alacena | E50: ARAUCO BLANCO | F50: 0 | G50: 0 | H50: 0 | I50: 0 | J50: 0 | K50: ALA-1PU-506832 | L50: RES-ALA-6850 | M50: =IF(AND(ISNUMBER(B50),ISNUMBER(C50),B50>0,C50>0),A50*(B50*C50/1000000),0) -> 0.304381 | N50: =IF(AND(ISNUMBER(B50),B50>0),A50*(((G50+H50)*B50+(I50+J50)*C50)/1000),0) -> 0 | O50: =IF(E50="HERRAJE",IFERROR(_xlfn.XLOOKUP(D50,'⚙️ Configuración Costos'!$A$11:$A$20,'⚙️ Configuración Costos'!$B$11:$B$20),""),IFERROR(_xlfn.XLOOKUP(E50,'⚙️ Configuración Costos'!$A$5:$A$6,'⚙️ Configuración Costos'!$B$5:$B$6),"")) -> 239.84262 | P50: =IF(E50="HERRAJE",A50*O50,M50*O50) -> 73.003537 | Q50: =IF(E50="HERRAJE",0,IFERROR(_xlfn.XLOOKUP(E50,'⚙️ Configuración Costos'!$E$5:$E$6,'⚙️ Configuración Costos'!$F$5:$F$6),"")) -> 6 | R50: =N50*Q50 -> 0 | S50: =P50+R50 -> 73.003537 | T50: =IF(K50="","SIN ID MÓDULO",IF(E50="HERRAJE",IF(OR(O50="",O50<=0),"SIN PRECIO HERRAJE","OK"),IF(OR(O50="",O50<=0),"SIN PRECIO MATERIAL",IF(AND(N50>0,OR(Q50="",Q50<=0)),"SIN PRECIO CINTILLA","OK")))) -> OK | U50: =IF(T50="OK","",IF(T50="SIN PRECIO HERRAJE","Capturar precio: "&D50,IF(T50="SIN PRECIO MATERIAL","Configurar material: "&E50,IF(T50="SIN PRECIO CINTILLA","Configurar cintilla: "&E50,IF(T50="SIN ID MÓDULO","Revisar ID del módulo",""))))) | V50: =IF(T50="OK",0,IF(T50="",0,1)) -> 0
A51: 1 | B51: 469 | C51: 320 | D51: Base Alacena | E51: ARAUCO BLANCO | F51: 0 | G51: 1 | H51: 1 | I51: 0 | J51: 0 | K51: ALA-1PU-506832 | L51: BAS-ALA-5032 | M51: =IF(AND(ISNUMBER(B51),ISNUMBER(C51),B51>0,C51>0),A51*(B51*C51/1000000),0) -> 0.15008 | N51: =IF(AND(ISNUMBER(B51),B51>0),A51*(((G51+H51)*B51+(I51+J51)*C51)/1000),0) -> 0.938 | O51: =IF(E51="HERRAJE",IFERROR(_xlfn.XLOOKUP(D51,'⚙️ Configuración Costos'!$A$11:$A$20,'⚙️ Configuración Costos'!$B$11:$B$20),""),IFERROR(_xlfn.XLOOKUP(E51,'⚙️ Configuración Costos'!$A$5:$A$6,'⚙️ Configuración Costos'!$B$5:$B$6),"")) -> 239.84262 | P51: =IF(E51="HERRAJE",A51*O51,M51*O51) -> 35.995581 | Q51: =IF(E51="HERRAJE",0,IFERROR(_xlfn.XLOOKUP(E51,'⚙️ Configuración Costos'!$E$5:$E$6,'⚙️ Configuración Costos'!$F$5:$F$6),"")) -> 6 | R51: =N51*Q51 -> 5.628 | S51: =P51+R51 -> 41.623581 | T51: =IF(K51="","SIN ID MÓDULO",IF(E51="HERRAJE",IF(OR(O51="",O51<=0),"SIN PRECIO HERRAJE","OK"),IF(OR(O51="",O51<=0),"SIN PRECIO MATERIAL",IF(AND(N51>0,OR(Q51="",Q51<=0)),"SIN PRECIO CINTILLA","OK")))) -> OK | U51: =IF(T51="OK","",IF(T51="SIN PRECIO HERRAJE","Capturar precio: "&D51,IF(T51="SIN PRECIO MATERIAL","Configurar material: "&E51,IF(T51="SIN PRECIO CINTILLA","Configurar cintilla: "&E51,IF(T51="SIN ID MÓDULO","Revisar ID del módulo",""))))) | V51: =IF(T51="OK",0,IF(T51="",0,1)) -> 0
A52: 1 | B52: 469 | C52: 320 | D52: Techo Alacena | E52: ARAUCO BLANCO | F52: 0 | G52: 1 | H52: 1 | I52: 0 | J52: 0 | K52: ALA-1PU-506832 | L52: TEC-ALA-5032 | M52: =IF(AND(ISNUMBER(B52),ISNUMBER(C52),B52>0,C52>0),A52*(B52*C52/1000000),0) -> 0.15008 | N52: =IF(AND(ISNUMBER(B52),B52>0),A52*(((G52+H52)*B52+(I52+J52)*C52)/1000),0) -> 0.938 | O52: =IF(E52="HERRAJE",IFERROR(_xlfn.XLOOKUP(D52,'⚙️ Configuración Costos'!$A$11:$A$20,'⚙️ Configuración Costos'!$B$11:$B$20),""),IFERROR(_xlfn.XLOOKUP(E52,'⚙️ Configuración Costos'!$A$5:$A$6,'⚙️ Configuración Costos'!$B$5:$B$6),"")) -> 239.84262 | P52: =IF(E52="HERRAJE",A52*O52,M52*O52) -> 35.995581 | Q52: =IF(E52="HERRAJE",0,IFERROR(_xlfn.XLOOKUP(E52,'⚙️ Configuración Costos'!$E$5:$E$6,'⚙️ Configuración Costos'!$F$5:$F$6),"")) -> 6 | R52: =N52*Q52 -> 5.628 | S52: =P52+R52 -> 41.623581 | T52: =IF(K52="","SIN ID MÓDULO",IF(E52="HERRAJE",IF(OR(O52="",O52<=0),"SIN PRECIO HERRAJE","OK"),IF(OR(O52="",O52<=0),"SIN PRECIO MATERIAL",IF(AND(N52>0,OR(Q52="",Q52<=0)),"SIN PRECIO CINTILLA","OK")))) -> OK | U52: =IF(T52="OK","",IF(T52="SIN PRECIO HERRAJE","Capturar precio: "&D52,IF(T52="SIN PRECIO MATERIAL","Configurar material: "&E52,IF(T52="SIN PRECIO CINTILLA","Configurar cintilla: "&E52,IF(T52="SIN ID MÓDULO","Revisar ID del módulo",""))))) | V52: =IF(T52="OK",0,IF(T52="",0,1)) -> 0
A53: 1 | B53: 469 | C53: 256 | D53: Entrepano Alacena | E53: ARAUCO BLANCO | F53: 0 | G53: 1 | H53: 1 | I53: 0 | J53: 0 | K53: ALA-1PU-506832 | L53: ENT-ALA-5026 | M53: =IF(AND(ISNUMBER(B53),ISNUMBER(C53),B53>0,C53>0),A53*(B53*C53/1000000),0) -> 0.120064 | N53: =IF(AND(ISNUMBER(B53),B53>0),A53*(((G53+H53)*B53+(I53+J53)*C53)/1000),0) -> 0.938 | O53: =IF(E53="HERRAJE",IFERROR(_xlfn.XLOOKUP(D53,'⚙️ Configuración Costos'!$A$11:$A$20,'⚙️ Configuración Costos'!$B$11:$B$20),""),IFERROR(_xlfn.XLOOKUP(E53,'⚙️ Configuración Costos'!$A$5:$A$6,'⚙️ Configuración Costos'!$B$5:$B$6),"")) -> 239.84262 | P53: =IF(E53="HERRAJE",A53*O53,M53*O53) -> 28.796465 | Q53: =IF(E53="HERRAJE",0,IFERROR(_xlfn.XLOOKUP(E53,'⚙️ Configuración Costos'!$E$5:$E$6,'⚙️ Configuración Costos'!$F$5:$F$6),"")) -> 6 | R53: =N53*Q53 -> 5.628 | S53: =P53+R53 -> 34.424465 | T53: =IF(K53="","SIN ID MÓDULO",IF(E53="HERRAJE",IF(OR(O53="",O53<=0),"SIN PRECIO HERRAJE","OK"),IF(OR(O53="",O53<=0),"SIN PRECIO MATERIAL",IF(AND(N53>0,OR(Q53="",Q53<=0)),"SIN PRECIO CINTILLA","OK")))) -> OK | U53: =IF(T53="OK","",IF(T53="SIN PRECIO HERRAJE","Capturar precio: "&D53,IF(T53="SIN PRECIO MATERIAL","Configurar material: "&E53,IF(T53="SIN PRECIO CINTILLA","Configurar cintilla: "&E53,IF(T53="SIN ID MÓDULO","Revisar ID del módulo",""))))) | V53: =IF(T53="OK",0,IF(T53="",0,1)) -> 0
A54: 1 | B54: 677 | C54: 497 | D54: Puerta Alacena | E54: VESTO NOUGAT | F54: 1 | G54: 1 | H54: 1 | I54: 1 | J54: 1 | K54: ALA-1PU-506832 | L54: PUE-ALA-6850 | M54: =IF(AND(ISNUMBER(B54),ISNUMBER(C54),B54>0,C54>0),A54*(B54*C54/1000000),0) -> 0.336469 | N54: =IF(AND(ISNUMBER(B54),B54>0),A54*(((G54+H54)*B54+(I54+J54)*C54)/1000),0) -> 2.348 | O54: =IF(E54="HERRAJE",IFERROR(_xlfn.XLOOKUP(D54,'⚙️ Configuración Costos'!$A$11:$A$20,'⚙️ Configuración Costos'!$B$11:$B$20),""),IFERROR(_xlfn.XLOOKUP(E54,'⚙️ Configuración Costos'!$A$5:$A$6,'⚙️ Configuración Costos'!$B$5:$B$6),"")) -> 332.85246 | P54: =IF(E54="HERRAJE",A54*O54,M54*O54) -> 111.99453 | Q54: =IF(E54="HERRAJE",0,IFERROR(_xlfn.XLOOKUP(E54,'⚙️ Configuración Costos'!$E$5:$E$6,'⚙️ Configuración Costos'!$F$5:$F$6),"")) -> 9.5 | R54: =N54*Q54 -> 22.306 | S54: =P54+R54 -> 134.30053 | T54: =IF(K54="","SIN ID MÓDULO",IF(E54="HERRAJE",IF(OR(O54="",O54<=0),"SIN PRECIO HERRAJE","OK"),IF(OR(O54="",O54<=0),"SIN PRECIO MATERIAL",IF(AND(N54>0,OR(Q54="",Q54<=0)),"SIN PRECIO CINTILLA","OK")))) -> OK | U54: =IF(T54="OK","",IF(T54="SIN PRECIO HERRAJE","Capturar precio: "&D54,IF(T54="SIN PRECIO MATERIAL","Configurar material: "&E54,IF(T54="SIN PRECIO CINTILLA","Configurar cintilla: "&E54,IF(T54="SIN ID MÓDULO","Revisar ID del módulo",""))))) | V54: =IF(T54="OK",0,IF(T54="",0,1)) -> 0
A55: 2 | B55: 0 | C55: 0 | D55: Bisagra Cierre Lento | E55: HERRAJE | F55: 0 | G55: 0 | H55: 0 | I55: 0 | J55: 0 | K55: ALA-1PU-506832 | L55: BIS-CL | M55: =IF(AND(ISNUMBER(B55),ISNUMBER(C55),B55>0,C55>0),A55*(B55*C55/1000000),0) -> 0 | N55: =IF(AND(ISNUMBER(B55),B55>0),A55*(((G55+H55)*B55+(I55+J55)*C55)/1000),0) -> 0 | O55: =IF(E55="HERRAJE",IFERROR(_xlfn.XLOOKUP(D55,'⚙️ Configuración Costos'!$A$11:$A$20,'⚙️ Configuración Costos'!$B$11:$B$20),""),IFERROR(_xlfn.XLOOKUP(E55,'⚙️ Configuración Costos'!$A$5:$A$6,'⚙️ Configuración Costos'!$B$5:$B$6),"")) -> 20 | P55: =IF(E55="HERRAJE",A55*O55,M55*O55) -> 40 | Q55: =IF(E55="HERRAJE",0,IFERROR(_xlfn.XLOOKUP(E55,'⚙️ Configuración Costos'!$E$5:$E$6,'⚙️ Configuración Costos'!$F$5:$F$6),"")) -> 0 | R55: =N55*Q55 -> 0 | S55: =P55+R55 -> 40 | T55: =IF(K55="","SIN ID MÓDULO",IF(E55="HERRAJE",IF(OR(O55="",O55<=0),"SIN PRECIO HERRAJE","OK"),IF(OR(O55="",O55<=0),"SIN PRECIO MATERIAL",IF(AND(N55>0,OR(Q55="",Q55<=0)),"SIN PRECIO CINTILLA","OK")))) -> OK | U55: =IF(T55="OK","",IF(T55="SIN PRECIO HERRAJE","Capturar precio: "&D55,IF(T55="SIN PRECIO MATERIAL","Configurar material: "&E55,IF(T55="SIN PRECIO CINTILLA","Configurar cintilla: "&E55,IF(T55="SIN ID MÓDULO","Revisar ID del módulo",""))))) | V55: =IF(T55="OK",0,IF(T55="",0,1)) -> 0
A56: 1 | B56: 0 | C56: 0 | D56: Jaladera Acero Inox | E56: HERRAJE | F56: 0 | G56: 0 | H56: 0 | I56: 0 | J56: 0 | K56: ALA-1PU-506832 | L56: JAL-INOX | M56: =IF(AND(ISNUMBER(B56),ISNUMBER(C56),B56>0,C56>0),A56*(B56*C56/1000000),0) -> 0 | N56: =IF(AND(ISNUMBER(B56),B56>0),A56*(((G56+H56)*B56+(I56+J56)*C56)/1000),0) -> 0 | O56: =IF(E56="HERRAJE",IFERROR(_xlfn.XLOOKUP(D56,'⚙️ Configuración Costos'!$A$11:$A$20,'⚙️ Configuración Costos'!$B$11:$B$20),""),IFERROR(_xlfn.XLOOKUP(E56,'⚙️ Configuración Costos'!$A$5:$A$6,'⚙️ Configuración Costos'!$B$5:$B$6),"")) -> 15 | P56: =IF(E56="HERRAJE",A56*O56,M56*O56) -> 15 | Q56: =IF(E56="HERRAJE",0,IFERROR(_xlfn.XLOOKUP(E56,'⚙️ Configuración Costos'!$E$5:$E$6,'⚙️ Configuración Costos'!$F$5:$F$6),"")) -> 0 | R56: =N56*Q56 -> 0 | S56: =P56+R56 -> 15 | T56: =IF(K56="","SIN ID MÓDULO",IF(E56="HERRAJE",IF(OR(O56="",O56<=0),"SIN PRECIO HERRAJE","OK"),IF(OR(O56="",O56<=0),"SIN PRECIO MATERIAL",IF(AND(N56>0,OR(Q56="",Q56<=0)),"SIN PRECIO CINTILLA","OK")))) -> OK | U56: =IF(T56="OK","",IF(T56="SIN PRECIO HERRAJE","Capturar precio: "&D56,IF(T56="SIN PRECIO MATERIAL","Configurar material: "&E56,IF(T56="SIN PRECIO CINTILLA","Configurar cintilla: "&E56,IF(T56="SIN ID MÓDULO","Revisar ID del módulo",""))))) | V56: =IF(T56="OK",0,IF(T56="",0,1)) -> 0
A57: 4 | B57: 0 | C57: 0 | D57: Soporte de Entrepaño | E57: HERRAJE | F57: 0 | G57: 0 | H57: 0 | I57: 0 | J57: 0 | K57: ALA-1PU-506832 | L57: SOP-ENT | M57: =IF(AND(ISNUMBER(B57),ISNUMBER(C57),B57>0,C57>0),A57*(B57*C57/1000000),0) -> 0 | N57: =IF(AND(ISNUMBER(B57),B57>0),A57*(((G57+H57)*B57+(I57+J57)*C57)/1000),0) -> 0 | O57: =IF(E57="HERRAJE",IFERROR(_xlfn.XLOOKUP(D57,'⚙️ Configuración Costos'!$A$11:$A$20,'⚙️ Configuración Costos'!$B$11:$B$20),""),IFERROR(_xlfn.XLOOKUP(E57,'⚙️ Configuración Costos'!$A$5:$A$6,'⚙️ Configuración Costos'!$B$5:$B$6),"")) -> 2 | P57: =IF(E57="HERRAJE",A57*O57,M57*O57) -> 8 | Q57: =IF(E57="HERRAJE",0,IFERROR(_xlfn.XLOOKUP(E57,'⚙️ Configuración Costos'!$E$5:$E$6,'⚙️ Configuración Costos'!$F$5:$F$6),"")) -> 0 | R57: =N57*Q57 -> 0 | S57: =P57+R57 -> 8 | T57: =IF(K57="","SIN ID MÓDULO",IF(E57="HERRAJE",IF(OR(O57="",O57<=0),"SIN PRECIO HERRAJE","OK"),IF(OR(O57="",O57<=0),"SIN PRECIO MATERIAL",IF(AND(N57>0,OR(Q57="",Q57<=0)),"SIN PRECIO CINTILLA","OK")))) -> OK | U57: =IF(T57="OK","",IF(T57="SIN PRECIO HERRAJE","Capturar precio: "&D57,IF(T57="SIN PRECIO MATERIAL","Configurar material: "&E57,IF(T57="SIN PRECIO CINTILLA","Configurar cintilla: "&E57,IF(T57="SIN ID MÓDULO","Revisar ID del módulo",""))))) | V57: =IF(T57="OK",0,IF(T57="",0,1)) -> 0
A58: 24 | B58: 0 | C58: 0 | D58: Tornillo 4x50 mm | E58: HERRAJE | F58: 0 | G58: 0 | H58: 0 | I58: 0 | J58: 0 | K58: ALA-1PU-506832 | L58: TOR-4X50 | M58: =IF(AND(ISNUMBER(B58),ISNUMBER(C58),B58>0,C58>0),A58*(B58*C58/1000000),0) -> 0 | N58: =IF(AND(ISNUMBER(B58),B58>0),A58*(((G58+H58)*B58+(I58+J58)*C58)/1000),0) -> 0 | O58: =IF(E58="HERRAJE",IFERROR(_xlfn.XLOOKUP(D58,'⚙️ Configuración Costos'!$A$11:$A$20,'⚙️ Configuración Costos'!$B$11:$B$20),""),IFERROR(_xlfn.XLOOKUP(E58,'⚙️ Configuración Costos'!$A$5:$A$6,'⚙️ Configuración Costos'!$B$5:$B$6),"")) -> 1.5 | P58: =IF(E58="HERRAJE",A58*O58,M58*O58) -> 36 | Q58: =IF(E58="HERRAJE",0,IFERROR(_xlfn.XLOOKUP(E58,'⚙️ Configuración Costos'!$E$5:$E$6,'⚙️ Configuración Costos'!$F$5:$F$6),"")) -> 0 | R58: =N58*Q58 -> 0 | S58: =P58+R58 -> 36 | T58: =IF(K58="","SIN ID MÓDULO",IF(E58="HERRAJE",IF(OR(O58="",O58<=0),"SIN PRECIO HERRAJE","OK"),IF(OR(O58="",O58<=0),"SIN PRECIO MATERIAL",IF(AND(N58>0,OR(Q58="",Q58<=0)),"SIN PRECIO CINTILLA","OK")))) -> OK | U58: =IF(T58="OK","",IF(T58="SIN PRECIO HERRAJE","Capturar precio: "&D58,IF(T58="SIN PRECIO MATERIAL","Configurar material: "&E58,IF(T58="SIN PRECIO CINTILLA","Configurar cintilla: "&E58,IF(T58="SIN ID MÓDULO","Revisar ID del módulo",""))))) | V58: =IF(T58="OK",0,IF(T58="",0,1)) -> 0
A59: TOTALES | M59: =SUM(M48:M58) -> 1.496274 | N59: =SUM(N48:N58) -> 9.162 | P59: =SUM(P48:P58) -> 489.16521 | R59: =SUM(R48:R58) -> 63.19 | S59: =SUM(S48:S58) -> 552.35521
A60: Alacena 1 Puerta 600 x 680 x 320 mm
A61: 1 | B61: 680 | C61: 320 | D61: Lateral Derecho | E61: ARAUCO BLANCO | F61: 0 | G61: 1 | H61: 1 | I61: 1 | J61: 1 | K61: ALA-1PU-606832 | L61: LAT-ALA-6832-D | M61: =IF(AND(ISNUMBER(B61),ISNUMBER(C61),B61>0,C61>0),A61*(B61*C61/1000000),0) -> 0.2176 | N61: =IF(AND(ISNUMBER(B61),B61>0),A61*(((G61+H61)*B61+(I61+J61)*C61)/1000),0) -> 2 | O61: =IF(E61="HERRAJE",IFERROR(_xlfn.XLOOKUP(D61,'⚙️ Configuración Costos'!$A$11:$A$20,'⚙️ Configuración Costos'!$B$11:$B$20),""),IFERROR(_xlfn.XLOOKUP(E61,'⚙️ Configuración Costos'!$A$5:$A$6,'⚙️ Configuración Costos'!$B$5:$B$6),"")) -> 239.84262 | P61: =IF(E61="HERRAJE",A61*O61,M61*O61) -> 52.189755 | Q61: =IF(E61="HERRAJE",0,IFERROR(_xlfn.XLOOKUP(E61,'⚙️ Configuración Costos'!$E$5:$E$6,'⚙️ Configuración Costos'!$F$5:$F$6),"")) -> 6 | R61: =N61*Q61 -> 12 | S61: =P61+R61 -> 64.189755 | T61: =IF(K61="","SIN ID MÓDULO",IF(E61="HERRAJE",IF(OR(O61="",O61<=0),"SIN PRECIO HERRAJE","OK"),IF(OR(O61="",O61<=0),"SIN PRECIO MATERIAL",IF(AND(N61>0,OR(Q61="",Q61<=0)),"SIN PRECIO CINTILLA","OK")))) -> OK | U61: =IF(T61="OK","",IF(T61="SIN PRECIO HERRAJE","Capturar precio: "&D61,IF(T61="SIN PRECIO MATERIAL","Configurar material: "&E61,IF(T61="SIN PRECIO CINTILLA","Configurar cintilla: "&E61,IF(T61="SIN ID MÓDULO","Revisar ID del módulo",""))))) | V61: =IF(T61="OK",0,IF(T61="",0,1)) -> 0
A62: 1 | B62: 680 | C62: 320 | D62: Lateral Izquierdo | E62: ARAUCO BLANCO | F62: 0 | G62: 1 | H62: 1 | I62: 1 | J62: 1 | K62: ALA-1PU-606832 | L62: LAT-ALA-6832-I | M62: =IF(AND(ISNUMBER(B62),ISNUMBER(C62),B62>0,C62>0),A62*(B62*C62/1000000),0) -> 0.2176 | N62: =IF(AND(ISNUMBER(B62),B62>0),A62*(((G62+H62)*B62+(I62+J62)*C62)/1000),0) -> 2 | O62: =IF(E62="HERRAJE",IFERROR(_xlfn.XLOOKUP(D62,'⚙️ Configuración Costos'!$A$11:$A$20,'⚙️ Configuración Costos'!$B$11:$B$20),""),IFERROR(_xlfn.XLOOKUP(E62,'⚙️ Configuración Costos'!$A$5:$A$6,'⚙️ Configuración Costos'!$B$5:$B$6),"")) -> 239.84262 | P62: =IF(E62="HERRAJE",A62*O62,M62*O62) -> 52.189755 | Q62: =IF(E62="HERRAJE",0,IFERROR(_xlfn.XLOOKUP(E62,'⚙️ Configuración Costos'!$E$5:$E$6,'⚙️ Configuración Costos'!$F$5:$F$6),"")) -> 6 | R62: =N62*Q62 -> 12 | S62: =P62+R62 -> 64.189755 | T62: =IF(K62="","SIN ID MÓDULO",IF(E62="HERRAJE",IF(OR(O62="",O62<=0),"SIN PRECIO HERRAJE","OK"),IF(OR(O62="",O62<=0),"SIN PRECIO MATERIAL",IF(AND(N62>0,OR(Q62="",Q62<=0)),"SIN PRECIO CINTILLA","OK")))) -> OK | U62: =IF(T62="OK","",IF(T62="SIN PRECIO HERRAJE","Capturar precio: "&D62,IF(T62="SIN PRECIO MATERIAL","Configurar material: "&E62,IF(T62="SIN PRECIO CINTILLA","Configurar cintilla: "&E62,IF(T62="SIN ID MÓDULO","Revisar ID del módulo",""))))) | V62: =IF(T62="OK",0,IF(T62="",0,1)) -> 0
A63: 1 | B63: 649 | C63: 569 | D63: Respaldo Alacena | E63: ARAUCO BLANCO | F63: 0 | G63: 0 | H63: 0 | I63: 0 | J63: 0 | K63: ALA-1PU-606832 | L63: RES-ALA-6860 | M63: =IF(AND(ISNUMBER(B63),ISNUMBER(C63),B63>0,C63>0),A63*(B63*C63/1000000),0) -> 0.369281 | N63: =IF(AND(ISNUMBER(B63),B63>0),A63*(((G63+H63)*B63+(I63+J63)*C63)/1000),0) -> 0 | O63: =IF(E63="HERRAJE",IFERROR(_xlfn.XLOOKUP(D63,'⚙️ Configuración Costos'!$A$11:$A$20,'⚙️ Configuración Costos'!$B$11:$B$20),""),IFERROR(_xlfn.XLOOKUP(E63,'⚙️ Configuración Costos'!$A$5:$A$6,'⚙️ Configuración Costos'!$B$5:$B$6),"")) -> 239.84262 | P63: =IF(E63="HERRAJE",A63*O63,M63*O63) -> 88.569324 | Q63: =IF(E63="HERRAJE",0,IFERROR(_xlfn.XLOOKUP(E63,'⚙️ Configuración Costos'!$E$5:$E$6,'⚙️ Configuración Costos'!$F$5:$F$6),"")) -> 6 | R63: =N63*Q63 -> 0 | S63: =P63+R63 -> 88.569324 | T63: =IF(K63="","SIN ID MÓDULO",IF(E63="HERRAJE",IF(OR(O63="",O63<=0),"SIN PRECIO HERRAJE","OK"),IF(OR(O63="",O63<=0),"SIN PRECIO MATERIAL",IF(AND(N63>0,OR(Q63="",Q63<=0)),"SIN PRECIO CINTILLA","OK")))) -> OK | U63: =IF(T63="OK","",IF(T63="SIN PRECIO HERRAJE","Capturar precio: "&D63,IF(T63="SIN PRECIO MATERIAL","Configurar material: "&E63,IF(T63="SIN PRECIO CINTILLA","Configurar cintilla: "&E63,IF(T63="SIN ID MÓDULO","Revisar ID del módulo",""))))) | V63: =IF(T63="OK",0,IF(T63="",0,1)) -> 0
A64: 1 | B64: 569 | C64: 320 | D64: Base Alacena | E64: ARAUCO BLANCO | F64: 0 | G64: 1 | H64: 1 | I64: 0 | J64: 0 | K64: ALA-1PU-606832 | L64: BAS-ALA-6032 | M64: =IF(AND(ISNUMBER(B64),ISNUMBER(C64),B64>0,C64>0),A64*(B64*C64/1000000),0) -> 0.18208 | N64: =IF(AND(ISNUMBER(B64),B64>0),A64*(((G64+H64)*B64+(I64+J64)*C64)/1000),0) -> 1.138 | O64: =IF(E64="HERRAJE",IFERROR(_xlfn.XLOOKUP(D64,'⚙️ Configuración Costos'!$A$11:$A$20,'⚙️ Configuración Costos'!$B$11:$B$20),""),IFERROR(_xlfn.XLOOKUP(E64,'⚙️ Configuración Costos'!$A$5:$A$6,'⚙️ Configuración Costos'!$B$5:$B$6),"")) -> 239.84262 | P64: =IF(E64="HERRAJE",A64*O64,M64*O64) -> 43.670545 | Q64: =IF(E64="HERRAJE",0,IFERROR(_xlfn.XLOOKUP(E64,'⚙️ Configuración Costos'!$E$5:$E$6,'⚙️ Configuración Costos'!$F$5:$F$6),"")) -> 6 | R64: =N64*Q64 -> 6.828 | S64: =P64+R64 -> 50.498545 | T64: =IF(K64="","SIN ID MÓDULO",IF(E64="HERRAJE",IF(OR(O64="",O64<=0),"SIN PRECIO HERRAJE","OK"),IF(OR(O64="",O64<=0),"SIN PRECIO MATERIAL",IF(AND(N64>0,OR(Q64="",Q64<=0)),"SIN PRECIO CINTILLA","OK")))) -> OK | U64: =IF(T64="OK","",IF(T64="SIN PRECIO HERRAJE","Capturar precio: "&D64,IF(T64="SIN PRECIO MATERIAL","Configurar material: "&E64,IF(T64="SIN PRECIO CINTILLA","Configurar cintilla: "&E64,IF(T64="SIN ID MÓDULO","Revisar ID del módulo",""))))) | V64: =IF(T64="OK",0,IF(T64="",0,1)) -> 0
A65: 1 | B65: 569 | C65: 320 | D65: Techo Alacena | E65: ARAUCO BLANCO | F65: 0 | G65: 1 | H65: 1 | I65: 0 | J65: 0 | K65: ALA-1PU-606832 | L65: TEC-ALA-6032 | M65: =IF(AND(ISNUMBER(B65),ISNUMBER(C65),B65>0,C65>0),A65*(B65*C65/1000000),0) -> 0.18208 | N65: =IF(AND(ISNUMBER(B65),B65>0),A65*(((G65+H65)*B65+(I65+J65)*C65)/1000),0) -> 1.138 | O65: =IF(E65="HERRAJE",IFERROR(_xlfn.XLOOKUP(D65,'⚙️ Configuración Costos'!$A$11:$A$20,'⚙️ Configuración Costos'!$B$11:$B$20),""),IFERROR(_xlfn.XLOOKUP(E65,'⚙️ Configuración Costos'!$A$5:$A$6,'⚙️ Configuración Costos'!$B$5:$B$6),"")) -> 239.84262 | P65: =IF(E65="HERRAJE",A65*O65,M65*O65) -> 43.670545 | Q65: =IF(E65="HERRAJE",0,IFERROR(_xlfn.XLOOKUP(E65,'⚙️ Configuración Costos'!$E$5:$E$6,'⚙️ Configuración Costos'!$F$5:$F$6),"")) -> 6 | R65: =N65*Q65 -> 6.828 | S65: =P65+R65 -> 50.498545 | T65: =IF(K65="","SIN ID MÓDULO",IF(E65="HERRAJE",IF(OR(O65="",O65<=0),"SIN PRECIO HERRAJE","OK"),IF(OR(O65="",O65<=0),"SIN PRECIO MATERIAL",IF(AND(N65>0,OR(Q65="",Q65<=0)),"SIN PRECIO CINTILLA","OK")))) -> OK | U65: =IF(T65="OK","",IF(T65="SIN PRECIO HERRAJE","Capturar precio: "&D65,IF(T65="SIN PRECIO MATERIAL","Configurar material: "&E65,IF(T65="SIN PRECIO CINTILLA","Configurar cintilla: "&E65,IF(T65="SIN ID MÓDULO","Revisar ID del módulo",""))))) | V65: =IF(T65="OK",0,IF(T65="",0,1)) -> 0
A66: 1 | B66: 569 | C66: 256 | D66: Entrepano Alacena | E66: ARAUCO BLANCO | F66: 0 | G66: 1 | H66: 1 | I66: 0 | J66: 0 | K66: ALA-1PU-606832 | L66: ENT-ALA-6026 | M66: =IF(AND(ISNUMBER(B66),ISNUMBER(C66),B66>0,C66>0),A66*(B66*C66/1000000),0) -> 0.145664 | N66: =IF(AND(ISNUMBER(B66),B66>0),A66*(((G66+H66)*B66+(I66+J66)*C66)/1000),0) -> 1.138 | O66: =IF(E66="HERRAJE",IFERROR(_xlfn.XLOOKUP(D66,'⚙️ Configuración Costos'!$A$11:$A$20,'⚙️ Configuración Costos'!$B$11:$B$20),""),IFERROR(_xlfn.XLOOKUP(E66,'⚙️ Configuración Costos'!$A$5:$A$6,'⚙️ Configuración Costos'!$B$5:$B$6),"")) -> 239.84262 | P66: =IF(E66="HERRAJE",A66*O66,M66*O66) -> 34.936436 | Q66: =IF(E66="HERRAJE",0,IFERROR(_xlfn.XLOOKUP(E66,'⚙️ Configuración Costos'!$E$5:$E$6,'⚙️ Configuración Costos'!$F$5:$F$6),"")) -> 6 | R66: =N66*Q66 -> 6.828 | S66: =P66+R66 -> 41.764436 | T66: =IF(K66="","SIN ID MÓDULO",IF(E66="HERRAJE",IF(OR(O66="",O66<=0),"SIN PRECIO HERRAJE","OK"),IF(OR(O66="",O66<=0),"SIN PRECIO MATERIAL",IF(AND(N66>0,OR(Q66="",Q66<=0)),"SIN PRECIO CINTILLA","OK")))) -> OK | U66: =IF(T66="OK","",IF(T66="SIN PRECIO HERRAJE","Capturar precio: "&D66,IF(T66="SIN PRECIO MATERIAL","Configurar material: "&E66,IF(T66="SIN PRECIO CINTILLA","Configurar cintilla: "&E66,IF(T66="SIN ID MÓDULO","Revisar ID del módulo",""))))) | V66: =IF(T66="OK",0,IF(T66="",0,1)) -> 0
A67: 1 | B67: 677 | C67: 597 | D67: Puerta Alacena | E67: VESTO NOUGAT | F67: 1 | G67: 1 | H67: 1 | I67: 1 | J67: 1 | K67: ALA-1PU-606832 | L67: PUE-ALA-6860 | M67: =IF(AND(ISNUMBER(B67),ISNUMBER(C67),B67>0,C67>0),A67*(B67*C67/1000000),0) -> 0.404169 | N67: =IF(AND(ISNUMBER(B67),B67>0),A67*(((G67+H67)*B67+(I67+J67)*C67)/1000),0) -> 2.548 | O67: =IF(E67="HERRAJE",IFERROR(_xlfn.XLOOKUP(D67,'⚙️ Configuración Costos'!$A$11:$A$20,'⚙️ Configuración Costos'!$B$11:$B$20),""),IFERROR(_xlfn.XLOOKUP(E67,'⚙️ Configuración Costos'!$A$5:$A$6,'⚙️ Configuración Costos'!$B$5:$B$6),"")) -> 332.85246 | P67: =IF(E67="HERRAJE",A67*O67,M67*O67) -> 134.52865 | Q67: =IF(E67="HERRAJE",0,IFERROR(_xlfn.XLOOKUP(E67,'⚙️ Configuración Costos'!$E$5:$E$6,'⚙️ Configuración Costos'!$F$5:$F$6),"")) -> 9.5 | R67: =N67*Q67 -> 24.206 | S67: =P67+R67 -> 158.73465 | T67: =IF(K67="","SIN ID MÓDULO",IF(E67="HERRAJE",IF(OR(O67="",O67<=0),"SIN PRECIO HERRAJE","OK"),IF(OR(O67="",O67<=0),"SIN PRECIO MATERIAL",IF(AND(N67>0,OR(Q67="",Q67<=0)),"SIN PRECIO CINTILLA","OK")))) -> OK | U67: =IF(T67="OK","",IF(T67="SIN PRECIO HERRAJE","Capturar precio: "&D67,IF(T67="SIN PRECIO MATERIAL","Configurar material: "&E67,IF(T67="SIN PRECIO CINTILLA","Configurar cintilla: "&E67,IF(T67="SIN ID MÓDULO","Revisar ID del módulo",""))))) | V67: =IF(T67="OK",0,IF(T67="",0,1)) -> 0
A68: 2 | B68: 0 | C68: 0 | D68: Bisagra Cierre Lento | E68: HERRAJE | F68: 0 | G68: 0 | H68: 0 | I68: 0 | J68: 0 | K68: ALA-1PU-606832 | L68: BIS-CL | M68: =IF(AND(ISNUMBER(B68),ISNUMBER(C68),B68>0,C68>0),A68*(B68*C68/1000000),0) -> 0 | N68: =IF(AND(ISNUMBER(B68),B68>0),A68*(((G68+H68)*B68+(I68+J68)*C68)/1000),0) -> 0 | O68: =IF(E68="HERRAJE",IFERROR(_xlfn.XLOOKUP(D68,'⚙️ Configuración Costos'!$A$11:$A$20,'⚙️ Configuración Costos'!$B$11:$B$20),""),IFERROR(_xlfn.XLOOKUP(E68,'⚙️ Configuración Costos'!$A$5:$A$6,'⚙️ Configuración Costos'!$B$5:$B$6),"")) -> 20 | P68: =IF(E68="HERRAJE",A68*O68,M68*O68) -> 40 | Q68: =IF(E68="HERRAJE",0,IFERROR(_xlfn.XLOOKUP(E68,'⚙️ Configuración Costos'!$E$5:$E$6,'⚙️ Configuración Costos'!$F$5:$F$6),"")) -> 0 | R68: =N68*Q68 -> 0 | S68: =P68+R68 -> 40 | T68: =IF(K68="","SIN ID MÓDULO",IF(E68="HERRAJE",IF(OR(O68="",O68<=0),"SIN PRECIO HERRAJE","OK"),IF(OR(O68="",O68<=0),"SIN PRECIO MATERIAL",IF(AND(N68>0,OR(Q68="",Q68<=0)),"SIN PRECIO CINTILLA","OK")))) -> OK | U68: =IF(T68="OK","",IF(T68="SIN PRECIO HERRAJE","Capturar precio: "&D68,IF(T68="SIN PRECIO MATERIAL","Configurar material: "&E68,IF(T68="SIN PRECIO CINTILLA","Configurar cintilla: "&E68,IF(T68="SIN ID MÓDULO","Revisar ID del módulo",""))))) | V68: =IF(T68="OK",0,IF(T68="",0,1)) -> 0
A69: 1 | B69: 0 | C69: 0 | D69: Jaladera Acero Inox | E69: HERRAJE | F69: 0 | G69: 0 | H69: 0 | I69: 0 | J69: 0 | K69: ALA-1PU-606832 | L69: JAL-INOX | M69: =IF(AND(ISNUMBER(B69),ISNUMBER(C69),B69>0,C69>0),A69*(B69*C69/1000000),0) -> 0 | N69: =IF(AND(ISNUMBER(B69),B69>0),A69*(((G69+H69)*B69+(I69+J69)*C69)/1000),0) -> 0 | O69: =IF(E69="HERRAJE",IFERROR(_xlfn.XLOOKUP(D69,'⚙️ Configuración Costos'!$A$11:$A$20,'⚙️ Configuración Costos'!$B$11:$B$20),""),IFERROR(_xlfn.XLOOKUP(E69,'⚙️ Configuración Costos'!$A$5:$A$6,'⚙️ Configuración Costos'!$B$5:$B$6),"")) -> 15 | P69: =IF(E69="HERRAJE",A69*O69,M69*O69) -> 15 | Q69: =IF(E69="HERRAJE",0,IFERROR(_xlfn.XLOOKUP(E69,'⚙️ Configuración Costos'!$E$5:$E$6,'⚙️ Configuración Costos'!$F$5:$F$6),"")) -> 0 | R69: =N69*Q69 -> 0 | S69: =P69+R69 -> 15 | T69: =IF(K69="","SIN ID MÓDULO",IF(E69="HERRAJE",IF(OR(O69="",O69<=0),"SIN PRECIO HERRAJE","OK"),IF(OR(O69="",O69<=0),"SIN PRECIO MATERIAL",IF(AND(N69>0,OR(Q69="",Q69<=0)),"SIN PRECIO CINTILLA","OK")))) -> OK | U69: =IF(T69="OK","",IF(T69="SIN PRECIO HERRAJE","Capturar precio: "&D69,IF(T69="SIN PRECIO MATERIAL","Configurar material: "&E69,IF(T69="SIN PRECIO CINTILLA","Configurar cintilla: "&E69,IF(T69="SIN ID MÓDULO","Revisar ID del módulo",""))))) | V69: =IF(T69="OK",0,IF(T69="",0,1)) -> 0
A70: 4 | B70: 0 | C70: 0 | D70: Soporte de Entrepaño | E70: HERRAJE | F70: 0 | G70: 0 | H70: 0 | I70: 0 | J70: 0 | K70: ALA-1PU-606832 | L70: SOP-ENT | M70: =IF(AND(ISNUMBER(B70),ISNUMBER(C70),B70>0,C70>0),A70*(B70*C70/1000000),0) -> 0 | N70: =IF(AND(ISNUMBER(B70),B70>0),A70*(((G70+H70)*B70+(I70+J70)*C70)/1000),0) -> 0 | O70: =IF(E70="HERRAJE",IFERROR(_xlfn.XLOOKUP(D70,'⚙️ Configuración Costos'!$A$11:$A$20,'⚙️ Configuración Costos'!$B$11:$B$20),""),IFERROR(_xlfn.XLOOKUP(E70,'⚙️ Configuración Costos'!$A$5:$A$6,'⚙️ Configuración Costos'!$B$5:$B$6),"")) -> 2 | P70: =IF(E70="HERRAJE",A70*O70,M70*O70) -> 8 | Q70: =IF(E70="HERRAJE",0,IFERROR(_xlfn.XLOOKUP(E70,'⚙️ Configuración Costos'!$E$5:$E$6,'⚙️ Configuración Costos'!$F$5:$F$6),"")) -> 0 | R70: =N70*Q70 -> 0 | S70: =P70+R70 -> 8 | T70: =IF(K70="","SIN ID MÓDULO",IF(E70="HERRAJE",IF(OR(O70="",O70<=0),"SIN PRECIO HERRAJE","OK"),IF(OR(O70="",O70<=0),"SIN PRECIO MATERIAL",IF(AND(N70>0,OR(Q70="",Q70<=0)),"SIN PRECIO CINTILLA","OK")))) -> OK | U70: =IF(T70="OK","",IF(T70="SIN PRECIO HERRAJE","Capturar precio: "&D70,IF(T70="SIN PRECIO MATERIAL","Configurar material: "&E70,IF(T70="SIN PRECIO CINTILLA","Configurar cintilla: "&E70,IF(T70="SIN ID MÓDULO","Revisar ID del módulo",""))))) | V70: =IF(T70="OK",0,IF(T70="",0,1)) -> 0
A71: 24 | B71: 0 | C71: 0 | D71: Tornillo 4x50 mm | E71: HERRAJE | F71: 0 | G71: 0 | H71: 0 | I71: 0 | J71: 0 | K71: ALA-1PU-606832 | L71: TOR-4X50 | M71: =IF(AND(ISNUMBER(B71),ISNUMBER(C71),B71>0,C71>0),A71*(B71*C71/1000000),0) -> 0 | N71: =IF(AND(ISNUMBER(B71),B71>0),A71*(((G71+H71)*B71+(I71+J71)*C71)/1000),0) -> 0 | O71: =IF(E71="HERRAJE",IFERROR(_xlfn.XLOOKUP(D71,'⚙️ Configuración Costos'!$A$11:$A$20,'⚙️ Configuración Costos'!$B$11:$B$20),""),IFERROR(_xlfn.XLOOKUP(E71,'⚙️ Configuración Costos'!$A$5:$A$6,'⚙️ Configuración Costos'!$B$5:$B$6),"")) -> 1.5 | P71: =IF(E71="HERRAJE",A71*O71,M71*O71) -> 36 | Q71: =IF(E71="HERRAJE",0,IFERROR(_xlfn.XLOOKUP(E71,'⚙️ Configuración Costos'!$E$5:$E$6,'⚙️ Configuración Costos'!$F$5:$F$6),"")) -> 0 | R71: =N71*Q71 -> 0 | S71: =P71+R71 -> 36 | T71: =IF(K71="","SIN ID MÓDULO",IF(E71="HERRAJE",IF(OR(O71="",O71<=0),"SIN PRECIO HERRAJE","OK"),IF(OR(O71="",O71<=0),"SIN PRECIO MATERIAL",IF(AND(N71>0,OR(Q71="",Q71<=0)),"SIN PRECIO CINTILLA","OK")))) -> OK | U71: =IF(T71="OK","",IF(T71="SIN PRECIO HERRAJE","Capturar precio: "&D71,IF(T71="SIN PRECIO MATERIAL","Configurar material: "&E71,IF(T71="SIN PRECIO CINTILLA","Configurar cintilla: "&E71,IF(T71="SIN ID MÓDULO","Revisar ID del módulo",""))))) | V71: =IF(T71="OK",0,IF(T71="",0,1)) -> 0
A72: TOTALES | M72: =SUM(M61:M71) -> 1.718474 | N72: =SUM(N61:N71) -> 9.962 | P72: =SUM(P61:P71) -> 548.755 | R72: =SUM(R61:R71) -> 68.69 | S72: =SUM(S61:S71) -> 617.445
A73: Alacena 2 Puertas 700 x 680 x 320 mm
A74: 1 | B74: 680 | C74: 320 | D74: Lateral Derecho | E74: ARAUCO BLANCO | F74: 0 | G74: 1 | H74: 1 | I74: 1 | J74: 1 | K74: ALA-2PU-706832 | L74: LAT-ALA-6832-D | M74: =IF(AND(ISNUMBER(B74),ISNUMBER(C74),B74>0,C74>0),A74*(B74*C74/1000000),0) -> 0.2176 | N74: =IF(AND(ISNUMBER(B74),B74>0),A74*(((G74+H74)*B74+(I74+J74)*C74)/1000),0) -> 2 | O74: =IF(E74="HERRAJE",IFERROR(_xlfn.XLOOKUP(D74,'⚙️ Configuración Costos'!$A$11:$A$20,'⚙️ Configuración Costos'!$B$11:$B$20),""),IFERROR(_xlfn.XLOOKUP(E74,'⚙️ Configuración Costos'!$A$5:$A$6,'⚙️ Configuración Costos'!$B$5:$B$6),"")) -> 239.84262 | P74: =IF(E74="HERRAJE",A74*O74,M74*O74) -> 52.189755 | Q74: =IF(E74="HERRAJE",0,IFERROR(_xlfn.XLOOKUP(E74,'⚙️ Configuración Costos'!$E$5:$E$6,'⚙️ Configuración Costos'!$F$5:$F$6),"")) -> 6 | R74: =N74*Q74 -> 12 | S74: =P74+R74 -> 64.189755 | T74: =IF(K74="","SIN ID MÓDULO",IF(E74="HERRAJE",IF(OR(O74="",O74<=0),"SIN PRECIO HERRAJE","OK"),IF(OR(O74="",O74<=0),"SIN PRECIO MATERIAL",IF(AND(N74>0,OR(Q74="",Q74<=0)),"SIN PRECIO CINTILLA","OK")))) -> OK | U74: =IF(T74="OK","",IF(T74="SIN PRECIO HERRAJE","Capturar precio: "&D74,IF(T74="SIN PRECIO MATERIAL","Configurar material: "&E74,IF(T74="SIN PRECIO CINTILLA","Configurar cintilla: "&E74,IF(T74="SIN ID MÓDULO","Revisar ID del módulo",""))))) | V74: =IF(T74="OK",0,IF(T74="",0,1)) -> 0
A75: 1 | B75: 680 | C75: 320 | D75: Lateral Izquierdo | E75: ARAUCO BLANCO | F75: 0 | G75: 1 | H75: 1 | I75: 1 | J75: 1 | K75: ALA-2PU-706832 | L75: LAT-ALA-6832-I | M75: =IF(AND(ISNUMBER(B75),ISNUMBER(C75),B75>0,C75>0),A75*(B75*C75/1000000),0) -> 0.2176 | N75: =IF(AND(ISNUMBER(B75),B75>0),A75*(((G75+H75)*B75+(I75+J75)*C75)/1000),0) -> 2 | O75: =IF(E75="HERRAJE",IFERROR(_xlfn.XLOOKUP(D75,'⚙️ Configuración Costos'!$A$11:$A$20,'⚙️ Configuración Costos'!$B$11:$B$20),""),IFERROR(_xlfn.XLOOKUP(E75,'⚙️ Configuración Costos'!$A$5:$A$6,'⚙️ Configuración Costos'!$B$5:$B$6),"")) -> 239.84262 | P75: =IF(E75="HERRAJE",A75*O75,M75*O75) -> 52.189755 | Q75: =IF(E75="HERRAJE",0,IFERROR(_xlfn.XLOOKUP(E75,'⚙️ Configuración Costos'!$E$5:$E$6,'⚙️ Configuración Costos'!$F$5:$F$6),"")) -> 6 | R75: =N75*Q75 -> 12 | S75: =P75+R75 -> 64.189755 | T75: =IF(K75="","SIN ID MÓDULO",IF(E75="HERRAJE",IF(OR(O75="",O75<=0),"SIN PRECIO HERRAJE","OK"),IF(OR(O75="",O75<=0),"SIN PRECIO MATERIAL",IF(AND(N75>0,OR(Q75="",Q75<=0)),"SIN PRECIO CINTILLA","OK")))) -> OK | U75: =IF(T75="OK","",IF(T75="SIN PRECIO HERRAJE","Capturar precio: "&D75,IF(T75="SIN PRECIO MATERIAL","Configurar material: "&E75,IF(T75="SIN PRECIO CINTILLA","Configurar cintilla: "&E75,IF(T75="SIN ID MÓDULO","Revisar ID del módulo",""))))) | V75: =IF(T75="OK",0,IF(T75="",0,1)) -> 0
A76: 1 | B76: 669 | C76: 649 | D76: Respaldo Alacena | E76: ARAUCO BLANCO | F76: 0 | G76: 0 | H76: 0 | I76: 0 | J76: 0 | K76: ALA-2PU-706832 | L76: RES-ALA-6880 | M76: =IF(AND(ISNUMBER(B76),ISNUMBER(C76),B76>0,C76>0),A76*(B76*C76/1000000),0) -> 0.434181 | N76: =IF(AND(ISNUMBER(B76),B76>0),A76*(((G76+H76)*B76+(I76+J76)*C76)/1000),0) -> 0 | O76: =IF(E76="HERRAJE",IFERROR(_xlfn.XLOOKUP(D76,'⚙️ Configuración Costos'!$A$11:$A$20,'⚙️ Configuración Costos'!$B$11:$B$20),""),IFERROR(_xlfn.XLOOKUP(E76,'⚙️ Configuración Costos'!$A$5:$A$6,'⚙️ Configuración Costos'!$B$5:$B$6),"")) -> 239.84262 | P76: =IF(E76="HERRAJE",A76*O76,M76*O76) -> 104.13511 | Q76: =IF(E76="HERRAJE",0,IFERROR(_xlfn.XLOOKUP(E76,'⚙️ Configuración Costos'!$E$5:$E$6,'⚙️ Configuración Costos'!$F$5:$F$6),"")) -> 6 | R76: =N76*Q76 -> 0 | S76: =P76+R76 -> 104.13511 | T76: =IF(K76="","SIN ID MÓDULO",IF(E76="HERRAJE",IF(OR(O76="",O76<=0),"SIN PRECIO HERRAJE","OK"),IF(OR(O76="",O76<=0),"SIN PRECIO MATERIAL",IF(AND(N76>0,OR(Q76="",Q76<=0)),"SIN PRECIO CINTILLA","OK")))) -> OK | U76: =IF(T76="OK","",IF(T76="SIN PRECIO HERRAJE","Capturar precio: "&D76,IF(T76="SIN PRECIO MATERIAL","Configurar material: "&E76,IF(T76="SIN PRECIO CINTILLA","Configurar cintilla: "&E76,IF(T76="SIN ID MÓDULO","Revisar ID del módulo",""))))) | V76: =IF(T76="OK",0,IF(T76="",0,1)) -> 0
A77: 1 | B77: 669 | C77: 320 | D77: Base Alacena | E77: ARAUCO BLANCO | F77: 0 | G77: 1 | H77: 1 | I77: 0 | J77: 0 | K77: ALA-2PU-706832 | L77: BAS-ALA-8032 | M77: =IF(AND(ISNUMBER(B77),ISNUMBER(C77),B77>0,C77>0),A77*(B77*C77/1000000),0) -> 0.21408 | N77: =IF(AND(ISNUMBER(B77),B77>0),A77*(((G77+H77)*B77+(I77+J77)*C77)/1000),0) -> 1.338 | O77: =IF(E77="HERRAJE",IFERROR(_xlfn.XLOOKUP(D77,'⚙️ Configuración Costos'!$A$11:$A$20,'⚙️ Configuración Costos'!$B$11:$B$20),""),IFERROR(_xlfn.XLOOKUP(E77,'⚙️ Configuración Costos'!$A$5:$A$6,'⚙️ Configuración Costos'!$B$5:$B$6),"")) -> 239.84262 | P77: =IF(E77="HERRAJE",A77*O77,M77*O77) -> 51.345509 | Q77: =IF(E77="HERRAJE",0,IFERROR(_xlfn.XLOOKUP(E77,'⚙️ Configuración Costos'!$E$5:$E$6,'⚙️ Configuración Costos'!$F$5:$F$6),"")) -> 6 | R77: =N77*Q77 -> 8.028 | S77: =P77+R77 -> 59.373509 | T77: =IF(K77="","SIN ID MÓDULO",IF(E77="HERRAJE",IF(OR(O77="",O77<=0),"SIN PRECIO HERRAJE","OK"),IF(OR(O77="",O77<=0),"SIN PRECIO MATERIAL",IF(AND(N77>0,OR(Q77="",Q77<=0)),"SIN PRECIO CINTILLA","OK")))) -> OK | U77: =IF(T77="OK","",IF(T77="SIN PRECIO HERRAJE","Capturar precio: "&D77,IF(T77="SIN PRECIO MATERIAL","Configurar material: "&E77,IF(T77="SIN PRECIO CINTILLA","Configurar cintilla: "&E77,IF(T77="SIN ID MÓDULO","Revisar ID del módulo",""))))) | V77: =IF(T77="OK",0,IF(T77="",0,1)) -> 0
A78: 1 | B78: 669 | C78: 320 | D78: Techo Alacena | E78: ARAUCO BLANCO | F78: 0 | G78: 1 | H78: 1 | I78: 0 | J78: 0 | K78: ALA-2PU-706832 | L78: TEC-ALA-8032 | M78: =IF(AND(ISNUMBER(B78),ISNUMBER(C78),B78>0,C78>0),A78*(B78*C78/1000000),0) -> 0.21408 | N78: =IF(AND(ISNUMBER(B78),B78>0),A78*(((G78+H78)*B78+(I78+J78)*C78)/1000),0) -> 1.338 | O78: =IF(E78="HERRAJE",IFERROR(_xlfn.XLOOKUP(D78,'⚙️ Configuración Costos'!$A$11:$A$20,'⚙️ Configuración Costos'!$B$11:$B$20),""),IFERROR(_xlfn.XLOOKUP(E78,'⚙️ Configuración Costos'!$A$5:$A$6,'⚙️ Configuración Costos'!$B$5:$B$6),"")) -> 239.84262 | P78: =IF(E78="HERRAJE",A78*O78,M78*O78) -> 51.345509 | Q78: =IF(E78="HERRAJE",0,IFERROR(_xlfn.XLOOKUP(E78,'⚙️ Configuración Costos'!$E$5:$E$6,'⚙️ Configuración Costos'!$F$5:$F$6),"")) -> 6 | R78: =N78*Q78 -> 8.028 | S78: =P78+R78 -> 59.373509 | T78: =IF(K78="","SIN ID MÓDULO",IF(E78="HERRAJE",IF(OR(O78="",O78<=0),"SIN PRECIO HERRAJE","OK"),IF(OR(O78="",O78<=0),"SIN PRECIO MATERIAL",IF(AND(N78>0,OR(Q78="",Q78<=0)),"SIN PRECIO CINTILLA","OK")))) -> OK | U78: =IF(T78="OK","",IF(T78="SIN PRECIO HERRAJE","Capturar precio: "&D78,IF(T78="SIN PRECIO MATERIAL","Configurar material: "&E78,IF(T78="SIN PRECIO CINTILLA","Configurar cintilla: "&E78,IF(T78="SIN ID MÓDULO","Revisar ID del módulo",""))))) | V78: =IF(T78="OK",0,IF(T78="",0,1)) -> 0
A79: 1 | B79: 669 | C79: 256 | D79: Entrepano Alacena | E79: ARAUCO BLANCO | F79: 0 | G79: 1 | H79: 1 | I79: 0 | J79: 0 | K79: ALA-2PU-706832 | L79: ENT-ALA-8026 | M79: =IF(AND(ISNUMBER(B79),ISNUMBER(C79),B79>0,C79>0),A79*(B79*C79/1000000),0) -> 0.171264 | N79: =IF(AND(ISNUMBER(B79),B79>0),A79*(((G79+H79)*B79+(I79+J79)*C79)/1000),0) -> 1.338 | O79: =IF(E79="HERRAJE",IFERROR(_xlfn.XLOOKUP(D79,'⚙️ Configuración Costos'!$A$11:$A$20,'⚙️ Configuración Costos'!$B$11:$B$20),""),IFERROR(_xlfn.XLOOKUP(E79,'⚙️ Configuración Costos'!$A$5:$A$6,'⚙️ Configuración Costos'!$B$5:$B$6),"")) -> 239.84262 | P79: =IF(E79="HERRAJE",A79*O79,M79*O79) -> 41.076407 | Q79: =IF(E79="HERRAJE",0,IFERROR(_xlfn.XLOOKUP(E79,'⚙️ Configuración Costos'!$E$5:$E$6,'⚙️ Configuración Costos'!$F$5:$F$6),"")) -> 6 | R79: =N79*Q79 -> 8.028 | S79: =P79+R79 -> 49.104407 | T79: =IF(K79="","SIN ID MÓDULO",IF(E79="HERRAJE",IF(OR(O79="",O79<=0),"SIN PRECIO HERRAJE","OK"),IF(OR(O79="",O79<=0),"SIN PRECIO MATERIAL",IF(AND(N79>0,OR(Q79="",Q79<=0)),"SIN PRECIO CINTILLA","OK")))) -> OK | U79: =IF(T79="OK","",IF(T79="SIN PRECIO HERRAJE","Capturar precio: "&D79,IF(T79="SIN PRECIO MATERIAL","Configurar material: "&E79,IF(T79="SIN PRECIO CINTILLA","Configurar cintilla: "&E79,IF(T79="SIN ID MÓDULO","Revisar ID del módulo",""))))) | V79: =IF(T79="OK",0,IF(T79="",0,1)) -> 0
A80: 1 | B80: 677 | C80: 347 | D80: Puerta Der Alacena | E80: VESTO NOUGAT | F80: 1 | G80: 1 | H80: 1 | I80: 1 | J80: 1 | K80: ALA-2PU-706832 | L80: PUE-DER-ALA-6840 | M80: =IF(AND(ISNUMBER(B80),ISNUMBER(C80),B80>0,C80>0),A80*(B80*C80/1000000),0) -> 0.234919 | N80: =IF(AND(ISNUMBER(B80),B80>0),A80*(((G80+H80)*B80+(I80+J80)*C80)/1000),0) -> 2.048 | O80: =IF(E80="HERRAJE",IFERROR(_xlfn.XLOOKUP(D80,'⚙️ Configuración Costos'!$A$11:$A$20,'⚙️ Configuración Costos'!$B$11:$B$20),""),IFERROR(_xlfn.XLOOKUP(E80,'⚙️ Configuración Costos'!$A$5:$A$6,'⚙️ Configuración Costos'!$B$5:$B$6),"")) -> 332.85246 | P80: =IF(E80="HERRAJE",A80*O80,M80*O80) -> 78.193367 | Q80: =IF(E80="HERRAJE",0,IFERROR(_xlfn.XLOOKUP(E80,'⚙️ Configuración Costos'!$E$5:$E$6,'⚙️ Configuración Costos'!$F$5:$F$6),"")) -> 9.5 | R80: =N80*Q80 -> 19.456 | S80: =P80+R80 -> 97.649367 | T80: =IF(K80="","SIN ID MÓDULO",IF(E80="HERRAJE",IF(OR(O80="",O80<=0),"SIN PRECIO HERRAJE","OK"),IF(OR(O80="",O80<=0),"SIN PRECIO MATERIAL",IF(AND(N80>0,OR(Q80="",Q80<=0)),"SIN PRECIO CINTILLA","OK")))) -> OK | U80: =IF(T80="OK","",IF(T80="SIN PRECIO HERRAJE","Capturar precio: "&D80,IF(T80="SIN PRECIO MATERIAL","Configurar material: "&E80,IF(T80="SIN PRECIO CINTILLA","Configurar cintilla: "&E80,IF(T80="SIN ID MÓDULO","Revisar ID del módulo",""))))) | V80: =IF(T80="OK",0,IF(T80="",0,1)) -> 0
A81: 1 | B81: 677 | C81: 347 | D81: Puerta Izq Alacena | E81: VESTO NOUGAT | F81: 1 | G81: 1 | H81: 1 | I81: 1 | J81: 1 | K81: ALA-2PU-706832 | L81: PUE-IZQ-ALA-6840 | M81: =IF(AND(ISNUMBER(B81),ISNUMBER(C81),B81>0,C81>0),A81*(B81*C81/1000000),0) -> 0.234919 | N81: =IF(AND(ISNUMBER(B81),B81>0),A81*(((G81+H81)*B81+(I81+J81)*C81)/1000),0) -> 2.048 | O81: =IF(E81="HERRAJE",IFERROR(_xlfn.XLOOKUP(D81,'⚙️ Configuración Costos'!$A$11:$A$20,'⚙️ Configuración Costos'!$B$11:$B$20),""),IFERROR(_xlfn.XLOOKUP(E81,'⚙️ Configuración Costos'!$A$5:$A$6,'⚙️ Configuración Costos'!$B$5:$B$6),"")) -> 332.85246 | P81: =IF(E81="HERRAJE",A81*O81,M81*O81) -> 78.193367 | Q81: =IF(E81="HERRAJE",0,IFERROR(_xlfn.XLOOKUP(E81,'⚙️ Configuración Costos'!$E$5:$E$6,'⚙️ Configuración Costos'!$F$5:$F$6),"")) -> 9.5 | R81: =N81*Q81 -> 19.456 | S81: =P81+R81 -> 97.649367 | T81: =IF(K81="","SIN ID MÓDULO",IF(E81="HERRAJE",IF(OR(O81="",O81<=0),"SIN PRECIO HERRAJE","OK"),IF(OR(O81="",O81<=0),"SIN PRECIO MATERIAL",IF(AND(N81>0,OR(Q81="",Q81<=0)),"SIN PRECIO CINTILLA","OK")))) -> OK | U81: =IF(T81="OK","",IF(T81="SIN PRECIO HERRAJE","Capturar precio: "&D81,IF(T81="SIN PRECIO MATERIAL","Configurar material: "&E81,IF(T81="SIN PRECIO CINTILLA","Configurar cintilla: "&E81,IF(T81="SIN ID MÓDULO","Revisar ID del módulo",""))))) | V81: =IF(T81="OK",0,IF(T81="",0,1)) -> 0
A82: 4 | B82: 0 | C82: 0 | D82: Bisagra Cierre Lento | E82: HERRAJE | F82: 0 | G82: 0 | H82: 0 | I82: 0 | J82: 0 | K82: ALA-2PU-706832 | L82: BIS-CL | M82: =IF(AND(ISNUMBER(B82),ISNUMBER(C82),B82>0,C82>0),A82*(B82*C82/1000000),0) -> 0 | N82: =IF(AND(ISNUMBER(B82),B82>0),A82*(((G82+H82)*B82+(I82+J82)*C82)/1000),0) -> 0 | O82: =IF(E82="HERRAJE",IFERROR(_xlfn.XLOOKUP(D82,'⚙️ Configuración Costos'!$A$11:$A$20,'⚙️ Configuración Costos'!$B$11:$B$20),""),IFERROR(_xlfn.XLOOKUP(E82,'⚙️ Configuración Costos'!$A$5:$A$6,'⚙️ Configuración Costos'!$B$5:$B$6),"")) -> 20 | P82: =IF(E82="HERRAJE",A82*O82,M82*O82) -> 80 | Q82: =IF(E82="HERRAJE",0,IFERROR(_xlfn.XLOOKUP(E82,'⚙️ Configuración Costos'!$E$5:$E$6,'⚙️ Configuración Costos'!$F$5:$F$6),"")) -> 0 | R82: =N82*Q82 -> 0 | S82: =P82+R82 -> 80 | T82: =IF(K82="","SIN ID MÓDULO",IF(E82="HERRAJE",IF(OR(O82="",O82<=0),"SIN PRECIO HERRAJE","OK"),IF(OR(O82="",O82<=0),"SIN PRECIO MATERIAL",IF(AND(N82>0,OR(Q82="",Q82<=0)),"SIN PRECIO CINTILLA","OK")))) -> OK | U82: =IF(T82="OK","",IF(T82="SIN PRECIO HERRAJE","Capturar precio: "&D82,IF(T82="SIN PRECIO MATERIAL","Configurar material: "&E82,IF(T82="SIN PRECIO CINTILLA","Configurar cintilla: "&E82,IF(T82="SIN ID MÓDULO","Revisar ID del módulo",""))))) | V82: =IF(T82="OK",0,IF(T82="",0,1)) -> 0
A83: 2 | B83: 0 | C83: 0 | D83: Jaladera Acero Inox | E83: HERRAJE | F83: 0 | G83: 0 | H83: 0 | I83: 0 | J83: 0 | K83: ALA-2PU-706832 | L83: JAL-INOX | M83: =IF(AND(ISNUMBER(B83),ISNUMBER(C83),B83>0,C83>0),A83*(B83*C83/1000000),0) -> 0 | N83: =IF(AND(ISNUMBER(B83),B83>0),A83*(((G83+H83)*B83+(I83+J83)*C83)/1000),0) -> 0 | O83: =IF(E83="HERRAJE",IFERROR(_xlfn.XLOOKUP(D83,'⚙️ Configuración Costos'!$A$11:$A$20,'⚙️ Configuración Costos'!$B$11:$B$20),""),IFERROR(_xlfn.XLOOKUP(E83,'⚙️ Configuración Costos'!$A$5:$A$6,'⚙️ Configuración Costos'!$B$5:$B$6),"")) -> 15 | P83: =IF(E83="HERRAJE",A83*O83,M83*O83) -> 30 | Q83: =IF(E83="HERRAJE",0,IFERROR(_xlfn.XLOOKUP(E83,'⚙️ Configuración Costos'!$E$5:$E$6,'⚙️ Configuración Costos'!$F$5:$F$6),"")) -> 0 | R83: =N83*Q83 -> 0 | S83: =P83+R83 -> 30 | T83: =IF(K83="","SIN ID MÓDULO",IF(E83="HERRAJE",IF(OR(O83="",O83<=0),"SIN PRECIO HERRAJE","OK"),IF(OR(O83="",O83<=0),"SIN PRECIO MATERIAL",IF(AND(N83>0,OR(Q83="",Q83<=0)),"SIN PRECIO CINTILLA","OK")))) -> OK | U83: =IF(T83="OK","",IF(T83="SIN PRECIO HERRAJE","Capturar precio: "&D83,IF(T83="SIN PRECIO MATERIAL","Configurar material: "&E83,IF(T83="SIN PRECIO CINTILLA","Configurar cintilla: "&E83,IF(T83="SIN ID MÓDULO","Revisar ID del módulo",""))))) | V83: =IF(T83="OK",0,IF(T83="",0,1)) -> 0
A84: 4 | B84: 0 | C84: 0 | D84: Soporte de Entrepaño | E84: HERRAJE | F84: 0 | G84: 0 | H84: 0 | I84: 0 | J84: 0 | K84: ALA-2PU-706832 | L84: SOP-ENT | M84: =IF(AND(ISNUMBER(B84),ISNUMBER(C84),B84>0,C84>0),A84*(B84*C84/1000000),0) -> 0 | N84: =IF(AND(ISNUMBER(B84),B84>0),A84*(((G84+H84)*B84+(I84+J84)*C84)/1000),0) -> 0 | O84: =IF(E84="HERRAJE",IFERROR(_xlfn.XLOOKUP(D84,'⚙️ Configuración Costos'!$A$11:$A$20,'⚙️ Configuración Costos'!$B$11:$B$20),""),IFERROR(_xlfn.XLOOKUP(E84,'⚙️ Configuración Costos'!$A$5:$A$6,'⚙️ Configuración Costos'!$B$5:$B$6),"")) -> 2 | P84: =IF(E84="HERRAJE",A84*O84,M84*O84) -> 8 | Q84: =IF(E84="HERRAJE",0,IFERROR(_xlfn.XLOOKUP(E84,'⚙️ Configuración Costos'!$E$5:$E$6,'⚙️ Configuración Costos'!$F$5:$F$6),"")) -> 0 | R84: =N84*Q84 -> 0 | S84: =P84+R84 -> 8 | T84: =IF(K84="","SIN ID MÓDULO",IF(E84="HERRAJE",IF(OR(O84="",O84<=0),"SIN PRECIO HERRAJE","OK"),IF(OR(O84="",O84<=0),"SIN PRECIO MATERIAL",IF(AND(N84>0,OR(Q84="",Q84<=0)),"SIN PRECIO CINTILLA","OK")))) -> OK | U84: =IF(T84="OK","",IF(T84="SIN PRECIO HERRAJE","Capturar precio: "&D84,IF(T84="SIN PRECIO MATERIAL","Configurar material: "&E84,IF(T84="SIN PRECIO CINTILLA","Configurar cintilla: "&E84,IF(T84="SIN ID MÓDULO","Revisar ID del módulo",""))))) | V84: =IF(T84="OK",0,IF(T84="",0,1)) -> 0
A85: 40 | B85: 0 | C85: 0 | D85: Tornillo 4x50 mm | E85: HERRAJE | F85: 0 | G85: 0 | H85: 0 | I85: 0 | J85: 0 | K85: ALA-2PU-706832 | L85: TOR-4X50 | M85: =IF(AND(ISNUMBER(B85),ISNUMBER(C85),B85>0,C85>0),A85*(B85*C85/1000000),0) -> 0 | N85: =IF(AND(ISNUMBER(B85),B85>0),A85*(((G85+H85)*B85+(I85+J85)*C85)/1000),0) -> 0 | O85: =IF(E85="HERRAJE",IFERROR(_xlfn.XLOOKUP(D85,'⚙️ Configuración Costos'!$A$11:$A$20,'⚙️ Configuración Costos'!$B$11:$B$20),""),IFERROR(_xlfn.XLOOKUP(E85,'⚙️ Configuración Costos'!$A$5:$A$6,'⚙️ Configuración Costos'!$B$5:$B$6),"")) -> 1.5 | P85: =IF(E85="HERRAJE",A85*O85,M85*O85) -> 60 | Q85: =IF(E85="HERRAJE",0,IFERROR(_xlfn.XLOOKUP(E85,'⚙️ Configuración Costos'!$E$5:$E$6,'⚙️ Configuración Costos'!$F$5:$F$6),"")) -> 0 | R85: =N85*Q85 -> 0 | S85: =P85+R85 -> 60 | T85: =IF(K85="","SIN ID MÓDULO",IF(E85="HERRAJE",IF(OR(O85="",O85<=0),"SIN PRECIO HERRAJE","OK"),IF(OR(O85="",O85<=0),"SIN PRECIO MATERIAL",IF(AND(N85>0,OR(Q85="",Q85<=0)),"SIN PRECIO CINTILLA","OK")))) -> OK | U85: =IF(T85="OK","",IF(T85="SIN PRECIO HERRAJE","Capturar precio: "&D85,IF(T85="SIN PRECIO MATERIAL","Configurar material: "&E85,IF(T85="SIN PRECIO CINTILLA","Configurar cintilla: "&E85,IF(T85="SIN ID MÓDULO","Revisar ID del módulo",""))))) | V85: =IF(T85="OK",0,IF(T85="",0,1)) -> 0
A86: TOTALES | M86: =SUM(M74:M85) -> 1.938643 | N86: =SUM(N74:N85) -> 12.11 | P86: =SUM(P74:P85) -> 686.66878 | R86: =SUM(R74:R85) -> 86.996 | S86: =SUM(S74:S85) -> 773.66478
A87: Alacena 2 Puertas 800 x 680 x 320 mm
A88: 1 | B88: 680 | C88: 320 | D88: Lateral Derecho | E88: ARAUCO BLANCO | F88: 0 | G88: 1 | H88: 1 | I88: 1 | J88: 1 | K88: ALA-2PU-806832 | L88: LAT-ALA-6832-D | M88: =IF(AND(ISNUMBER(B88),ISNUMBER(C88),B88>0,C88>0),A88*(B88*C88/1000000),0) -> 0.2176 | N88: =IF(AND(ISNUMBER(B88),B88>0),A88*(((G88+H88)*B88+(I88+J88)*C88)/1000),0) -> 2 | O88: =IF(E88="HERRAJE",IFERROR(_xlfn.XLOOKUP(D88,'⚙️ Configuración Costos'!$A$11:$A$20,'⚙️ Configuración Costos'!$B$11:$B$20),""),IFERROR(_xlfn.XLOOKUP(E88,'⚙️ Configuración Costos'!$A$5:$A$6,'⚙️ Configuración Costos'!$B$5:$B$6),"")) -> 239.84262 | P88: =IF(E88="HERRAJE",A88*O88,M88*O88) -> 52.189755 | Q88: =IF(E88="HERRAJE",0,IFERROR(_xlfn.XLOOKUP(E88,'⚙️ Configuración Costos'!$E$5:$E$6,'⚙️ Configuración Costos'!$F$5:$F$6),"")) -> 6 | R88: =N88*Q88 -> 12 | S88: =P88+R88 -> 64.189755 | T88: =IF(K88="","SIN ID MÓDULO",IF(E88="HERRAJE",IF(OR(O88="",O88<=0),"SIN PRECIO HERRAJE","OK"),IF(OR(O88="",O88<=0),"SIN PRECIO MATERIAL",IF(AND(N88>0,OR(Q88="",Q88<=0)),"SIN PRECIO CINTILLA","OK")))) -> OK | U88: =IF(T88="OK","",IF(T88="SIN PRECIO HERRAJE","Capturar precio: "&D88,IF(T88="SIN PRECIO MATERIAL","Configurar material: "&E88,IF(T88="SIN PRECIO CINTILLA","Configurar cintilla: "&E88,IF(T88="SIN ID MÓDULO","Revisar ID del módulo",""))))) | V88: =IF(T88="OK",0,IF(T88="",0,1)) -> 0
A89: 1 | B89: 680 | C89: 320 | D89: Lateral Izquierdo | E89: ARAUCO BLANCO | F89: 0 | G89: 1 | H89: 1 | I89: 1 | J89: 1 | K89: ALA-2PU-806832 | L89: LAT-ALA-6832-I | M89: =IF(AND(ISNUMBER(B89),ISNUMBER(C89),B89>0,C89>0),A89*(B89*C89/1000000),0) -> 0.2176 | N89: =IF(AND(ISNUMBER(B89),B89>0),A89*(((G89+H89)*B89+(I89+J89)*C89)/1000),0) -> 2 | O89: =IF(E89="HERRAJE",IFERROR(_xlfn.XLOOKUP(D89,'⚙️ Configuración Costos'!$A$11:$A$20,'⚙️ Configuración Costos'!$B$11:$B$20),""),IFERROR(_xlfn.XLOOKUP(E89,'⚙️ Configuración Costos'!$A$5:$A$6,'⚙️ Configuración Costos'!$B$5:$B$6),"")) -> 239.84262 | P89: =IF(E89="HERRAJE",A89*O89,M89*O89) -> 52.189755 | Q89: =IF(E89="HERRAJE",0,IFERROR(_xlfn.XLOOKUP(E89,'⚙️ Configuración Costos'!$E$5:$E$6,'⚙️ Configuración Costos'!$F$5:$F$6),"")) -> 6 | R89: =N89*Q89 -> 12 | S89: =P89+R89 -> 64.189755 | T89: =IF(K89="","SIN ID MÓDULO",IF(E89="HERRAJE",IF(OR(O89="",O89<=0),"SIN PRECIO HERRAJE","OK"),IF(OR(O89="",O89<=0),"SIN PRECIO MATERIAL",IF(AND(N89>0,OR(Q89="",Q89<=0)),"SIN PRECIO CINTILLA","OK")))) -> OK | U89: =IF(T89="OK","",IF(T89="SIN PRECIO HERRAJE","Capturar precio: "&D89,IF(T89="SIN PRECIO MATERIAL","Configurar material: "&E89,IF(T89="SIN PRECIO CINTILLA","Configurar cintilla: "&E89,IF(T89="SIN ID MÓDULO","Revisar ID del módulo",""))))) | V89: =IF(T89="OK",0,IF(T89="",0,1)) -> 0
A90: 1 | B90: 769 | C90: 649 | D90: Respaldo Alacena | E90: ARAUCO BLANCO | F90: 0 | G90: 0 | H90: 0 | I90: 0 | J90: 0 | K90: ALA-2PU-806832 | L90: RES-ALA-6880 | M90: =IF(AND(ISNUMBER(B90),ISNUMBER(C90),B90>0,C90>0),A90*(B90*C90/1000000),0) -> 0.499081 | N90: =IF(AND(ISNUMBER(B90),B90>0),A90*(((G90+H90)*B90+(I90+J90)*C90)/1000),0) -> 0 | O90: =IF(E90="HERRAJE",IFERROR(_xlfn.XLOOKUP(D90,'⚙️ Configuración Costos'!$A$11:$A$20,'⚙️ Configuración Costos'!$B$11:$B$20),""),IFERROR(_xlfn.XLOOKUP(E90,'⚙️ Configuración Costos'!$A$5:$A$6,'⚙️ Configuración Costos'!$B$5:$B$6),"")) -> 239.84262 | P90: =IF(E90="HERRAJE",A90*O90,M90*O90) -> 119.7009 | Q90: =IF(E90="HERRAJE",0,IFERROR(_xlfn.XLOOKUP(E90,'⚙️ Configuración Costos'!$E$5:$E$6,'⚙️ Configuración Costos'!$F$5:$F$6),"")) -> 6 | R90: =N90*Q90 -> 0 | S90: =P90+R90 -> 119.7009 | T90: =IF(K90="","SIN ID MÓDULO",IF(E90="HERRAJE",IF(OR(O90="",O90<=0),"SIN PRECIO HERRAJE","OK"),IF(OR(O90="",O90<=0),"SIN PRECIO MATERIAL",IF(AND(N90>0,OR(Q90="",Q90<=0)),"SIN PRECIO CINTILLA","OK")))) -> OK | U90: =IF(T90="OK","",IF(T90="SIN PRECIO HERRAJE","Capturar precio: "&D90,IF(T90="SIN PRECIO MATERIAL","Configurar material: "&E90,IF(T90="SIN PRECIO CINTILLA","Configurar cintilla: "&E90,IF(T90="SIN ID MÓDULO","Revisar ID del módulo",""))))) | V90: =IF(T90="OK",0,IF(T90="",0,1)) -> 0
A91: 1 | B91: 769 | C91: 320 | D91: Base Alacena | E91: ARAUCO BLANCO | F91: 0 | G91: 1 | H91: 1 | I91: 0 | J91: 0 | K91: ALA-2PU-806832 | L91: BAS-ALA-8032 | M91: =IF(AND(ISNUMBER(B91),ISNUMBER(C91),B91>0,C91>0),A91*(B91*C91/1000000),0) -> 0.24608 | N91: =IF(AND(ISNUMBER(B91),B91>0),A91*(((G91+H91)*B91+(I91+J91)*C91)/1000),0) -> 1.538 | O91: =IF(E91="HERRAJE",IFERROR(_xlfn.XLOOKUP(D91,'⚙️ Configuración Costos'!$A$11:$A$20,'⚙️ Configuración Costos'!$B$11:$B$20),""),IFERROR(_xlfn.XLOOKUP(E91,'⚙️ Configuración Costos'!$A$5:$A$6,'⚙️ Configuración Costos'!$B$5:$B$6),"")) -> 239.84262 | P91: =IF(E91="HERRAJE",A91*O91,M91*O91) -> 59.020473 | Q91: =IF(E91="HERRAJE",0,IFERROR(_xlfn.XLOOKUP(E91,'⚙️ Configuración Costos'!$E$5:$E$6,'⚙️ Configuración Costos'!$F$5:$F$6),"")) -> 6 | R91: =N91*Q91 -> 9.228 | S91: =P91+R91 -> 68.248473 | T91: =IF(K91="","SIN ID MÓDULO",IF(E91="HERRAJE",IF(OR(O91="",O91<=0),"SIN PRECIO HERRAJE","OK"),IF(OR(O91="",O91<=0),"SIN PRECIO MATERIAL",IF(AND(N91>0,OR(Q91="",Q91<=0)),"SIN PRECIO CINTILLA","OK")))) -> OK | U91: =IF(T91="OK","",IF(T91="SIN PRECIO HERRAJE","Capturar precio: "&D91,IF(T91="SIN PRECIO MATERIAL","Configurar material: "&E91,IF(T91="SIN PRECIO CINTILLA","Configurar cintilla: "&E91,IF(T91="SIN ID MÓDULO","Revisar ID del módulo",""))))) | V91: =IF(T91="OK",0,IF(T91="",0,1)) -> 0
A92: 1 | B92: 769 | C92: 320 | D92: Techo Alacena | E92: ARAUCO BLANCO | F92: 0 | G92: 1 | H92: 1 | I92: 0 | J92: 0 | K92: ALA-2PU-806832 | L92: TEC-ALA-8032 | M92: =IF(AND(ISNUMBER(B92),ISNUMBER(C92),B92>0,C92>0),A92*(B92*C92/1000000),0) -> 0.24608 | N92: =IF(AND(ISNUMBER(B92),B92>0),A92*(((G92+H92)*B92+(I92+J92)*C92)/1000),0) -> 1.538 | O92: =IF(E92="HERRAJE",IFERROR(_xlfn.XLOOKUP(D92,'⚙️ Configuración Costos'!$A$11:$A$20,'⚙️ Configuración Costos'!$B$11:$B$20),""),IFERROR(_xlfn.XLOOKUP(E92,'⚙️ Configuración Costos'!$A$5:$A$6,'⚙️ Configuración Costos'!$B$5:$B$6),"")) -> 239.84262 | P92: =IF(E92="HERRAJE",A92*O92,M92*O92) -> 59.020473 | Q92: =IF(E92="HERRAJE",0,IFERROR(_xlfn.XLOOKUP(E92,'⚙️ Configuración Costos'!$E$5:$E$6,'⚙️ Configuración Costos'!$F$5:$F$6),"")) -> 6 | R92: =N92*Q92 -> 9.228 | S92: =P92+R92 -> 68.248473 | T92: =IF(K92="","SIN ID MÓDULO",IF(E92="HERRAJE",IF(OR(O92="",O92<=0),"SIN PRECIO HERRAJE","OK"),IF(OR(O92="",O92<=0),"SIN PRECIO MATERIAL",IF(AND(N92>0,OR(Q92="",Q92<=0)),"SIN PRECIO CINTILLA","OK")))) -> OK | U92: =IF(T92="OK","",IF(T92="SIN PRECIO HERRAJE","Capturar precio: "&D92,IF(T92="SIN PRECIO MATERIAL","Configurar material: "&E92,IF(T92="SIN PRECIO CINTILLA","Configurar cintilla: "&E92,IF(T92="SIN ID MÓDULO","Revisar ID del módulo",""))))) | V92: =IF(T92="OK",0,IF(T92="",0,1)) -> 0
A93: 1 | B93: 769 | C93: 256 | D93: Entrepano Alacena | E93: ARAUCO BLANCO | F93: 0 | G93: 1 | H93: 1 | I93: 0 | J93: 0 | K93: ALA-2PU-806832 | L93: ENT-ALA-8026 | M93: =IF(AND(ISNUMBER(B93),ISNUMBER(C93),B93>0,C93>0),A93*(B93*C93/1000000),0) -> 0.196864 | N93: =IF(AND(ISNUMBER(B93),B93>0),A93*(((G93+H93)*B93+(I93+J93)*C93)/1000),0) -> 1.538 | O93: =IF(E93="HERRAJE",IFERROR(_xlfn.XLOOKUP(D93,'⚙️ Configuración Costos'!$A$11:$A$20,'⚙️ Configuración Costos'!$B$11:$B$20),""),IFERROR(_xlfn.XLOOKUP(E93,'⚙️ Configuración Costos'!$A$5:$A$6,'⚙️ Configuración Costos'!$B$5:$B$6),"")) -> 239.84262 | P93: =IF(E93="HERRAJE",A93*O93,M93*O93) -> 47.216378 | Q93: =IF(E93="HERRAJE",0,IFERROR(_xlfn.XLOOKUP(E93,'⚙️ Configuración Costos'!$E$5:$E$6,'⚙️ Configuración Costos'!$F$5:$F$6),"")) -> 6 | R93: =N93*Q93 -> 9.228 | S93: =P93+R93 -> 56.444378 | T93: =IF(K93="","SIN ID MÓDULO",IF(E93="HERRAJE",IF(OR(O93="",O93<=0),"SIN PRECIO HERRAJE","OK"),IF(OR(O93="",O93<=0),"SIN PRECIO MATERIAL",IF(AND(N93>0,OR(Q93="",Q93<=0)),"SIN PRECIO CINTILLA","OK")))) -> OK | U93: =IF(T93="OK","",IF(T93="SIN PRECIO HERRAJE","Capturar precio: "&D93,IF(T93="SIN PRECIO MATERIAL","Configurar material: "&E93,IF(T93="SIN PRECIO CINTILLA","Configurar cintilla: "&E93,IF(T93="SIN ID MÓDULO","Revisar ID del módulo",""))))) | V93: =IF(T93="OK",0,IF(T93="",0,1)) -> 0
A94: 1 | B94: 677 | C94: 397 | D94: Puerta Der Alacena | E94: VESTO NOUGAT | F94: 1 | G94: 1 | H94: 1 | I94: 1 | J94: 1 | K94: ALA-2PU-806832 | L94: PUE-DER-ALA-6840 | M94: =IF(AND(ISNUMBER(B94),ISNUMBER(C94),B94>0,C94>0),A94*(B94*C94/1000000),0) -> 0.268769 | N94: =IF(AND(ISNUMBER(B94),B94>0),A94*(((G94+H94)*B94+(I94+J94)*C94)/1000),0) -> 2.148 | O94: =IF(E94="HERRAJE",IFERROR(_xlfn.XLOOKUP(D94,'⚙️ Configuración Costos'!$A$11:$A$20,'⚙️ Configuración Costos'!$B$11:$B$20),""),IFERROR(_xlfn.XLOOKUP(E94,'⚙️ Configuración Costos'!$A$5:$A$6,'⚙️ Configuración Costos'!$B$5:$B$6),"")) -> 332.85246 | P94: =IF(E94="HERRAJE",A94*O94,M94*O94) -> 89.460423 | Q94: =IF(E94="HERRAJE",0,IFERROR(_xlfn.XLOOKUP(E94,'⚙️ Configuración Costos'!$E$5:$E$6,'⚙️ Configuración Costos'!$F$5:$F$6),"")) -> 9.5 | R94: =N94*Q94 -> 20.406 | S94: =P94+R94 -> 109.86642 | T94: =IF(K94="","SIN ID MÓDULO",IF(E94="HERRAJE",IF(OR(O94="",O94<=0),"SIN PRECIO HERRAJE","OK"),IF(OR(O94="",O94<=0),"SIN PRECIO MATERIAL",IF(AND(N94>0,OR(Q94="",Q94<=0)),"SIN PRECIO CINTILLA","OK")))) -> OK | U94: =IF(T94="OK","",IF(T94="SIN PRECIO HERRAJE","Capturar precio: "&D94,IF(T94="SIN PRECIO MATERIAL","Configurar material: "&E94,IF(T94="SIN PRECIO CINTILLA","Configurar cintilla: "&E94,IF(T94="SIN ID MÓDULO","Revisar ID del módulo",""))))) | V94: =IF(T94="OK",0,IF(T94="",0,1)) -> 0
A95: 1 | B95: 677 | C95: 397 | D95: Puerta Izq Alacena | E95: VESTO NOUGAT | F95: 1 | G95: 1 | H95: 1 | I95: 1 | J95: 1 | K95: ALA-2PU-806832 | L95: PUE-IZQ-ALA-6840 | M95: =IF(AND(ISNUMBER(B95),ISNUMBER(C95),B95>0,C95>0),A95*(B95*C95/1000000),0) -> 0.268769 | N95: =IF(AND(ISNUMBER(B95),B95>0),A95*(((G95+H95)*B95+(I95+J95)*C95)/1000),0) -> 2.148 | O95: =IF(E95="HERRAJE",IFERROR(_xlfn.XLOOKUP(D95,'⚙️ Configuración Costos'!$A$11:$A$20,'⚙️ Configuración Costos'!$B$11:$B$20),""),IFERROR(_xlfn.XLOOKUP(E95,'⚙️ Configuración Costos'!$A$5:$A$6,'⚙️ Configuración Costos'!$B$5:$B$6),"")) -> 332.85246 | P95: =IF(E95="HERRAJE",A95*O95,M95*O95) -> 89.460423 | Q95: =IF(E95="HERRAJE",0,IFERROR(_xlfn.XLOOKUP(E95,'⚙️ Configuración Costos'!$E$5:$E$6,'⚙️ Configuración Costos'!$F$5:$F$6),"")) -> 9.5 | R95: =N95*Q95 -> 20.406 | S95: =P95+R95 -> 109.86642 | T95: =IF(K95="","SIN ID MÓDULO",IF(E95="HERRAJE",IF(OR(O95="",O95<=0),"SIN PRECIO HERRAJE","OK"),IF(OR(O95="",O95<=0),"SIN PRECIO MATERIAL",IF(AND(N95>0,OR(Q95="",Q95<=0)),"SIN PRECIO CINTILLA","OK")))) -> OK | U95: =IF(T95="OK","",IF(T95="SIN PRECIO HERRAJE","Capturar precio: "&D95,IF(T95="SIN PRECIO MATERIAL","Configurar material: "&E95,IF(T95="SIN PRECIO CINTILLA","Configurar cintilla: "&E95,IF(T95="SIN ID MÓDULO","Revisar ID del módulo",""))))) | V95: =IF(T95="OK",0,IF(T95="",0,1)) -> 0
A96: 4 | B96: 0 | C96: 0 | D96: Bisagra Cierre Lento | E96: HERRAJE | F96: 0 | G96: 0 | H96: 0 | I96: 0 | J96: 0 | K96: ALA-2PU-806832 | L96: BIS-CL | M96: =IF(AND(ISNUMBER(B96),ISNUMBER(C96),B96>0,C96>0),A96*(B96*C96/1000000),0) -> 0 | N96: =IF(AND(ISNUMBER(B96),B96>0),A96*(((G96+H96)*B96+(I96+J96)*C96)/1000),0) -> 0 | O96: =IF(E96="HERRAJE",IFERROR(_xlfn.XLOOKUP(D96,'⚙️ Configuración Costos'!$A$11:$A$20,'⚙️ Configuración Costos'!$B$11:$B$20),""),IFERROR(_xlfn.XLOOKUP(E96,'⚙️ Configuración Costos'!$A$5:$A$6,'⚙️ Configuración Costos'!$B$5:$B$6),"")) -> 20 | P96: =IF(E96="HERRAJE",A96*O96,M96*O96) -> 80 | Q96: =IF(E96="HERRAJE",0,IFERROR(_xlfn.XLOOKUP(E96,'⚙️ Configuración Costos'!$E$5:$E$6,'⚙️ Configuración Costos'!$F$5:$F$6),"")) -> 0 | R96: =N96*Q96 -> 0 | S96: =P96+R96 -> 80 | T96: =IF(K96="","SIN ID MÓDULO",IF(E96="HERRAJE",IF(OR(O96="",O96<=0),"SIN PRECIO HERRAJE","OK"),IF(OR(O96="",O96<=0),"SIN PRECIO MATERIAL",IF(AND(N96>0,OR(Q96="",Q96<=0)),"SIN PRECIO CINTILLA","OK")))) -> OK | U96: =IF(T96="OK","",IF(T96="SIN PRECIO HERRAJE","Capturar precio: "&D96,IF(T96="SIN PRECIO MATERIAL","Configurar material: "&E96,IF(T96="SIN PRECIO CINTILLA","Configurar cintilla: "&E96,IF(T96="SIN ID MÓDULO","Revisar ID del módulo",""))))) | V96: =IF(T96="OK",0,IF(T96="",0,1)) -> 0
A97: 2 | B97: 0 | C97: 0 | D97: Jaladera Acero Inox | E97: HERRAJE | F97: 0 | G97: 0 | H97: 0 | I97: 0 | J97: 0 | K97: ALA-2PU-806832 | L97: JAL-INOX | M97: =IF(AND(ISNUMBER(B97),ISNUMBER(C97),B97>0,C97>0),A97*(B97*C97/1000000),0) -> 0 | N97: =IF(AND(ISNUMBER(B97),B97>0),A97*(((G97+H97)*B97+(I97+J97)*C97)/1000),0) -> 0 | O97: =IF(E97="HERRAJE",IFERROR(_xlfn.XLOOKUP(D97,'⚙️ Configuración Costos'!$A$11:$A$20,'⚙️ Configuración Costos'!$B$11:$B$20),""),IFERROR(_xlfn.XLOOKUP(E97,'⚙️ Configuración Costos'!$A$5:$A$6,'⚙️ Configuración Costos'!$B$5:$B$6),"")) -> 15 | P97: =IF(E97="HERRAJE",A97*O97,M97*O97) -> 30 | Q97: =IF(E97="HERRAJE",0,IFERROR(_xlfn.XLOOKUP(E97,'⚙️ Configuración Costos'!$E$5:$E$6,'⚙️ Configuración Costos'!$F$5:$F$6),"")) -> 0 | R97: =N97*Q97 -> 0 | S97: =P97+R97 -> 30 | T97: =IF(K97="","SIN ID MÓDULO",IF(E97="HERRAJE",IF(OR(O97="",O97<=0),"SIN PRECIO HERRAJE","OK"),IF(OR(O97="",O97<=0),"SIN PRECIO MATERIAL",IF(AND(N97>0,OR(Q97="",Q97<=0)),"SIN PRECIO CINTILLA","OK")))) -> OK | U97: =IF(T97="OK","",IF(T97="SIN PRECIO HERRAJE","Capturar precio: "&D97,IF(T97="SIN PRECIO MATERIAL","Configurar material: "&E97,IF(T97="SIN PRECIO CINTILLA","Configurar cintilla: "&E97,IF(T97="SIN ID MÓDULO","Revisar ID del módulo",""))))) | V97: =IF(T97="OK",0,IF(T97="",0,1)) -> 0
A98: 4 | B98: 0 | C98: 0 | D98: Soporte de Entrepaño | E98: HERRAJE | F98: 0 | G98: 0 | H98: 0 | I98: 0 | J98: 0 | K98: ALA-2PU-806832 | L98: SOP-ENT | M98: =IF(AND(ISNUMBER(B98),ISNUMBER(C98),B98>0,C98>0),A98*(B98*C98/1000000),0) -> 0 | N98: =IF(AND(ISNUMBER(B98),B98>0),A98*(((G98+H98)*B98+(I98+J98)*C98)/1000),0) -> 0 | O98: =IF(E98="HERRAJE",IFERROR(_xlfn.XLOOKUP(D98,'⚙️ Configuración Costos'!$A$11:$A$20,'⚙️ Configuración Costos'!$B$11:$B$20),""),IFERROR(_xlfn.XLOOKUP(E98,'⚙️ Configuración Costos'!$A$5:$A$6,'⚙️ Configuración Costos'!$B$5:$B$6),"")) -> 2 | P98: =IF(E98="HERRAJE",A98*O98,M98*O98) -> 8 | Q98: =IF(E98="HERRAJE",0,IFERROR(_xlfn.XLOOKUP(E98,'⚙️ Configuración Costos'!$E$5:$E$6,'⚙️ Configuración Costos'!$F$5:$F$6),"")) -> 0 | R98: =N98*Q98 -> 0 | S98: =P98+R98 -> 8 | T98: =IF(K98="","SIN ID MÓDULO",IF(E98="HERRAJE",IF(OR(O98="",O98<=0),"SIN PRECIO HERRAJE","OK"),IF(OR(O98="",O98<=0),"SIN PRECIO MATERIAL",IF(AND(N98>0,OR(Q98="",Q98<=0)),"SIN PRECIO CINTILLA","OK")))) -> OK | U98: =IF(T98="OK","",IF(T98="SIN PRECIO HERRAJE","Capturar precio: "&D98,IF(T98="SIN PRECIO MATERIAL","Configurar material: "&E98,IF(T98="SIN PRECIO CINTILLA","Configurar cintilla: "&E98,IF(T98="SIN ID MÓDULO","Revisar ID del módulo",""))))) | V98: =IF(T98="OK",0,IF(T98="",0,1)) -> 0
A99: 40 | B99: 0 | C99: 0 | D99: Tornillo 4x50 mm | E99: HERRAJE | F99: 0 | G99: 0 | H99: 0 | I99: 0 | J99: 0 | K99: ALA-2PU-806832 | L99: TOR-4X50 | M99: =IF(AND(ISNUMBER(B99),ISNUMBER(C99),B99>0,C99>0),A99*(B99*C99/1000000),0) -> 0 | N99: =IF(AND(ISNUMBER(B99),B99>0),A99*(((G99+H99)*B99+(I99+J99)*C99)/1000),0) -> 0 | O99: =IF(E99="HERRAJE",IFERROR(_xlfn.XLOOKUP(D99,'⚙️ Configuración Costos'!$A$11:$A$20,'⚙️ Configuración Costos'!$B$11:$B$20),""),IFERROR(_xlfn.XLOOKUP(E99,'⚙️ Configuración Costos'!$A$5:$A$6,'⚙️ Configuración Costos'!$B$5:$B$6),"")) -> 1.5 | P99: =IF(E99="HERRAJE",A99*O99,M99*O99) -> 60 | Q99: =IF(E99="HERRAJE",0,IFERROR(_xlfn.XLOOKUP(E99,'⚙️ Configuración Costos'!$E$5:$E$6,'⚙️ Configuración Costos'!$F$5:$F$6),"")) -> 0 | R99: =N99*Q99 -> 0 | S99: =P99+R99 -> 60 | T99: =IF(K99="","SIN ID MÓDULO",IF(E99="HERRAJE",IF(OR(O99="",O99<=0),"SIN PRECIO HERRAJE","OK"),IF(OR(O99="",O99<=0),"SIN PRECIO MATERIAL",IF(AND(N99>0,OR(Q99="",Q99<=0)),"SIN PRECIO CINTILLA","OK")))) -> OK | U99: =IF(T99="OK","",IF(T99="SIN PRECIO HERRAJE","Capturar precio: "&D99,IF(T99="SIN PRECIO MATERIAL","Configurar material: "&E99,IF(T99="SIN PRECIO CINTILLA","Configurar cintilla: "&E99,IF(T99="SIN ID MÓDULO","Revisar ID del módulo",""))))) | V99: =IF(T99="OK",0,IF(T99="",0,1)) -> 0
A100: TOTALES | M100: =SUM(M88:M99) -> 2.160843 | N100: =SUM(N88:N99) -> 12.91 | P100: =SUM(P88:P99) -> 746.25857 | R100: =SUM(R88:R99) -> 92.496 | S100: =SUM(S88:S99) -> 838.75457
A101: Alacena 2 Puertas 900 x 680 x 320 mm
A102: 1 | B102: 680 | C102: 320 | D102: Lateral Derecho | E102: ARAUCO BLANCO | F102: 0 | G102: 1 | H102: 1 | I102: 1 | J102: 1 | K102: ALA-2PU-906832 | L102: LAT-ALA-6832-D | M102: =IF(AND(ISNUMBER(B102),ISNUMBER(C102),B102>0,C102>0),A102*(B102*C102/1000000),0) -> 0.2176 | N102: =IF(AND(ISNUMBER(B102),B102>0),A102*(((G102+H102)*B102+(I102+J102)*C102)/1000),0) -> 2 | O102: =IF(E102="HERRAJE",IFERROR(_xlfn.XLOOKUP(D102,'⚙️ Configuración Costos'!$A$11:$A$20,'⚙️ Configuración Costos'!$B$11:$B$20),""),IFERROR(_xlfn.XLOOKUP(E102,'⚙️ Configuración Costos'!$A$5:$A$6,'⚙️ Configuración Costos'!$B$5:$B$6),"")) -> 239.84262 | P102: =IF(E102="HERRAJE",A102*O102,M102*O102) -> 52.189755 | Q102: =IF(E102="HERRAJE",0,IFERROR(_xlfn.XLOOKUP(E102,'⚙️ Configuración Costos'!$E$5:$E$6,'⚙️ Configuración Costos'!$F$5:$F$6),"")) -> 6 | R102: =N102*Q102 -> 12 | S102: =P102+R102 -> 64.189755 | T102: =IF(K102="","SIN ID MÓDULO",IF(E102="HERRAJE",IF(OR(O102="",O102<=0),"SIN PRECIO HERRAJE","OK"),IF(OR(O102="",O102<=0),"SIN PRECIO MATERIAL",IF(AND(N102>0,OR(Q102="",Q102<=0)),"SIN PRECIO CINTILLA","OK")))) -> OK | U102: =IF(T102="OK","",IF(T102="SIN PRECIO HERRAJE","Capturar precio: "&D102,IF(T102="SIN PRECIO MATERIAL","Configurar material: "&E102,IF(T102="SIN PRECIO CINTILLA","Configurar cintilla: "&E102,IF(T102="SIN ID MÓDULO","Revisar ID del módulo",""))))) | V102: =IF(T102="OK",0,IF(T102="",0,1)) -> 0
A103: 1 | B103: 680 | C103: 320 | D103: Lateral Izquierdo | E103: ARAUCO BLANCO | F103: 0 | G103: 1 | H103: 1 | I103: 1 | J103: 1 | K103: ALA-2PU-906832 | L103: LAT-ALA-6832-I | M103: =IF(AND(ISNUMBER(B103),ISNUMBER(C103),B103>0,C103>0),A103*(B103*C103/1000000),0) -> 0.2176 | N103: =IF(AND(ISNUMBER(B103),B103>0),A103*(((G103+H103)*B103+(I103+J103)*C103)/1000),0) -> 2 | O103: =IF(E103="HERRAJE",IFERROR(_xlfn.XLOOKUP(D103,'⚙️ Configuración Costos'!$A$11:$A$20,'⚙️ Configuración Costos'!$B$11:$B$20),""),IFERROR(_xlfn.XLOOKUP(E103,'⚙️ Configuración Costos'!$A$5:$A$6,'⚙️ Configuración Costos'!$B$5:$B$6),"")) -> 239.84262 | P103: =IF(E103="HERRAJE",A103*O103,M103*O103) -> 52.189755 | Q103: =IF(E103="HERRAJE",0,IFERROR(_xlfn.XLOOKUP(E103,'⚙️ Configuración Costos'!$E$5:$E$6,'⚙️ Configuración Costos'!$F$5:$F$6),"")) -> 6 | R103: =N103*Q103 -> 12 | S103: =P103+R103 -> 64.189755 | T103: =IF(K103="","SIN ID MÓDULO",IF(E103="HERRAJE",IF(OR(O103="",O103<=0),"SIN PRECIO HERRAJE","OK"),IF(OR(O103="",O103<=0),"SIN PRECIO MATERIAL",IF(AND(N103>0,OR(Q103="",Q103<=0)),"SIN PRECIO CINTILLA","OK")))) -> OK | U103: =IF(T103="OK","",IF(T103="SIN PRECIO HERRAJE","Capturar precio: "&D103,IF(T103="SIN PRECIO MATERIAL","Configurar material: "&E103,IF(T103="SIN PRECIO CINTILLA","Configurar cintilla: "&E103,IF(T103="SIN ID MÓDULO","Revisar ID del módulo",""))))) | V103: =IF(T103="OK",0,IF(T103="",0,1)) -> 0
A104: 1 | B104: 869 | C104: 649 | D104: Respaldo Alacena | E104: ARAUCO BLANCO | F104: 0 | G104: 0 | H104: 0 | I104: 0 | J104: 0 | K104: ALA-2PU-906832 | L104: RES-ALA-6890 | M104: =IF(AND(ISNUMBER(B104),ISNUMBER(C104),B104>0,C104>0),A104*(B104*C104/1000000),0) -> 0.563981 | N104: =IF(AND(ISNUMBER(B104),B104>0),A104*(((G104+H104)*B104+(I104+J104)*C104)/1000),0) -> 0 | O104: =IF(E104="HERRAJE",IFERROR(_xlfn.XLOOKUP(D104,'⚙️ Configuración Costos'!$A$11:$A$20,'⚙️ Configuración Costos'!$B$11:$B$20),""),IFERROR(_xlfn.XLOOKUP(E104,'⚙️ Configuración Costos'!$A$5:$A$6,'⚙️ Configuración Costos'!$B$5:$B$6),"")) -> 239.84262 | P104: =IF(E104="HERRAJE",A104*O104,M104*O104) -> 135.26668 | Q104: =IF(E104="HERRAJE",0,IFERROR(_xlfn.XLOOKUP(E104,'⚙️ Configuración Costos'!$E$5:$E$6,'⚙️ Configuración Costos'!$F$5:$F$6),"")) -> 6 | R104: =N104*Q104 -> 0 | S104: =P104+R104 -> 135.26668 | T104: =IF(K104="","SIN ID MÓDULO",IF(E104="HERRAJE",IF(OR(O104="",O104<=0),"SIN PRECIO HERRAJE","OK"),IF(OR(O104="",O104<=0),"SIN PRECIO MATERIAL",IF(AND(N104>0,OR(Q104="",Q104<=0)),"SIN PRECIO CINTILLA","OK")))) -> OK | U104: =IF(T104="OK","",IF(T104="SIN PRECIO HERRAJE","Capturar precio: "&D104,IF(T104="SIN PRECIO MATERIAL","Configurar material: "&E104,IF(T104="SIN PRECIO CINTILLA","Configurar cintilla: "&E104,IF(T104="SIN ID MÓDULO","Revisar ID del módulo",""))))) | V104: =IF(T104="OK",0,IF(T104="",0,1)) -> 0
...

Sheet 📋 Explosión y Despiece Mad
A1: Cantidad | B1: Largo (mm) | C1: Ancho (mm) | D1: Descripción de la Pieza / Módulo | E1: Materia Prima | F1: Veta | G1: Largo 1 | H1: Largo 2 | I1: Ancho 1 | J1: Ancho 2 | K1: Codigo | L1: Código Pieza | M1: M² Totales | N1: ML Cintilla | O1: Costo Unit. Mat/Herr | P1: Costo Tot. Mat/Herr | Q1: Costo Unit. Cintilla | R1: Costo Tot. Cintilla | S1: Costo Total Elemento | T1: Validación | U1: Detalle de alerta | V1: Alerta
A2: Alacena Rinconera 650 x 680 x 320 mm
A3: 1 | B3: 680 | C3: 320 | D3: Lateral Derecho | E3: VESTO NOUGAT | F3: 1 | G3: 1 | H3: 1 | I3: 1 | J3: 1 | K3: ALA-RIN-656832 | L3: LAT-ALA-6832-D | M3: =IF(AND(ISNUMBER(B3),ISNUMBER(C3),B3>0,C3>0),A3*(B3*C3/1000000),0) -> 0.2176 | N3: =IF(AND(ISNUMBER(B3),B3>0),A3*(((G3+H3)*B3+(I3+J3)*C3)/1000),0) -> 2 | O3: =IF(E3="HERRAJE",IFERROR(_xlfn.XLOOKUP(D3,'⚙️ Configuración Costos'!$A$11:$A$20,'⚙️ Configuración Costos'!$B$11:$B$20),""),IFERROR(_xlfn.XLOOKUP(E3,'⚙️ Configuración Costos'!$A$5:$A$6,'⚙️ Configuración Costos'!$B$5:$B$6),"")) -> 332.85246 | P3: =IF(E3="HERRAJE",A3*O3,M3*O3) -> 72.428695 | Q3: =IF(E3="HERRAJE",0,IFERROR(_xlfn.XLOOKUP(E3,'⚙️ Configuración Costos'!$E$5:$E$6,'⚙️ Configuración Costos'!$F$5:$F$6),"")) -> 9.5 | R3: =N3*Q3 -> 19 | S3: =P3+R3 -> 91.428695 | T3: =IF(K3="","SIN ID MÓDULO",IF(E3="HERRAJE",IF(OR(O3="",O3<=0),"SIN PRECIO HERRAJE","OK"),IF(OR(O3="",O3<=0),"SIN PRECIO MATERIAL",IF(AND(N3>0,OR(Q3="",Q3<=0)),"SIN PRECIO CINTILLA","OK")))) -> OK | U3: =IF(T3="OK","",IF(T3="SIN PRECIO HERRAJE","Capturar precio: "&D3,IF(T3="SIN PRECIO MATERIAL","Configurar material: "&E3,IF(T3="SIN PRECIO CINTILLA","Configurar cintilla: "&E3,IF(T3="SIN ID MÓDULO","Revisar ID del módulo",""))))) | V3: =IF(T3="OK",0,IF(T3="",0,1)) -> 0
A4: 1 | B4: 680 | C4: 320 | D4: Lateral Izquierdo | E4: VESTO NOUGAT | F4: 1 | G4: 1 | H4: 1 | I4: 1 | J4: 1 | K4: ALA-RIN-656832 | L4: LAT-ALA-6832-I | M4: =IF(AND(ISNUMBER(B4),ISNUMBER(C4),B4>0,C4>0),A4*(B4*C4/1000000),0) -> 0.2176 | N4: =IF(AND(ISNUMBER(B4),B4>0),A4*(((G4+H4)*B4+(I4+J4)*C4)/1000),0) -> 2 | O4: =IF(E4="HERRAJE",IFERROR(_xlfn.XLOOKUP(D4,'⚙️ Configuración Costos'!$A$11:$A$20,'⚙️ Configuración Costos'!$B$11:$B$20),""),IFERROR(_xlfn.XLOOKUP(E4,'⚙️ Configuración Costos'!$A$5:$A$6,'⚙️ Configuración Costos'!$B$5:$B$6),"")) -> 332.85246 | P4: =IF(E4="HERRAJE",A4*O4,M4*O4) -> 72.428695 | Q4: =IF(E4="HERRAJE",0,IFERROR(_xlfn.XLOOKUP(E4,'⚙️ Configuración Costos'!$E$5:$E$6,'⚙️ Configuración Costos'!$F$5:$F$6),"")) -> 9.5 | R4: =N4*Q4 -> 19 | S4: =P4+R4 -> 91.428695 | T4: =IF(K4="","SIN ID MÓDULO",IF(E4="HERRAJE",IF(OR(O4="",O4<=0),"SIN PRECIO HERRAJE","OK"),IF(OR(O4="",O4<=0),"SIN PRECIO MATERIAL",IF(AND(N4>0,OR(Q4="",Q4<=0)),"SIN PRECIO CINTILLA","OK")))) -> OK | U4: =IF(T4="OK","",IF(T4="SIN PRECIO HERRAJE","Capturar precio: "&D4,IF(T4="SIN PRECIO MATERIAL","Configurar material: "&E4,IF(T4="SIN PRECIO CINTILLA","Configurar cintilla: "&E4,IF(T4="SIN ID MÓDULO","Revisar ID del módulo",""))))) | V4: =IF(T4="OK",0,IF(T4="",0,1)) -> 0
A5: 1 | B5: 649 | C5: 619 | D5: Respaldo Alacena | E5: VESTO NOUGAT | F5: 1 | G5: 0 | H5: 0 | I5: 0 | J5: 0 | K5: ALA-RIN-656832 | L5: RES-ALA-6865 | M5: =IF(AND(ISNUMBER(B5),ISNUMBER(C5),B5>0,C5>0),A5*(B5*C5/1000000),0) -> 0.401731 | N5: =IF(AND(ISNUMBER(B5),B5>0),A5*(((G5+H5)*B5+(I5+J5)*C5)/1000),0) -> 0 | O5: =IF(E5="HERRAJE",IFERROR(_xlfn.XLOOKUP(D5,'⚙️ Configuración Costos'!$A$11:$A$20,'⚙️ Configuración Costos'!$B$11:$B$20),""),IFERROR(_xlfn.XLOOKUP(E5,'⚙️ Configuración Costos'!$A$5:$A$6,'⚙️ Configuración Costos'!$B$5:$B$6),"")) -> 332.85246 | P5: =IF(E5="HERRAJE",A5*O5,M5*O5) -> 133.71715 | Q5: =IF(E5="HERRAJE",0,IFERROR(_xlfn.XLOOKUP(E5,'⚙️ Configuración Costos'!$E$5:$E$6,'⚙️ Configuración Costos'!$F$5:$F$6),"")) -> 9.5 | R5: =N5*Q5 -> 0 | S5: =P5+R5 -> 133.71715 | T5: =IF(K5="","SIN ID MÓDULO",IF(E5="HERRAJE",IF(OR(O5="",O5<=0),"SIN PRECIO HERRAJE","OK"),IF(OR(O5="",O5<=0),"SIN PRECIO MATERIAL",IF(AND(N5>0,OR(Q5="",Q5<=0)),"SIN PRECIO CINTILLA","OK")))) -> OK | U5: =IF(T5="OK","",IF(T5="SIN PRECIO HERRAJE","Capturar precio: "&D5,IF(T5="SIN PRECIO MATERIAL","Configurar material: "&E5,IF(T5="SIN PRECIO CINTILLA","Configurar cintilla: "&E5,IF(T5="SIN ID MÓDULO","Revisar ID del módulo",""))))) | V5: =IF(T5="OK",0,IF(T5="",0,1)) -> 0
A6: 1 | B6: 619 | C6: 320 | D6: Base Alacena | E6: VESTO NOUGAT | F6: 1 | G6: 1 | H6: 1 | I6: 0 | J6: 0 | K6: ALA-RIN-656832 | L6: BAS-ALA-6532 | M6: =IF(AND(ISNUMBER(B6),ISNUMBER(C6),B6>0,C6>0),A6*(B6*C6/1000000),0) -> 0.19808 | N6: =IF(AND(ISNUMBER(B6),B6>0),A6*(((G6+H6)*B6+(I6+J6)*C6)/1000),0) -> 1.238 | O6: =IF(E6="HERRAJE",IFERROR(_xlfn.XLOOKUP(D6,'⚙️ Configuración Costos'!$A$11:$A$20,'⚙️ Configuración Costos'!$B$11:$B$20),""),IFERROR(_xlfn.XLOOKUP(E6,'⚙️ Configuración Costos'!$A$5:$A$6,'⚙️ Configuración Costos'!$B$5:$B$6),"")) -> 332.85246 | P6: =IF(E6="HERRAJE",A6*O6,M6*O6) -> 65.931415 | Q6: =IF(E6="HERRAJE",0,IFERROR(_xlfn.XLOOKUP(E6,'⚙️ Configuración Costos'!$E$5:$E$6,'⚙️ Configuración Costos'!$F$5:$F$6),"")) -> 9.5 | R6: =N6*Q6 -> 11.761 | S6: =P6+R6 -> 77.692415 | T6: =IF(K6="","SIN ID MÓDULO",IF(E6="HERRAJE",IF(OR(O6="",O6<=0),"SIN PRECIO HERRAJE","OK"),IF(OR(O6="",O6<=0),"SIN PRECIO MATERIAL",IF(AND(N6>0,OR(Q6="",Q6<=0)),"SIN PRECIO CINTILLA","OK")))) -> OK | U6: =IF(T6="OK","",IF(T6="SIN PRECIO HERRAJE","Capturar precio: "&D6,IF(T6="SIN PRECIO MATERIAL","Configurar material: "&E6,IF(T6="SIN PRECIO CINTILLA","Configurar cintilla: "&E6,IF(T6="SIN ID MÓDULO","Revisar ID del módulo",""))))) | V6: =IF(T6="OK",0,IF(T6="",0,1)) -> 0
A7: 1 | B7: 619 | C7: 320 | D7: Techo Alacena | E7: VESTO NOUGAT | F7: 1 | G7: 1 | H7: 1 | I7: 0 | J7: 0 | K7: ALA-RIN-656832 | L7: TEC-ALA-6532 | M7: =IF(AND(ISNUMBER(B7),ISNUMBER(C7),B7>0,C7>0),A7*(B7*C7/1000000),0) -> 0.19808 | N7: =IF(AND(ISNUMBER(B7),B7>0),A7*(((G7+H7)*B7+(I7+J7)*C7)/1000),0) -> 1.238 | O7: =IF(E7="HERRAJE",IFERROR(_xlfn.XLOOKUP(D7,'⚙️ Configuración Costos'!$A$11:$A$20,'⚙️ Configuración Costos'!$B$11:$B$20),""),IFERROR(_xlfn.XLOOKUP(E7,'⚙️ Configuración Costos'!$A$5:$A$6,'⚙️ Configuración Costos'!$B$5:$B$6),"")) -> 332.85246 | P7: =IF(E7="HERRAJE",A7*O7,M7*O7) -> 65.931415 | Q7: =IF(E7="HERRAJE",0,IFERROR(_xlfn.XLOOKUP(E7,'⚙️ Configuración Costos'!$E$5:$E$6,'⚙️ Configuración Costos'!$F$5:$F$6),"")) -> 9.5 | R7: =N7*Q7 -> 11.761 | S7: =P7+R7 -> 77.692415 | T7: =IF(K7="","SIN ID MÓDULO",IF(E7="HERRAJE",IF(OR(O7="",O7<=0),"SIN PRECIO HERRAJE","OK"),IF(OR(O7="",O7<=0),"SIN PRECIO MATERIAL",IF(AND(N7>0,OR(Q7="",Q7<=0)),"SIN PRECIO CINTILLA","OK")))) -> OK | U7: =IF(T7="OK","",IF(T7="SIN PRECIO HERRAJE","Capturar precio: "&D7,IF(T7="SIN PRECIO MATERIAL","Configurar material: "&E7,IF(T7="SIN PRECIO CINTILLA","Configurar cintilla: "&E7,IF(T7="SIN ID MÓDULO","Revisar ID del módulo",""))))) | V7: =IF(T7="OK",0,IF(T7="",0,1)) -> 0
A8: 1 | B8: 619 | C8: 256 | D8: Entrepaño Alacena | E8: VESTO NOUGAT | F8: 1 | G8: 1 | H8: 0 | I8: 0 | J8: 0 | K8: ALA-RIN-656832 | L8: ENT-ALA-6526 | M8: =IF(AND(ISNUMBER(B8),ISNUMBER(C8),B8>0,C8>0),A8*(B8*C8/1000000),0) -> 0.158464 | N8: =IF(AND(ISNUMBER(B8),B8>0),A8*(((G8+H8)*B8+(I8+J8)*C8)/1000),0) -> 0.619 | O8: =IF(E8="HERRAJE",IFERROR(_xlfn.XLOOKUP(D8,'⚙️ Configuración Costos'!$A$11:$A$20,'⚙️ Configuración Costos'!$B$11:$B$20),""),IFERROR(_xlfn.XLOOKUP(E8,'⚙️ Configuración Costos'!$A$5:$A$6,'⚙️ Configuración Costos'!$B$5:$B$6),"")) -> 332.85246 | P8: =IF(E8="HERRAJE",A8*O8,M8*O8) -> 52.745132 | Q8: =IF(E8="HERRAJE",0,IFERROR(_xlfn.XLOOKUP(E8,'⚙️ Configuración Costos'!$E$5:$E$6,'⚙️ Configuración Costos'!$F$5:$F$6),"")) -> 9.5 | R8: =N8*Q8 -> 5.8805 | S8: =P8+R8 -> 58.625632 | T8: =IF(K8="","SIN ID MÓDULO",IF(E8="HERRAJE",IF(OR(O8="",O8<=0),"SIN PRECIO HERRAJE","OK"),IF(OR(O8="",O8<=0),"SIN PRECIO MATERIAL",IF(AND(N8>0,OR(Q8="",Q8<=0)),"SIN PRECIO CINTILLA","OK")))) -> OK | U8: =IF(T8="OK","",IF(T8="SIN PRECIO HERRAJE","Capturar precio: "&D8,IF(T8="SIN PRECIO MATERIAL","Configurar material: "&E8,IF(T8="SIN PRECIO CINTILLA","Configurar cintilla: "&E8,IF(T8="SIN ID MÓDULO","Revisar ID del módulo",""))))) | V8: =IF(T8="OK",0,IF(T8="",0,1)) -> 0
A9: 1 | B9: 649 | C9: 339 | D9: Tapa Ciega | E9: VESTO NOUGAT | F9: 1 | G9: 0 | H9: 0 | I9: 0 | J9: 0 | K9: ALA-RIN-656832 | L9: TAP-ALA-6534 | M9: =IF(AND(ISNUMBER(B9),ISNUMBER(C9),B9>0,C9>0),A9*(B9*C9/1000000),0) -> 0.220011 | N9: =IF(AND(ISNUMBER(B9),B9>0),A9*(((G9+H9)*B9+(I9+J9)*C9)/1000),0) -> 0 | O9: =IF(E9="HERRAJE",IFERROR(_xlfn.XLOOKUP(D9,'⚙️ Configuración Costos'!$A$11:$A$20,'⚙️ Configuración Costos'!$B$11:$B$20),""),IFERROR(_xlfn.XLOOKUP(E9,'⚙️ Configuración Costos'!$A$5:$A$6,'⚙️ Configuración Costos'!$B$5:$B$6),"")) -> 332.85246 | P9: =IF(E9="HERRAJE",A9*O9,M9*O9) -> 73.231202 | Q9: =IF(E9="HERRAJE",0,IFERROR(_xlfn.XLOOKUP(E9,'⚙️ Configuración Costos'!$E$5:$E$6,'⚙️ Configuración Costos'!$F$5:$F$6),"")) -> 9.5 | R9: =N9*Q9 -> 0 | S9: =P9+R9 -> 73.231202 | T9: =IF(K9="","SIN ID MÓDULO",IF(E9="HERRAJE",IF(OR(O9="",O9<=0),"SIN PRECIO HERRAJE","OK"),IF(OR(O9="",O9<=0),"SIN PRECIO MATERIAL",IF(AND(N9>0,OR(Q9="",Q9<=0)),"SIN PRECIO CINTILLA","OK")))) -> OK | U9: =IF(T9="OK","",IF(T9="SIN PRECIO HERRAJE","Capturar precio: "&D9,IF(T9="SIN PRECIO MATERIAL","Configurar material: "&E9,IF(T9="SIN PRECIO CINTILLA","Configurar cintilla: "&E9,IF(T9="SIN ID MÓDULO","Revisar ID del módulo",""))))) | V9: =IF(T9="OK",0,IF(T9="",0,1)) -> 0
A10: 1 | B10: 649 | C10: 70 | D10: Refuerzo Bisagra | E10: VESTO NOUGAT | F10: 1 | G10: 1 | H10: 1 | I10: 0 | J10: 0 | K10: ALA-RIN-656832 | L10: REF-BIS-ALA-657 | M10: =IF(AND(ISNUMBER(B10),ISNUMBER(C10),B10>0,C10>0),A10*(B10*C10/1000000),0) -> 0.04543 | N10: =IF(AND(ISNUMBER(B10),B10>0),A10*(((G10+H10)*B10+(I10+J10)*C10)/1000),0) -> 1.298 | O10: =IF(E10="HERRAJE",IFERROR(_xlfn.XLOOKUP(D10,'⚙️ Configuración Costos'!$A$11:$A$20,'⚙️ Configuración Costos'!$B$11:$B$20),""),IFERROR(_xlfn.XLOOKUP(E10,'⚙️ Configuración Costos'!$A$5:$A$6,'⚙️ Configuración Costos'!$B$5:$B$6),"")) -> 332.85246 | P10: =IF(E10="HERRAJE",A10*O10,M10*O10) -> 15.121487 | Q10: =IF(E10="HERRAJE",0,IFERROR(_xlfn.XLOOKUP(E10,'⚙️ Configuración Costos'!$E$5:$E$6,'⚙️ Configuración Costos'!$F$5:$F$6),"")) -> 9.5 | R10: =N10*Q10 -> 12.331 | S10: =P10+R10 -> 27.452487 | T10: =IF(K10="","SIN ID MÓDULO",IF(E10="HERRAJE",IF(OR(O10="",O10<=0),"SIN PRECIO HERRAJE","OK"),IF(OR(O10="",O10<=0),"SIN PRECIO MATERIAL",IF(AND(N10>0,OR(Q10="",Q10<=0)),"SIN PRECIO CINTILLA","OK")))) -> OK | U10: =IF(T10="OK","",IF(T10="SIN PRECIO HERRAJE","Capturar precio: "&D10,IF(T10="SIN PRECIO MATERIAL","Configurar material: "&E10,IF(T10="SIN PRECIO CINTILLA","Configurar cintilla: "&E10,IF(T10="SIN ID MÓDULO","Revisar ID del módulo",""))))) | V10: =IF(T10="OK",0,IF(T10="",0,1)) -> 0
A11: 1 | B11: 320 | C11: 50 | D11: Ajuste Inferior | E11: VESTO NOUGAT | F11: 1 | G11: 0 | H11: 0 | I11: 1 | J11: 1 | K11: ALA-RIN-656832 | L11: AJU-INF-ALA-325 | M11: =IF(AND(ISNUMBER(B11),ISNUMBER(C11),B11>0,C11>0),A11*(B11*C11/1000000),0) -> 0.016 | N11: =IF(AND(ISNUMBER(B11),B11>0),A11*(((G11+H11)*B11+(I11+J11)*C11)/1000),0) -> 0.1 | O11: =IF(E11="HERRAJE",IFERROR(_xlfn.XLOOKUP(D11,'⚙️ Configuración Costos'!$A$11:$A$20,'⚙️ Configuración Costos'!$B$11:$B$20),""),IFERROR(_xlfn.XLOOKUP(E11,'⚙️ Configuración Costos'!$A$5:$A$6,'⚙️ Configuración Costos'!$B$5:$B$6),"")) -> 332.85246 | P11: =IF(E11="HERRAJE",A11*O11,M11*O11) -> 5.3256393 | Q11: =IF(E11="HERRAJE",0,IFERROR(_xlfn.XLOOKUP(E11,'⚙️ Configuración Costos'!$E$5:$E$6,'⚙️ Configuración Costos'!$F$5:$F$6),"")) -> 9.5 | R11: =N11*Q11 -> 0.95 | S11: =P11+R11 -> 6.2756393 | T11: =IF(K11="","SIN ID MÓDULO",IF(E11="HERRAJE",IF(OR(O11="",O11<=0),"SIN PRECIO HERRAJE","OK"),IF(OR(O11="",O11<=0),"SIN PRECIO MATERIAL",IF(AND(N11>0,OR(Q11="",Q11<=0)),"SIN PRECIO CINTILLA","OK")))) -> OK | U11: =IF(T11="OK","",IF(T11="SIN PRECIO HERRAJE","Capturar precio: "&D11,IF(T11="SIN PRECIO MATERIAL","Configurar material: "&E11,IF(T11="SIN PRECIO CINTILLA","Configurar cintilla: "&E11,IF(T11="SIN ID MÓDULO","Revisar ID del módulo",""))))) | V11: =IF(T11="OK",0,IF(T11="",0,1)) -> 0
A12: 1 | B12: 320 | C12: 50 | D12: Ajuste Superior | E12: VESTO NOUGAT | F12: 1 | G12: 0 | H12: 0 | I12: 1 | J12: 1 | K12: ALA-RIN-656832 | L12: AJU-SUP-ALA-325 | M12: =IF(AND(ISNUMBER(B12),ISNUMBER(C12),B12>0,C12>0),A12*(B12*C12/1000000),0) -> 0.016 | N12: =IF(AND(ISNUMBER(B12),B12>0),A12*(((G12+H12)*B12+(I12+J12)*C12)/1000),0) -> 0.1 | O12: =IF(E12="HERRAJE",IFERROR(_xlfn.XLOOKUP(D12,'⚙️ Configuración Costos'!$A$11:$A$20,'⚙️ Configuración Costos'!$B$11:$B$20),""),IFERROR(_xlfn.XLOOKUP(E12,'⚙️ Configuración Costos'!$A$5:$A$6,'⚙️ Configuración Costos'!$B$5:$B$6),"")) -> 332.85246 | P12: =IF(E12="HERRAJE",A12*O12,M12*O12) -> 5.3256393 | Q12: =IF(E12="HERRAJE",0,IFERROR(_xlfn.XLOOKUP(E12,'⚙️ Configuración Costos'!$E$5:$E$6,'⚙️ Configuración Costos'!$F$5:$F$6),"")) -> 9.5 | R12: =N12*Q12 -> 0.95 | S12: =P12+R12 -> 6.2756393 | T12: =IF(K12="","SIN ID MÓDULO",IF(E12="HERRAJE",IF(OR(O12="",O12<=0),"SIN PRECIO HERRAJE","OK"),IF(OR(O12="",O12<=0),"SIN PRECIO MATERIAL",IF(AND(N12>0,OR(Q12="",Q12<=0)),"SIN PRECIO CINTILLA","OK")))) -> OK | U12: =IF(T12="OK","",IF(T12="SIN PRECIO HERRAJE","Capturar precio: "&D12,IF(T12="SIN PRECIO MATERIAL","Configurar material: "&E12,IF(T12="SIN PRECIO CINTILLA","Configurar cintilla: "&E12,IF(T12="SIN ID MÓDULO","Revisar ID del módulo",""))))) | V12: =IF(T12="OK",0,IF(T12="",0,1)) -> 0
A13: 1 | B13: 677 | C13: 292 | D13: Puerta Alacena | E13: VESTO NOUGAT | F13: 1 | G13: 1 | H13: 1 | I13: 1 | J13: 1 | K13: ALA-RIN-656832 | L13: PUE-ALA-6829 | M13: =IF(AND(ISNUMBER(B13),ISNUMBER(C13),B13>0,C13>0),A13*(B13*C13/1000000),0) -> 0.197684 | N13: =IF(AND(ISNUMBER(B13),B13>0),A13*(((G13+H13)*B13+(I13+J13)*C13)/1000),0) -> 1.938 | O13: =IF(E13="HERRAJE",IFERROR(_xlfn.XLOOKUP(D13,'⚙️ Configuración Costos'!$A$11:$A$20,'⚙️ Configuración Costos'!$B$11:$B$20),""),IFERROR(_xlfn.XLOOKUP(E13,'⚙️ Configuración Costos'!$A$5:$A$6,'⚙️ Configuración Costos'!$B$5:$B$6),"")) -> 332.85246 | P13: =IF(E13="HERRAJE",A13*O13,M13*O13) -> 65.799606 | Q13: =IF(E13="HERRAJE",0,IFERROR(_xlfn.XLOOKUP(E13,'⚙️ Configuración Costos'!$E$5:$E$6,'⚙️ Configuración Costos'!$F$5:$F$6),"")) -> 9.5 | R13: =N13*Q13 -> 18.411 | S13: =P13+R13 -> 84.210606 | T13: =IF(K13="","SIN ID MÓDULO",IF(E13="HERRAJE",IF(OR(O13="",O13<=0),"SIN PRECIO HERRAJE","OK"),IF(OR(O13="",O13<=0),"SIN PRECIO MATERIAL",IF(AND(N13>0,OR(Q13="",Q13<=0)),"SIN PRECIO CINTILLA","OK")))) -> OK | U13: =IF(T13="OK","",IF(T13="SIN PRECIO HERRAJE","Capturar precio: "&D13,IF(T13="SIN PRECIO MATERIAL","Configurar material: "&E13,IF(T13="SIN PRECIO CINTILLA","Configurar cintilla: "&E13,IF(T13="SIN ID MÓDULO","Revisar ID del módulo",""))))) | V13: =IF(T13="OK",0,IF(T13="",0,1)) -> 0
A14: 1 | B14: 677 | C14: 70 | D14: Ajuste 1 Rinconero | E14: VESTO NOUGAT | F14: 1 | G14: 1 | H14: 1 | I14: 1 | J14: 1 | K14: ALA-RIN-656832 | L14: AJU-RIN-ALA-687 | M14: =IF(AND(ISNUMBER(B14),ISNUMBER(C14),B14>0,C14>0),A14*(B14*C14/1000000),0) -> 0.04739 | N14: =IF(AND(ISNUMBER(B14),B14>0),A14*(((G14+H14)*B14+(I14+J14)*C14)/1000),0) -> 1.494 | O14: =IF(E14="HERRAJE",IFERROR(_xlfn.XLOOKUP(D14,'⚙️ Configuración Costos'!$A$11:$A$20,'⚙️ Configuración Costos'!$B$11:$B$20),""),IFERROR(_xlfn.XLOOKUP(E14,'⚙️ Configuración Costos'!$A$5:$A$6,'⚙️ Configuración Costos'!$B$5:$B$6),"")) -> 332.85246 | P14: =IF(E14="HERRAJE",A14*O14,M14*O14) -> 15.773878 | Q14: =IF(E14="HERRAJE",0,IFERROR(_xlfn.XLOOKUP(E14,'⚙️ Configuración Costos'!$E$5:$E$6,'⚙️ Configuración Costos'!$F$5:$F$6),"")) -> 9.5 | R14: =N14*Q14 -> 14.193 | S14: =P14+R14 -> 29.966878 | T14: =IF(K14="","SIN ID MÓDULO",IF(E14="HERRAJE",IF(OR(O14="",O14<=0),"SIN PRECIO HERRAJE","OK"),IF(OR(O14="",O14<=0),"SIN PRECIO MATERIAL",IF(AND(N14>0,OR(Q14="",Q14<=0)),"SIN PRECIO CINTILLA","OK")))) -> OK | U14: =IF(T14="OK","",IF(T14="SIN PRECIO HERRAJE","Capturar precio: "&D14,IF(T14="SIN PRECIO MATERIAL","Configurar material: "&E14,IF(T14="SIN PRECIO CINTILLA","Configurar cintilla: "&E14,IF(T14="SIN ID MÓDULO","Revisar ID del módulo",""))))) | V14: =IF(T14="OK",0,IF(T14="",0,1)) -> 0
... A18: 4 | B18: 0 | C18: 0 | D18: Soporte de Entrepaño | E18: HERRAJE | F18: 0 | G18: 0 | H18: 0 | I18: 0 | J18: 0 | K18: ALA-RIN-656832 | L18: SOP-ENT | M18: =IF(AND(ISNUMBER(B18),ISNUMBER(C18),B18>0,C18>0),A18*(B18*C18/1000000),0) -> 0 | N18: =IF(AND(ISNUMBER(B18),B18>0),A18*(((G18+H18)*B18+(I18+J18)*C18)/1000),0) -> 0 | O18: =IF(E18="HERRAJE",IFERROR(_xlfn.XLOOKUP(D18,'⚙️ Configuración Costos'!$A$11:$A$20,'⚙️ Configuración Costos'!$B$11:$B$20),""),IFERROR(_xlfn.XLOOKUP(E18,'⚙️ Configuración Costos'!$A$5:$A$6,'⚙️ Configuración Costos'!$B$5:$B$6),"")) -> 2 | P18: =IF(E18="HERRAJE",A18*O18,M18*O18) -> 8 | Q18: =IF(E18="HERRAJE",0,IFERROR(_xlfn.XLOOKUP(E18,'⚙️ Configuración Costos'!$E$5:$E$6,'⚙️ Configuración Costos'!$F$5:$F$6),"")) -> 0 | R18: =N18*Q18 -> 0 | S18: =P18+R18 -> 8 | T18: =IF(K18="","SIN ID MÓDULO",IF(E18="HERRAJE",IF(OR(O18="",O18<=0),"SIN PRECIO HERRAJE","OK"),IF(OR(O18="",O18<=0),"SIN PRECIO MATERIAL",IF(AND(N18>0,OR(Q18="",Q18<=0)),"SIN PRECIO CINTILLA","OK")))) -> OK | U18: =IF(T18="OK","",IF(T18="SIN PRECIO HERRAJE","Capturar precio: "&D18,IF(T18="SIN PRECIO MATERIAL","Configurar material: "&E18,IF(T18="SIN PRECIO CINTILLA","Configurar cintilla: "&E18,IF(T18="SIN ID MÓDULO","Revisar ID del módulo",""))))) | V18: =IF(T18="OK",0,IF(T18="",0,1)) -> 0
A19: =4*(IF(LEFT(D3,4)="Base",A3,0)+IF(LEFT(D3,4)="Piso",A3,0)+IF(LEFT(D3,5)="Techo",A3,0)+IF(LEFT(D4,4)="Base",A4,0)+IF(LEFT(D4,4)="Piso",A4,0)+IF(LEFT(D4,5)="Techo",A4,0)+IF(LEFT(D5,4)="Base",A5,0)+IF(LEFT(D5,4)="Piso",A5,0)+IF(LEFT(D5,5)="Techo",A5,0)+IF(LEFT(D6,4)="Base",A6,0)+IF(LEFT(D6,4)="Piso",A6,0)+IF(LEFT(D6,5)="Techo",A6,0)+IF(LEFT(D7,4)="Base",A7,0)+IF(LEFT(D7,4)="Piso",A7,0)+IF(LEFT(D7,5)="Techo",A7,0)+IF(LEFT(D8,4)="Base",A8,0)+IF(LEFT(D8,4)="Piso",A8,0)+IF(LEFT(D8,5)="Techo",A8,0)+IF(LEFT(D9,4)="Base",A9,0)+IF(LEFT(D9,4)="Piso",A9,0)+IF(LEFT(D9,5)="Techo",A9,0)+IF(LEFT(D10,4)="Base",A10,0)+IF(LEFT(D10,4)="Piso",A10,0)+IF(LEFT(D10,5)="Techo",A10,0)+IF(LEFT(D11,4)="Base",A11,0)+IF(LEFT(D11,4)="Piso",A11,0)+IF(LEFT(D11,5)="Techo",A11,0)+IF(LEFT(D12,4)="Base",A12,0)+IF(LEFT(D12,4)="Piso",A12,0)+IF(LEFT(D12,5)="Techo",A12,0)+IF(LEFT(D13,4)="Base",A13,0)+IF(LEFT(D13,4)="Piso",A13,0)+IF(LEFT(D13,5)="Techo",A13,0)+IF(LEFT(D14,4)="Base",A14,0)+IF(LEFT(D14,4)="Piso",A14,0)+IF(LEFT(D14,5)="Techo",A14,0)+IF(LEFT(D15,4)="Base",A15,0)+IF(LEFT(D15,4)="Piso",A15,0)+IF(LEFT(D15,5)="Techo",A15,0))+10*(IF(LEFT(D3,8)="Respaldo",A3,0)+IF(LEFT(D4,8)="Respaldo",A4,0)+IF(LEFT(D5,8)="Respaldo",A5,0)+IF(LEFT(D6,8)="Respaldo",A6,0)+IF(LEFT(D7,8)="Respaldo",A7,0)+IF(LEFT(D8,8)="Respaldo",A8,0)+IF(LEFT(D9,8)="Respaldo",A9,0)+IF(LEFT(D10,8)="Respaldo",A10,0)+IF(LEFT(D11,8)="Respaldo",A11,0)+IF(LEFT(D12,8)="Respaldo",A12,0)+IF(LEFT(D13,8)="Respaldo",A13,0)+IF(LEFT(D14,8)="Respaldo",A14,0)+IF(LEFT(D15,8)="Respaldo",A15,0))+2*(IF(LEFT(D3,8)="Manguete",A3,0)+IF(LEFT(D4,8)="Manguete",A4,0)+IF(LEFT(D5,8)="Manguete",A5,0)+IF(LEFT(D6,8)="Manguete",A6,0)+IF(LEFT(D7,8)="Manguete",A7,0)+IF(LEFT(D8,8)="Manguete",A8,0)+IF(LEFT(D9,8)="Manguete",A9,0)+IF(LEFT(D10,8)="Manguete",A10,0)+IF(LEFT(D11,8)="Manguete",A11,0)+IF(LEFT(D12,8)="Manguete",A12,0)+IF(LEFT(D13,8)="Manguete",A13,0)+IF(LEFT(D14,8)="Manguete",A14,0)+IF(LEFT(D15,8)="Manguete",A15,0)) -> 18 | B19: 0 | C19: 0 | D19: Kit Minifixx 15mm | E19: HERRAJE | F19: 0 | G19: 0 | H19: 0 | I19: 0 | J19: 0 | K19: ALA-RIN-656832 | L19: KIT-MIN-15 | M19: =IF(AND(ISNUMBER(B19),ISNUMBER(C19),B19>0,C19>0),A19*(B19*C19/1000000),0) -> 0 | N19: =IF(AND(ISNUMBER(B19),B19>0),A19*(((G19+H19)*B19+(I19+J19)*C19)/1000),0) -> 0 | O19: =IF(E19="HERRAJE",IFERROR(_xlfn.XLOOKUP(D19,'⚙️ Configuración Costos'!$A$11:$A$20,'⚙️ Configuración Costos'!$B$11:$B$20),""),IFERROR(_xlfn.XLOOKUP(E19,'⚙️ Configuración Costos'!$A$5:$A$6,'⚙️ Configuración Costos'!$B$5:$B$6),"")) -> 3 | P19: =IF(E19="HERRAJE",A19*O19,M19*O19) -> 54 | Q19: =IF(E19="HERRAJE",0,IFERROR(_xlfn.XLOOKUP(E19,'⚙️ Configuración Costos'!$E$5:$E$6,'⚙️ Configuración Costos'!$F$5:$F$6),"")) -> 0 | R19: =N19*Q19 -> 0 | S19: =P19+R19 -> 54 | T19: =IF(K19="","SIN ID MÓDULO",IF(E19="HERRAJE",IF(OR(O19="",O19<=0),"SIN PRECIO HERRAJE","OK"),IF(OR(O19="",O19<=0),"SIN PRECIO MATERIAL",IF(AND(N19>0,OR(Q19="",Q19<=0)),"SIN PRECIO CINTILLA","OK")))) -> OK | U19: =IF(T19="OK","",IF(T19="SIN PRECIO HERRAJE","Capturar precio: "&D19,IF(T19="SIN PRECIO MATERIAL","Configurar material: "&E19,IF(T19="SIN PRECIO CINTILLA","Configurar cintilla: "&E19,IF(T19="SIN ID MÓDULO","Revisar ID del módulo",""))))) | V19: =IF(T19="OK",0,IF(T19="",0,1)) -> 0
A20: =6*(IF(LEFT(D3,4)="Base",A3,0)+IF(LEFT(D3,4)="Piso",A3,0)+IF(LEFT(D3,5)="Techo",A3,0)+IF(LEFT(D4,4)="Base",A4,0)+IF(LEFT(D4,4)="Piso",A4,0)+IF(LEFT(D4,5)="Techo",A4,0)+IF(LEFT(D5,4)="Base",A5,0)+IF(LEFT(D5,4)="Piso",A5,0)+IF(LEFT(D5,5)="Techo",A5,0)+IF(LEFT(D6,4)="Base",A6,0)+IF(LEFT(D6,4)="Piso",A6,0)+IF(LEFT(D6,5)="Techo",A6,0)+IF(LEFT(D7,4)="Base",A7,0)+IF(LEFT(D7,4)="Piso",A7,0)+IF(LEFT(D7,5)="Techo",A7,0)+IF(LEFT(D8,4)="Base",A8,0)+IF(LEFT(D8,4)="Piso",A8,0)+IF(LEFT(D8,5)="Techo",A8,0)+IF(LEFT(D9,4)="Base",A9,0)+IF(LEFT(D9,4)="Piso",A9,0)+IF(LEFT(D9,5)="Techo",A9,0)+IF(LEFT(D10,4)="Base",A10,0)+IF(LEFT(D10,4)="Piso",A10,0)+IF(LEFT(D10,5)="Techo",A10,0)+IF(LEFT(D11,4)="Base",A11,0)+IF(LEFT(D11,4)="Piso",A11,0)+IF(LEFT(D11,5)="Techo",A11,0)+IF(LEFT(D12,4)="Base",A12,0)+IF(LEFT(D12,4)="Piso",A12,0)+IF(LEFT(D12,5)="Techo",A12,0)+IF(LEFT(D13,4)="Base",A13,0)+IF(LEFT(D13,4)="Piso",A13,0)+IF(LEFT(D13,5)="Techo",A13,0)+IF(LEFT(D14,4)="Base",A14,0)+IF(LEFT(D14,4)="Piso",A14,0)+IF(LEFT(D14,5)="Techo",A14,0)+IF(LEFT(D15,4)="Base",A15,0)+IF(LEFT(D15,4)="Piso",A15,0)+IF(LEFT(D15,5)="Techo",A15,0))+10*(IF(LEFT(D3,8)="Respaldo",A3,0)+IF(LEFT(D4,8)="Respaldo",A4,0)+IF(LEFT(D5,8)="Respaldo",A5,0)+IF(LEFT(D6,8)="Respaldo",A6,0)+IF(LEFT(D7,8)="Respaldo",A7,0)+IF(LEFT(D8,8)="Respaldo",A8,0)+IF(LEFT(D9,8)="Respaldo",A9,0)+IF(LEFT(D10,8)="Respaldo",A10,0)+IF(LEFT(D11,8)="Respaldo",A11,0)+IF(LEFT(D12,8)="Respaldo",A12,0)+IF(LEFT(D13,8)="Respaldo",A13,0)+IF(LEFT(D14,8)="Respaldo",A14,0)+IF(LEFT(D15,8)="Respaldo",A15,0))+4*(IF(LEFT(D3,8)="Manguete",A3,0)+IF(LEFT(D4,8)="Manguete",A4,0)+IF(LEFT(D5,8)="Manguete",A5,0)+IF(LEFT(D6,8)="Manguete",A6,0)+IF(LEFT(D7,8)="Manguete",A7,0)+IF(LEFT(D8,8)="Manguete",A8,0)+IF(LEFT(D9,8)="Manguete",A9,0)+IF(LEFT(D10,8)="Manguete",A10,0)+IF(LEFT(D11,8)="Manguete",A11,0)+IF(LEFT(D12,8)="Manguete",A12,0)+IF(LEFT(D13,8)="Manguete",A13,0)+IF(LEFT(D14,8)="Manguete",A14,0)+IF(LEFT(D15,8)="Manguete",A15,0)) -> 22 | B20: 0 | C20: 0 | D20: Taquetes de Madera 8x30mm | E20: HERRAJE | F20: 0 | G20: 0 | H20: 0 | I20: 0 | J20: 0 | K20: ALA-RIN-656832 | L20: TAQ-MAD-8X30 | M20: =IF(AND(ISNUMBER(B20),ISNUMBER(C20),B20>0,C20>0),A20*(B20*C20/1000000),0) -> 0 | N20: =IF(AND(ISNUMBER(B20),B20>0),A20*(((G20+H20)*B20+(I20+J20)*C20)/1000),0) -> 0 | O20: =IF(E20="HERRAJE",IFERROR(_xlfn.XLOOKUP(D20,'⚙️ Configuración Costos'!$A$11:$A$20,'⚙️ Configuración Costos'!$B$11:$B$20),""),IFERROR(_xlfn.XLOOKUP(E20,'⚙️ Configuración Costos'!$A$5:$A$6,'⚙️ Configuración Costos'!$B$5:$B$6),"")) -> 1 | P20: =IF(E20="HERRAJE",A20*O20,M20*O20) -> 22 | Q20: =IF(E20="HERRAJE",0,IFERROR(_xlfn.XLOOKUP(E20,'⚙️ Configuración Costos'!$E$5:$E$6,'⚙️ Configuración Costos'!$F$5:$F$6),"")) -> 0 | R20: =N20*Q20 -> 0 | S20: =P20+R20 -> 22 | T20: =IF(K20="","SIN ID MÓDULO",IF(E20="HERRAJE",IF(OR(O20="",O20<=0),"SIN PRECIO HERRAJE","OK"),IF(OR(O20="",O20<=0),"SIN PRECIO MATERIAL",IF(AND(N20>0,OR(Q20="",Q20<=0)),"SIN PRECIO CINTILLA","OK")))) -> OK | U20: =IF(T20="OK","",IF(T20="SIN PRECIO HERRAJE","Capturar precio: "&D20,IF(T20="SIN PRECIO MATERIAL","Configurar material: "&E20,IF(T20="SIN PRECIO CINTILLA","Configurar cintilla: "&E20,IF(T20="SIN ID MÓDULO","Revisar ID del módulo",""))))) | V20: =IF(T20="OK",0,IF(T20="",0,1)) -> 0
A21: TOTALES | M21: =SUM(M3:M20) -> 1.96792 | N21: =SUM(N3:N20) -> 13.479 | P21: =SUM(P3:P20) -> 794.02701 | R21: =SUM(R3:R20) -> 128.0505 | S21: =SUM(S3:S20) -> 922.07751
A22: Alacena 1 Puerta 300 x 680 x 320 mm
A23: 1 | B23: 680 | C23: 320 | D23: Lateral Derecho | E23: VESTO NOUGAT | F23: 1 | G23: 1 | H23: 1 | I23: 1 | J23: 1 | K23: ALA-1PU-306832 | L23: LAT-ALA-6832-D | M23: =IF(AND(ISNUMBER(B23),ISNUMBER(C23),B23>0,C23>0),A23*(B23*C23/1000000),0) -> 0.2176 | N23: =IF(AND(ISNUMBER(B23),B23>0),A23*(((G23+H23)*B23+(I23+J23)*C23)/1000),0) -> 2 | O23: =IF(E23="HERRAJE",IFERROR(_xlfn.XLOOKUP(D23,'⚙️ Configuración Costos'!$A$11:$A$20,'⚙️ Configuración Costos'!$B$11:$B$20),""),IFERROR(_xlfn.XLOOKUP(E23,'⚙️ Configuración Costos'!$A$5:$A$6,'⚙️ Configuración Costos'!$B$5:$B$6),"")) -> 332.85246 | P23: =IF(E23="HERRAJE",A23*O23,M23*O23) -> 72.428695 | Q23: =IF(E23="HERRAJE",0,IFERROR(_xlfn.XLOOKUP(E23,'⚙️ Configuración Costos'!$E$5:$E$6,'⚙️ Configuración Costos'!$F$5:$F$6),"")) -> 9.5 | R23: =N23*Q23 -> 19 | S23: =P23+R23 -> 91.428695 | T23: =IF(K23="","SIN ID MÓDULO",IF(E23="HERRAJE",IF(OR(O23="",O23<=0),"SIN PRECIO HERRAJE","OK"),IF(OR(O23="",O23<=0),"SIN PRECIO MATERIAL",IF(AND(N23>0,OR(Q23="",Q23<=0)),"SIN PRECIO CINTILLA","OK")))) -> OK | U23: =IF(T23="OK","",IF(T23="SIN PRECIO HERRAJE","Capturar precio: "&D23,IF(T23="SIN PRECIO MATERIAL","Configurar material: "&E23,IF(T23="SIN PRECIO CINTILLA","Configurar cintilla: "&E23,IF(T23="SIN ID MÓDULO","Revisar ID del módulo",""))))) | V23: =IF(T23="OK",0,IF(T23="",0,1)) -> 0
A24: 1 | B24: 680 | C24: 320 | D24: Lateral Izquierdo | E24: VESTO NOUGAT | F24: 1 | G24: 1 | H24: 1 | I24: 1 | J24: 1 | K24: ALA-1PU-306832 | L24: LAT-ALA-6832-I | M24: =IF(AND(ISNUMBER(B24),ISNUMBER(C24),B24>0,C24>0),A24*(B24*C24/1000000),0) -> 0.2176 | N24: =IF(AND(ISNUMBER(B24),B24>0),A24*(((G24+H24)*B24+(I24+J24)*C24)/1000),0) -> 2 | O24: =IF(E24="HERRAJE",IFERROR(_xlfn.XLOOKUP(D24,'⚙️ Configuración Costos'!$A$11:$A$20,'⚙️ Configuración Costos'!$B$11:$B$20),""),IFERROR(_xlfn.XLOOKUP(E24,'⚙️ Configuración Costos'!$A$5:$A$6,'⚙️ Configuración Costos'!$B$5:$B$6),"")) -> 332.85246 | P24: =IF(E24="HERRAJE",A24*O24,M24*O24) -> 72.428695 | Q24: =IF(E24="HERRAJE",0,IFERROR(_xlfn.XLOOKUP(E24,'⚙️ Configuración Costos'!$E$5:$E$6,'⚙️ Configuración Costos'!$F$5:$F$6),"")) -> 9.5 | R24: =N24*Q24 -> 19 | S24: =P24+R24 -> 91.428695 | T24: =IF(K24="","SIN ID MÓDULO",IF(E24="HERRAJE",IF(OR(O24="",O24<=0),"SIN PRECIO HERRAJE","OK"),IF(OR(O24="",O24<=0),"SIN PRECIO MATERIAL",IF(AND(N24>0,OR(Q24="",Q24<=0)),"SIN PRECIO CINTILLA","OK")))) -> OK | U24: =IF(T24="OK","",IF(T24="SIN PRECIO HERRAJE","Capturar precio: "&D24,IF(T24="SIN PRECIO MATERIAL","Configurar material: "&E24,IF(T24="SIN PRECIO CINTILLA","Configurar cintilla: "&E24,IF(T24="SIN ID MÓDULO","Revisar ID del módulo",""))))) | V24: =IF(T24="OK",0,IF(T24="",0,1)) -> 0
A25: 1 | B25: 649 | C25: 269 | D25: Respaldo Alacena | E25: VESTO NOUGAT | F25: 1 | G25: 0 | H25: 0 | I25: 0 | J25: 0 | K25: ALA-1PU-306832 | L25: RES-ALA-6830 | M25: =IF(AND(ISNUMBER(B25),ISNUMBER(C25),B25>0,C25>0),A25*(B25*C25/1000000),0) -> 0.174581 | N25: =IF(AND(ISNUMBER(B25),B25>0),A25*(((G25+H25)*B25+(I25+J25)*C25)/1000),0) -> 0 | O25: =IF(E25="HERRAJE",IFERROR(_xlfn.XLOOKUP(D25,'⚙️ Configuración Costos'!$A$11:$A$20,'⚙️ Configuración Costos'!$B$11:$B$20),""),IFERROR(_xlfn.XLOOKUP(E25,'⚙️ Configuración Costos'!$A$5:$A$6,'⚙️ Configuración Costos'!$B$5:$B$6),"")) -> 332.85246 | P25: =IF(E25="HERRAJE",A25*O25,M25*O25) -> 58.109715 | Q25: =IF(E25="HERRAJE",0,IFERROR(_xlfn.XLOOKUP(E25,'⚙️ Configuración Costos'!$E$5:$E$6,'⚙️ Configuración Costos'!$F$5:$F$6),"")) -> 9.5 | R25: =N25*Q25 -> 0 | S25: =P25+R25 -> 58.109715 | T25: =IF(K25="","SIN ID MÓDULO",IF(E25="HERRAJE",IF(OR(O25="",O25<=0),"SIN PRECIO HERRAJE","OK"),IF(OR(O25="",O25<=0),"SIN PRECIO MATERIAL",IF(AND(N25>0,OR(Q25="",Q25<=0)),"SIN PRECIO CINTILLA","OK")))) -> OK | U25: =IF(T25="OK","",IF(T25="SIN PRECIO HERRAJE","Capturar precio: "&D25,IF(T25="SIN PRECIO MATERIAL","Configurar material: "&E25,IF(T25="SIN PRECIO CINTILLA","Configurar cintilla: "&E25,IF(T25="SIN ID MÓDULO","Revisar ID del módulo",""))))) | V25: =IF(T25="OK",0,IF(T25="",0,1)) -> 0
A26: 1 | B26: 269 | C26: 300 | D26: Base Alacena | E26: VESTO NOUGAT | F26: 1 | G26: 0 | H26: 0 | I26: 1 | J26: 1 | K26: ALA-1PU-306832 | L26: BAS-ALA-3027 | M26: =IF(AND(ISNUMBER(B26),ISNUMBER(C26),B26>0,C26>0),A26*(B26*C26/1000000),0) -> 0.0807 | N26: =IF(AND(ISNUMBER(B26),B26>0),A26*(((G26+H26)*B26+(I26+J26)*C26)/1000),0) -> 0.6 | O26: =IF(E26="HERRAJE",IFERROR(_xlfn.XLOOKUP(D26,'⚙️ Configuración Costos'!$A$11:$A$20,'⚙️ Configuración Costos'!$B$11:$B$20),""),IFERROR(_xlfn.XLOOKUP(E26,'⚙️ Configuración Costos'!$A$5:$A$6,'⚙️ Configuración Costos'!$B$5:$B$6),"")) -> 332.85246 | P26: =IF(E26="HERRAJE",A26*O26,M26*O26) -> 26.861193 | Q26: =IF(E26="HERRAJE",0,IFERROR(_xlfn.XLOOKUP(E26,'⚙️ Configuración Costos'!$E$5:$E$6,'⚙️ Configuración Costos'!$F$5:$F$6),"")) -> 9.5 | R26: =N26*Q26 -> 5.7 | S26: =P26+R26 -> 32.561193 | T26: =IF(K26="","SIN ID MÓDULO",IF(E26="HERRAJE",IF(OR(O26="",O26<=0),"SIN PRECIO HERRAJE","OK"),IF(OR(O26="",O26<=0),"SIN PRECIO MATERIAL",IF(AND(N26>0,OR(Q26="",Q26<=0)),"SIN PRECIO CINTILLA","OK")))) -> OK | U26: =IF(T26="OK","",IF(T26="SIN PRECIO HERRAJE","Capturar precio: "&D26,IF(T26="SIN PRECIO MATERIAL","Configurar material: "&E26,IF(T26="SIN PRECIO CINTILLA","Configurar cintilla: "&E26,IF(T26="SIN ID MÓDULO","Revisar ID del módulo",""))))) | V26: =IF(T26="OK",0,IF(T26="",0,1)) -> 0
A27: 1 | B27: 269 | C27: 300 | D27: Techo Alacena | E27: VESTO NOUGAT | F27: 1 | G27: 0 | H27: 0 | I27: 1 | J27: 1 | K27: ALA-1PU-306832 | L27: TEC-ALA-3027 | M27: =IF(AND(ISNUMBER(B27),ISNUMBER(C27),B27>0,C27>0),A27*(B27*C27/1000000),0) -> 0.0807 | N27: =IF(AND(ISNUMBER(B27),B27>0),A27*(((G27+H27)*B27+(I27+J27)*C27)/1000),0) -> 0.6 | O27: =IF(E27="HERRAJE",IFERROR(_xlfn.XLOOKUP(D27,'⚙️ Configuración Costos'!$A$11:$A$20,'⚙️ Configuración Costos'!$B$11:$B$20),""),IFERROR(_xlfn.XLOOKUP(E27,'⚙️ Configuración Costos'!$A$5:$A$6,'⚙️ Configuración Costos'!$B$5:$B$6),"")) -> 332.85246 | P27: =IF(E27="HERRAJE",A27*O27,M27*O27) -> 26.861193 | Q27: =IF(E27="HERRAJE",0,IFERROR(_xlfn.XLOOKUP(E27,'⚙️ Configuración Costos'!$E$5:$E$6,'⚙️ Configuración Costos'!$F$5:$F$6),"")) -> 9.5 | R27: =N27*Q27 -> 5.7 | S27: =P27+R27 -> 32.561193 | T27: =IF(K27="","SIN ID MÓDULO",IF(E27="HERRAJE",IF(OR(O27="",O27<=0),"SIN PRECIO HERRAJE","OK"),IF(OR(O27="",O27<=0),"SIN PRECIO MATERIAL",IF(AND(N27>0,OR(Q27="",Q27<=0)),"SIN PRECIO CINTILLA","OK")))) -> OK | U27: =IF(T27="OK","",IF(T27="SIN PRECIO HERRAJE","Capturar precio: "&D27,IF(T27="SIN PRECIO MATERIAL","Configurar material: "&E27,IF(T27="SIN PRECIO CINTILLA","Configurar cintilla: "&E27,IF(T27="SIN ID MÓDULO","Revisar ID del módulo",""))))) | V27: =IF(T27="OK",0,IF(T27="",0,1)) -> 0
A28: 1 | B28: 269 | C28: 256 | D28: Entrepaño Alacena | E28: VESTO NOUGAT | F28: 1 | G28: 1 | H28: 1 | I28: 0 | J28: 0 | K28: ALA-1PU-306832 | L28: ENT-ALA-3026 | M28: =IF(AND(ISNUMBER(B28),ISNUMBER(C28),B28>0,C28>0),A28*(B28*C28/1000000),0) -> 0.068864 | N28: =IF(AND(ISNUMBER(B28),B28>0),A28*(((G28+H28)*B28+(I28+J28)*C28)/1000),0) -> 0.538 | O28: =IF(E28="HERRAJE",IFERROR(_xlfn.XLOOKUP(D28,'⚙️ Configuración Costos'!$A$11:$A$20,'⚙️ Configuración Costos'!$B$11:$B$20),""),IFERROR(_xlfn.XLOOKUP(E28,'⚙️ Configuración Costos'!$A$5:$A$6,'⚙️ Configuración Costos'!$B$5:$B$6),"")) -> 332.85246 | P28: =IF(E28="HERRAJE",A28*O28,M28*O28) -> 22.921552 | Q28: =IF(E28="HERRAJE",0,IFERROR(_xlfn.XLOOKUP(E28,'⚙️ Configuración Costos'!$E$5:$E$6,'⚙️ Configuración Costos'!$F$5:$F$6),"")) -> 9.5 | R28: =N28*Q28 -> 5.111 | S28: =P28+R28 -> 28.032552 | T28: =IF(K28="","SIN ID MÓDULO",IF(E28="HERRAJE",IF(OR(O28="",O28<=0),"SIN PRECIO HERRAJE","OK"),IF(OR(O28="",O28<=0),"SIN PRECIO MATERIAL",IF(AND(N28>0,OR(Q28="",Q28<=0)),"SIN PRECIO CINTILLA","OK")))) -> OK | U28: =IF(T28="OK","",IF(T28="SIN PRECIO HERRAJE","Capturar precio: "&D28,IF(T28="SIN PRECIO MATERIAL","Configurar material: "&E28,IF(T28="SIN PRECIO CINTILLA","Configurar cintilla: "&E28,IF(T28="SIN ID MÓDULO","Revisar ID del módulo",""))))) | V28: =IF(T28="OK",0,IF(T28="",0,1)) -> 0
A29: 1 | B29: 677 | C29: 297 | D29: Puerta Alacena | E29: VESTO NOUGAT | F29: 1 | G29: 1 | H29: 1 | I29: 1 | J29: 1 | K29: ALA-1PU-306832 | L29: PUE-ALA-6830 | M29: =IF(AND(ISNUMBER(B29),ISNUMBER(C29),B29>0,C29>0),A29*(B29*C29/1000000),0) -> 0.201069 | N29: =IF(AND(ISNUMBER(B29),B29>0),A29*(((G29+H29)*B29+(I29+J29)*C29)/1000),0) -> 1.948 | O29: =IF(E29="HERRAJE",IFERROR(_xlfn.XLOOKUP(D29,'⚙️ Configuración Costos'!$A$11:$A$20,'⚙️ Configuración Costos'!$B$11:$B$20),""),IFERROR(_xlfn.XLOOKUP(E29,'⚙️ Configuración Costos'!$A$5:$A$6,'⚙️ Configuración Costos'!$B$5:$B$6),"")) -> 332.85246 | P29: =IF(E29="HERRAJE",A29*O29,M29*O29) -> 66.926311 | Q29: =IF(E29="HERRAJE",0,IFERROR(_xlfn.XLOOKUP(E29,'⚙️ Configuración Costos'!$E$5:$E$6,'⚙️ Configuración Costos'!$F$5:$F$6),"")) -> 9.5 | R29: =N29*Q29 -> 18.506 | S29: =P29+R29 -> 85.432311 | T29: =IF(K29="","SIN ID MÓDULO",IF(E29="HERRAJE",IF(OR(O29="",O29<=0),"SIN PRECIO HERRAJE","OK"),IF(OR(O29="",O29<=0),"SIN PRECIO MATERIAL",IF(AND(N29>0,OR(Q29="",Q29<=0)),"SIN PRECIO CINTILLA","OK")))) -> OK | U29: =IF(T29="OK","",IF(T29="SIN PRECIO HERRAJE","Capturar precio: "&D29,IF(T29="SIN PRECIO MATERIAL","Configurar material: "&E29,IF(T29="SIN PRECIO CINTILLA","Configurar cintilla: "&E29,IF(T29="SIN ID MÓDULO","Revisar ID del módulo",""))))) | V29: =IF(T29="OK",0,IF(T29="",0,1)) -> 0
A30: 2 | B30: 0 | C30: 0 | D30: Bisagra Cierre Lento | E30: HERRAJE | F30: 0 | G30: 0 | H30: 0 | I30: 0 | J30: 0 | K30: ALA-1PU-306832 | L30: BIS-CL | M30: =IF(AND(ISNUMBER(B30),ISNUMBER(C30),B30>0,C30>0),A30*(B30*C30/1000000),0) -> 0 | N30: =IF(AND(ISNUMBER(B30),B30>0),A30*(((G30+H30)*B30+(I30+J30)*C30)/1000),0) -> 0 | O30: =IF(E30="HERRAJE",IFERROR(_xlfn.XLOOKUP(D30,'⚙️ Configuración Costos'!$A$11:$A$20,'⚙️ Configuración Costos'!$B$11:$B$20),""),IFERROR(_xlfn.XLOOKUP(E30,'⚙️ Configuración Costos'!$A$5:$A$6,'⚙️ Configuración Costos'!$B$5:$B$6),"")) -> 20 | P30: =IF(E30="HERRAJE",A30*O30,M30*O30) -> 40 | Q30: =IF(E30="HERRAJE",0,IFERROR(_xlfn.XLOOKUP(E30,'⚙️ Configuración Costos'!$E$5:$E$6,'⚙️ Configuración Costos'!$F$5:$F$6),"")) -> 0 | R30: =N30*Q30 -> 0 | S30: =P30+R30 -> 40 | T30: =IF(K30="","SIN ID MÓDULO",IF(E30="HERRAJE",IF(OR(O30="",O30<=0),"SIN PRECIO HERRAJE","OK"),IF(OR(O30="",O30<=0),"SIN PRECIO MATERIAL",IF(AND(N30>0,OR(Q30="",Q30<=0)),"SIN PRECIO CINTILLA","OK")))) -> OK | U30: =IF(T30="OK","",IF(T30="SIN PRECIO HERRAJE","Capturar precio: "&D30,IF(T30="SIN PRECIO MATERIAL","Configurar material: "&E30,IF(T30="SIN PRECIO CINTILLA","Configurar cintilla: "&E30,IF(T30="SIN ID MÓDULO","Revisar ID del módulo",""))))) | V30: =IF(T30="OK",0,IF(T30="",0,1)) -> 0
A31: 1 | B31: 0 | C31: 0 | D31: Jaladera Acero Inox | E31: HERRAJE | F31: 0 | G31: 0 | H31: 0 | I31: 0 | J31: 0 | K31: ALA-1PU-306832 | L31: JAL-INOX | M31: =IF(AND(ISNUMBER(B31),ISNUMBER(C31),B31>0,C31>0),A31*(B31*C31/1000000),0) -> 0 | N31: =IF(AND(ISNUMBER(B31),B31>0),A31*(((G31+H31)*B31+(I31+J31)*C31)/1000),0) -> 0 | O31: =IF(E31="HERRAJE",IFERROR(_xlfn.XLOOKUP(D31,'⚙️ Configuración Costos'!$A$11:$A$20,'⚙️ Configuración Costos'!$B$11:$B$20),""),IFERROR(_xlfn.XLOOKUP(E31,'⚙️ Configuración Costos'!$A$5:$A$6,'⚙️ Configuración Costos'!$B$5:$B$6),"")) -> 15 | P31: =IF(E31="HERRAJE",A31*O31,M31*O31) -> 15 | Q31: =IF(E31="HERRAJE",0,IFERROR(_xlfn.XLOOKUP(E31,'⚙️ Configuración Costos'!$E$5:$E$6,'⚙️ Configuración Costos'!$F$5:$F$6),"")) -> 0 | R31: =N31*Q31 -> 0 | S31: =P31+R31 -> 15 | T31: =IF(K31="","SIN ID MÓDULO",IF(E31="HERRAJE",IF(OR(O31="",O31<=0),"SIN PRECIO HERRAJE","OK"),IF(OR(O31="",O31<=0),"SIN PRECIO MATERIAL",IF(AND(N31>0,OR(Q31="",Q31<=0)),"SIN PRECIO CINTILLA","OK")))) -> OK | U31: =IF(T31="OK","",IF(T31="SIN PRECIO HERRAJE","Capturar precio: "&D31,IF(T31="SIN PRECIO MATERIAL","Configurar material: "&E31,IF(T31="SIN PRECIO CINTILLA","Configurar cintilla: "&E31,IF(T31="SIN ID MÓDULO","Revisar ID del módulo",""))))) | V31: =IF(T31="OK",0,IF(T31="",0,1)) -> 0
A32: 4 | B32: 0 | C32: 0 | D32: Soporte de Entrepaño | E32: HERRAJE | F32: 0 | G32: 0 | H32: 0 | I32: 0 | J32: 0 | K32: ALA-1PU-306832 | L32: SOP-ENT | M32: =IF(AND(ISNUMBER(B32),ISNUMBER(C32),B32>0,C32>0),A32*(B32*C32/1000000),0) -> 0 | N32: =IF(AND(ISNUMBER(B32),B32>0),A32*(((G32+H32)*B32+(I32+J32)*C32)/1000),0) -> 0 | O32: =IF(E32="HERRAJE",IFERROR(_xlfn.XLOOKUP(D32,'⚙️ Configuración Costos'!$A$11:$A$20,'⚙️ Configuración Costos'!$B$11:$B$20),""),IFERROR(_xlfn.XLOOKUP(E32,'⚙️ Configuración Costos'!$A$5:$A$6,'⚙️ Configuración Costos'!$B$5:$B$6),"")) -> 2 | P32: =IF(E32="HERRAJE",A32*O32,M32*O32) -> 8 | Q32: =IF(E32="HERRAJE",0,IFERROR(_xlfn.XLOOKUP(E32,'⚙️ Configuración Costos'!$E$5:$E$6,'⚙️ Configuración Costos'!$F$5:$F$6),"")) -> 0 | R32: =N32*Q32 -> 0 | S32: =P32+R32 -> 8 | T32: =IF(K32="","SIN ID MÓDULO",IF(E32="HERRAJE",IF(OR(O32="",O32<=0),"SIN PRECIO HERRAJE","OK"),IF(OR(O32="",O32<=0),"SIN PRECIO MATERIAL",IF(AND(N32>0,OR(Q32="",Q32<=0)),"SIN PRECIO CINTILLA","OK")))) -> OK | U32: =IF(T32="OK","",IF(T32="SIN PRECIO HERRAJE","Capturar precio: "&D32,IF(T32="SIN PRECIO MATERIAL","Configurar material: "&E32,IF(T32="SIN PRECIO CINTILLA","Configurar cintilla: "&E32,IF(T32="SIN ID MÓDULO","Revisar ID del módulo",""))))) | V32: =IF(T32="OK",0,IF(T32="",0,1)) -> 0
A33: =4*(IF(LEFT(D23,4)="Base",A23,0)+IF(LEFT(D23,4)="Piso",A23,0)+IF(LEFT(D23,5)="Techo",A23,0)+IF(LEFT(D24,4)="Base",A24,0)+IF(LEFT(D24,4)="Piso",A24,0)+IF(LEFT(D24,5)="Techo",A24,0)+IF(LEFT(D25,4)="Base",A25,0)+IF(LEFT(D25,4)="Piso",A25,0)+IF(LEFT(D25,5)="Techo",A25,0)+IF(LEFT(D26,4)="Base",A26,0)+IF(LEFT(D26,4)="Piso",A26,0)+IF(LEFT(D26,5)="Techo",A26,0)+IF(LEFT(D27,4)="Base",A27,0)+IF(LEFT(D27,4)="Piso",A27,0)+IF(LEFT(D27,5)="Techo",A27,0)+IF(LEFT(D28,4)="Base",A28,0)+IF(LEFT(D28,4)="Piso",A28,0)+IF(LEFT(D28,5)="Techo",A28,0)+IF(LEFT(D29,4)="Base",A29,0)+IF(LEFT(D29,4)="Piso",A29,0)+IF(LEFT(D29,5)="Techo",A29,0))+10*(IF(LEFT(D23,8)="Respaldo",A23,0)+IF(LEFT(D24,8)="Respaldo",A24,0)+IF(LEFT(D25,8)="Respaldo",A25,0)+IF(LEFT(D26,8)="Respaldo",A26,0)+IF(LEFT(D27,8)="Respaldo",A27,0)+IF(LEFT(D28,8)="Respaldo",A28,0)+IF(LEFT(D29,8)="Respaldo",A29,0))+2*(IF(LEFT(D23,8)="Manguete",A23,0)+IF(LEFT(D24,8)="Manguete",A24,0)+IF(LEFT(D25,8)="Manguete",A25,0)+IF(LEFT(D26,8)="Manguete",A26,0)+IF(LEFT(D27,8)="Manguete",A27,0)+IF(LEFT(D28,8)="Manguete",A28,0)+IF(LEFT(D29,8)="Manguete",A29,0)) -> 18 | B33: 0 | C33: 0 | D33: Kit Minifixx 15mm | E33: HERRAJE | F33: 0 | G33: 0 | H33: 0 | I33: 0 | J33: 0 | K33: ALA-1PU-306832 | L33: KIT-MIN-15 | M33: =IF(AND(ISNUMBER(B33),ISNUMBER(C33),B33>0,C33>0),A33*(B33*C33/1000000),0) -> 0 | N33: =IF(AND(ISNUMBER(B33),B33>0),A33*(((G33+H33)*B33+(I33+J33)*C33)/1000),0) -> 0 | O33: =IF(E33="HERRAJE",IFERROR(_xlfn.XLOOKUP(D33,'⚙️ Configuración Costos'!$A$11:$A$20,'⚙️ Configuración Costos'!$B$11:$B$20),""),IFERROR(_xlfn.XLOOKUP(E33,'⚙️ Configuración Costos'!$A$5:$A$6,'⚙️ Configuración Costos'!$B$5:$B$6),"")) -> 3 | P33: =IF(E33="HERRAJE",A33*O33,M33*O33) -> 54 | Q33: =IF(E33="HERRAJE",0,IFERROR(_xlfn.XLOOKUP(E33,'⚙️ Configuración Costos'!$E$5:$E$6,'⚙️ Configuración Costos'!$F$5:$F$6),"")) -> 0 | R33: =N33*Q33 -> 0 | S33: =P33+R33 -> 54 | T33: =IF(K33="","SIN ID MÓDULO",IF(E33="HERRAJE",IF(OR(O33="",O33<=0),"SIN PRECIO HERRAJE","OK"),IF(OR(O33="",O33<=0),"SIN PRECIO MATERIAL",IF(AND(N33>0,OR(Q33="",Q33<=0)),"SIN PRECIO CINTILLA","OK")))) -> OK | U33: =IF(T33="OK","",IF(T33="SIN PRECIO HERRAJE","Capturar precio: "&D33,IF(T33="SIN PRECIO MATERIAL","Configurar material: "&E33,IF(T33="SIN PRECIO CINTILLA","Configurar cintilla: "&E33,IF(T33="SIN ID MÓDULO","Revisar ID del módulo",""))))) | V33: =IF(T33="OK",0,IF(T33="",0,1)) -> 0
A34: =6*(IF(LEFT(D23,4)="Base",A23,0)+IF(LEFT(D23,4)="Piso",A23,0)+IF(LEFT(D23,5)="Techo",A23,0)+IF(LEFT(D24,4)="Base",A24,0)+IF(LEFT(D24,4)="Piso",A24,0)+IF(LEFT(D24,5)="Techo",A24,0)+IF(LEFT(D25,4)="Base",A25,0)+IF(LEFT(D25,4)="Piso",A25,0)+IF(LEFT(D25,5)="Techo",A25,0)+IF(LEFT(D26,4)="Base",A26,0)+IF(LEFT(D26,4)="Piso",A26,0)+IF(LEFT(D26,5)="Techo",A26,0)+IF(LEFT(D27,4)="Base",A27,0)+IF(LEFT(D27,4)="Piso",A27,0)+IF(LEFT(D27,5)="Techo",A27,0)+IF(LEFT(D28,4)="Base",A28,0)+IF(LEFT(D28,4)="Piso",A28,0)+IF(LEFT(D28,5)="Techo",A28,0)+IF(LEFT(D29,4)="Base",A29,0)+IF(LEFT(D29,4)="Piso",A29,0)+IF(LEFT(D29,5)="Techo",A29,0))+10*(IF(LEFT(D23,8)="Respaldo",A23,0)+IF(LEFT(D24,8)="Respaldo",A24,0)+IF(LEFT(D25,8)="Respaldo",A25,0)+IF(LEFT(D26,8)="Respaldo",A26,0)+IF(LEFT(D27,8)="Respaldo",A27,0)+IF(LEFT(D28,8)="Respaldo",A28,0)+IF(LEFT(D29,8)="Respaldo",A29,0))+4*(IF(LEFT(D23,8)="Manguete",A23,0)+IF(LEFT(D24,8)="Manguete",A24,0)+IF(LEFT(D25,8)="Manguete",A25,0)+IF(LEFT(D26,8)="Manguete",A26,0)+IF(LEFT(D27,8)="Manguete",A27,0)+IF(LEFT(D28,8)="Manguete",A28,0)+IF(LEFT(D29,8)="Manguete",A29,0)) -> 22 | B34: 0 | C34: 0 | D34: Taquetes de Madera 8x30mm | E34: HERRAJE | F34: 0 | G34: 0 | H34: 0 | I34: 0 | J34: 0 | K34: ALA-1PU-306832 | L34: TAQ-MAD-8X30 | M34: =IF(AND(ISNUMBER(B34),ISNUMBER(C34),B34>0,C34>0),A34*(B34*C34/1000000),0) -> 0 | N34: =IF(AND(ISNUMBER(B34),B34>0),A34*(((G34+H34)*B34+(I34+J34)*C34)/1000),0) -> 0 | O34: =IF(E34="HERRAJE",IFERROR(_xlfn.XLOOKUP(D34,'⚙️ Configuración Costos'!$A$11:$A$20,'⚙️ Configuración Costos'!$B$11:$B$20),""),IFERROR(_xlfn.XLOOKUP(E34,'⚙️ Configuración Costos'!$A$5:$A$6,'⚙️ Configuración Costos'!$B$5:$B$6),"")) -> 1 | P34: =IF(E34="HERRAJE",A34*O34,M34*O34) -> 22 | Q34: =IF(E34="HERRAJE",0,IFERROR(_xlfn.XLOOKUP(E34,'⚙️ Configuración Costos'!$E$5:$E$6,'⚙️ Configuración Costos'!$F$5:$F$6),"")) -> 0 | R34: =N34*Q34 -> 0 | S34: =P34+R34 -> 22 | T34: =IF(K34="","SIN ID MÓDULO",IF(E34="HERRAJE",IF(OR(O34="",O34<=0),"SIN PRECIO HERRAJE","OK"),IF(OR(O34="",O34<=0),"SIN PRECIO MATERIAL",IF(AND(N34>0,OR(Q34="",Q34<=0)),"SIN PRECIO CINTILLA","OK")))) -> OK | U34: =IF(T34="OK","",IF(T34="SIN PRECIO HERRAJE","Capturar precio: "&D34,IF(T34="SIN PRECIO MATERIAL","Configurar material: "&E34,IF(T34="SIN PRECIO CINTILLA","Configurar cintilla: "&E34,IF(T34="SIN ID MÓDULO","Revisar ID del módulo",""))))) | V34: =IF(T34="OK",0,IF(T34="",0,1)) -> 0
A35: TOTALES | M35: =SUM(M23:M34) -> 1.041114 | N35: =SUM(N23:N34) -> 7.686 | P35: =SUM(P23:P34) -> 485.53736 | R35: =SUM(R23:R34) -> 73.017 | S35: =SUM(S23:S34) -> 558.55436
A36: Alacena 1 Puerta 400 x 680 x 320 mm
A37: 1 | B37: 680 | C37: 320 | D37: Lateral Derecho | E37: VESTO NOUGAT | F37: 1 | G37: 1 | H37: 1 | I37: 1 | J37: 1 | K37: ALA-1PU-406832 | L37: LAT-ALA-6832-D | M37: =IF(AND(ISNUMBER(B37),ISNUMBER(C37),B37>0,C37>0),A37*(B37*C37/1000000),0) -> 0.2176 | N37: =IF(AND(ISNUMBER(B37),B37>0),A37*(((G37+H37)*B37+(I37+J37)*C37)/1000),0) -> 2 | O37: =IF(E37="HERRAJE",IFERROR(_xlfn.XLOOKUP(D37,'⚙️ Configuración Costos'!$A$11:$A$20,'⚙️ Configuración Costos'!$B$11:$B$20),""),IFERROR(_xlfn.XLOOKUP(E37,'⚙️ Configuración Costos'!$A$5:$A$6,'⚙️ Configuración Costos'!$B$5:$B$6),"")) -> 332.85246 | P37: =IF(E37="HERRAJE",A37*O37,M37*O37) -> 72.428695 | Q37: =IF(E37="HERRAJE",0,IFERROR(_xlfn.XLOOKUP(E37,'⚙️ Configuración Costos'!$E$5:$E$6,'⚙️ Configuración Costos'!$F$5:$F$6),"")) -> 9.5 | R37: =N37*Q37 -> 19 | S37: =P37+R37 -> 91.428695 | T37: =IF(K37="","SIN ID MÓDULO",IF(E37="HERRAJE",IF(OR(O37="",O37<=0),"SIN PRECIO HERRAJE","OK"),IF(OR(O37="",O37<=0),"SIN PRECIO MATERIAL",IF(AND(N37>0,OR(Q37="",Q37<=0)),"SIN PRECIO CINTILLA","OK")))) -> OK | U37: =IF(T37="OK","",IF(T37="SIN PRECIO HERRAJE","Capturar precio: "&D37,IF(T37="SIN PRECIO MATERIAL","Configurar material: "&E37,IF(T37="SIN PRECIO CINTILLA","Configurar cintilla: "&E37,IF(T37="SIN ID MÓDULO","Revisar ID del módulo",""))))) | V37: =IF(T37="OK",0,IF(T37="",0,1)) -> 0
A38: 1 | B38: 680 | C38: 320 | D38: Lateral Izquierdo | E38: VESTO NOUGAT | F38: 1 | G38: 1 | H38: 1 | I38: 1 | J38: 1 | K38: ALA-1PU-406832 | L38: LAT-ALA-6832-I | M38: =IF(AND(ISNUMBER(B38),ISNUMBER(C38),B38>0,C38>0),A38*(B38*C38/1000000),0) -> 0.2176 | N38: =IF(AND(ISNUMBER(B38),B38>0),A38*(((G38+H38)*B38+(I38+J38)*C38)/1000),0) -> 2 | O38: =IF(E38="HERRAJE",IFERROR(_xlfn.XLOOKUP(D38,'⚙️ Configuración Costos'!$A$11:$A$20,'⚙️ Configuración Costos'!$B$11:$B$20),""),IFERROR(_xlfn.XLOOKUP(E38,'⚙️ Configuración Costos'!$A$5:$A$6,'⚙️ Configuración Costos'!$B$5:$B$6),"")) -> 332.85246 | P38: =IF(E38="HERRAJE",A38*O38,M38*O38) -> 72.428695 | Q38: =IF(E38="HERRAJE",0,IFERROR(_xlfn.XLOOKUP(E38,'⚙️ Configuración Costos'!$E$5:$E$6,'⚙️ Configuración Costos'!$F$5:$F$6),"")) -> 9.5 | R38: =N38*Q38 -> 19 | S38: =P38+R38 -> 91.428695 | T38: =IF(K38="","SIN ID MÓDULO",IF(E38="HERRAJE",IF(OR(O38="",O38<=0),"SIN PRECIO HERRAJE","OK"),IF(OR(O38="",O38<=0),"SIN PRECIO MATERIAL",IF(AND(N38>0,OR(Q38="",Q38<=0)),"SIN PRECIO CINTILLA","OK")))) -> OK | U38: =IF(T38="OK","",IF(T38="SIN PRECIO HERRAJE","Capturar precio: "&D38,IF(T38="SIN PRECIO MATERIAL","Configurar material: "&E38,IF(T38="SIN PRECIO CINTILLA","Configurar cintilla: "&E38,IF(T38="SIN ID MÓDULO","Revisar ID del módulo",""))))) | V38: =IF(T38="OK",0,IF(T38="",0,1)) -> 0
A39: 1 | B39: 649 | C39: 369 | D39: Respaldo Alacena | E39: VESTO NOUGAT | F39: 1 | G39: 0 | H39: 0 | I39: 0 | J39: 0 | K39: ALA-1PU-406832 | L39: RES-ALA-6840 | M39: =IF(AND(ISNUMBER(B39),ISNUMBER(C39),B39>0,C39>0),A39*(B39*C39/1000000),0) -> 0.239481 | N39: =IF(AND(ISNUMBER(B39),B39>0),A39*(((G39+H39)*B39+(I39+J39)*C39)/1000),0) -> 0 | O39: =IF(E39="HERRAJE",IFERROR(_xlfn.XLOOKUP(D39,'⚙️ Configuración Costos'!$A$11:$A$20,'⚙️ Configuración Costos'!$B$11:$B$20),""),IFERROR(_xlfn.XLOOKUP(E39,'⚙️ Configuración Costos'!$A$5:$A$6,'⚙️ Configuración Costos'!$B$5:$B$6),"")) -> 332.85246 | P39: =IF(E39="HERRAJE",A39*O39,M39*O39) -> 79.71184 | Q39: =IF(E39="HERRAJE",0,IFERROR(_xlfn.XLOOKUP(E39,'⚙️ Configuración Costos'!$E$5:$E$6,'⚙️ Configuración Costos'!$F$5:$F$6),"")) -> 9.5 | R39: =N39*Q39 -> 0 | S39: =P39+R39 -> 79.71184 | T39: =IF(K39="","SIN ID MÓDULO",IF(E39="HERRAJE",IF(OR(O39="",O39<=0),"SIN PRECIO HERRAJE","OK"),IF(OR(O39="",O39<=0),"SIN PRECIO MATERIAL",IF(AND(N39>0,OR(Q39="",Q39<=0)),"SIN PRECIO CINTILLA","OK")))) -> OK | U39: =IF(T39="OK","",IF(T39="SIN PRECIO HERRAJE","Capturar precio: "&D39,IF(T39="SIN PRECIO MATERIAL","Configurar material: "&E39,IF(T39="SIN PRECIO CINTILLA","Configurar cintilla: "&E39,IF(T39="SIN ID MÓDULO","Revisar ID del módulo",""))))) | V39: =IF(T39="OK",0,IF(T39="",0,1)) -> 0
A40: 1 | B40: 369 | C40: 320 | D40: Base Alacena | E40: VESTO NOUGAT | F40: 1 | G40: 1 | H40: 1 | I40: 0 | J40: 0 | K40: ALA-1PU-406832 | L40: BAS-ALA-4032 | M40: =IF(AND(ISNUMBER(B40),ISNUMBER(C40),B40>0,C40>0),A40*(B40*C40/1000000),0) -> 0.11808 | N40: =IF(AND(ISNUMBER(B40),B40>0),A40*(((G40+H40)*B40+(I40+J40)*C40)/1000),0) -> 0.738 | O40: =IF(E40="HERRAJE",IFERROR(_xlfn.XLOOKUP(D40,'⚙️ Configuración Costos'!$A$11:$A$20,'⚙️ Configuración Costos'!$B$11:$B$20),""),IFERROR(_xlfn.XLOOKUP(E40,'⚙️ Configuración Costos'!$A$5:$A$6,'⚙️ Configuración Costos'!$B$5:$B$6),"")) -> 332.85246 | P40: =IF(E40="HERRAJE",A40*O40,M40*O40) -> 39.303218 | Q40: =IF(E40="HERRAJE",0,IFERROR(_xlfn.XLOOKUP(E40,'⚙️ Configuración Costos'!$E$5:$E$6,'⚙️ Configuración Costos'!$F$5:$F$6),"")) -> 9.5 | R40: =N40*Q40 -> 7.011 | S40: =P40+R40 -> 46.314218 | T40: =IF(K40="","SIN ID MÓDULO",IF(E40="HERRAJE",IF(OR(O40="",O40<=0),"SIN PRECIO HERRAJE","OK"),IF(OR(O40="",O40<=0),"SIN PRECIO MATERIAL",IF(AND(N40>0,OR(Q40="",Q40<=0)),"SIN PRECIO CINTILLA","OK")))) -> OK | U40: =IF(T40="OK","",IF(T40="SIN PRECIO HERRAJE","Capturar precio: "&D40,IF(T40="SIN PRECIO MATERIAL","Configurar material: "&E40,IF(T40="SIN PRECIO CINTILLA","Configurar cintilla: "&E40,IF(T40="SIN ID MÓDULO","Revisar ID del módulo",""))))) | V40: =IF(T40="OK",0,IF(T40="",0,1)) -> 0
A41: 1 | B41: 369 | C41: 320 | D41: Techo Alacena | E41: VESTO NOUGAT | F41: 1 | G41: 1 | H41: 1 | I41: 0 | J41: 0 | K41: ALA-1PU-406832 | L41: TEC-ALA-4032 | M41: =IF(AND(ISNUMBER(B41),ISNUMBER(C41),B41>0,C41>0),A41*(B41*C41/1000000),0) -> 0.11808 | N41: =IF(AND(ISNUMBER(B41),B41>0),A41*(((G41+H41)*B41+(I41+J41)*C41)/1000),0) -> 0.738 | O41: =IF(E41="HERRAJE",IFERROR(_xlfn.XLOOKUP(D41,'⚙️ Configuración Costos'!$A$11:$A$20,'⚙️ Configuración Costos'!$B$11:$B$20),""),IFERROR(_xlfn.XLOOKUP(E41,'⚙️ Configuración Costos'!$A$5:$A$6,'⚙️ Configuración Costos'!$B$5:$B$6),"")) -> 332.85246 | P41: =IF(E41="HERRAJE",A41*O41,M41*O41) -> 39.303218 | Q41: =IF(E41="HERRAJE",0,IFERROR(_xlfn.XLOOKUP(E41,'⚙️ Configuración Costos'!$E$5:$E$6,'⚙️ Configuración Costos'!$F$5:$F$6),"")) -> 9.5 | R41: =N41*Q41 -> 7.011 | S41: =P41+R41 -> 46.314218 | T41: =IF(K41="","SIN ID MÓDULO",IF(E41="HERRAJE",IF(OR(O41="",O41<=0),"SIN PRECIO HERRAJE","OK"),IF(OR(O41="",O41<=0),"SIN PRECIO MATERIAL",IF(AND(N41>0,OR(Q41="",Q41<=0)),"SIN PRECIO CINTILLA","OK")))) -> OK | U41: =IF(T41="OK","",IF(T41="SIN PRECIO HERRAJE","Capturar precio: "&D41,IF(T41="SIN PRECIO MATERIAL","Configurar material: "&E41,IF(T41="SIN PRECIO CINTILLA","Configurar cintilla: "&E41,IF(T41="SIN ID MÓDULO","Revisar ID del módulo",""))))) | V41: =IF(T41="OK",0,IF(T41="",0,1)) -> 0
